Workbook
Name _ftn1: Summary!$I$5
Name _ftn2: Summary!$I$6
Name _ftn3: Summary!$I$7

Sheet Insights
A1: Strategy Insights | S&P 500 Comparison
A2: October 31, 2000–July 31, 2026 | 310 matched monthly observations | J2: Date | K2: S&P 500 Growth | L2: Leveraged Strategy Growth | M2: S&P Peak | N2: S&P Drawdown | O2: Strategy Drawdown
J3: =Summary!A2 -> 36830 | K3: =1+Summary!B2 -> 0.99069493 | L3: =1+Summary!E2 -> 1.0130587 | M3: =K3 -> 0.99069493 | N3: =K3/M3-1 -> 0 | O3: =L3/MAX($L$3:L3)-1 -> 0
A4: STORY IN BRIEF | J4: =Summary!A3 -> 36860 | K4: =K3*(1+Summary!B3) -> 0.90901706 | L4: =L3*(1+Summary!E3) -> 0.99637418 | M4: =MAX($K$3:K4) -> 0.99069493 | N4: =K4/M4-1 -> -0.082445024 | O4: =L4/MAX($L$3:L4)-1 -> -0.016469498
A5: ="The leveraged strategy generated "&TEXT(C11,"0.0%")&" annualized versus "&TEXT(B11,"0.0%")&" for the S&P 500 while running slightly lower volatility. Its maximum drawdown was "&TEXT(C14,"0.0%")&" versus "&TEXT(B14,"0.0%")&", and it lost less on average in the 118 months when the S&P 500 declined. The advantage is economically meaningful, but it depends on a 3.9x leverage assumption and should be stress-tested for costs and implementation constraints." -> The leveraged strategy generated 17.4% annualized versus 7.8% for the S&P 500 while running slightly lower volatility. Its maximum drawdown was -30.0% versus -56.1%, and it lost less on average in the 118 months when the S&P 500 declined. The advantage is economically meaningful, but it depends on a 3.9x leverage assumption and should be stress-tested for costs and implementation constraints. | J5: =Summary!A4 -> 36891 | K5: =K4*(1+Summary!B4) -> 0.90488147 | L5: =L4*(1+Summary!E4) -> 1.0044362 | M5: =MAX($K$3:K5) -> 0.99069493 | N5: =K5/M5-1 -> -0.086619456 | O5: =L5/MAX($L$3:L5)-1 -> -0.0085113672
J6: =Summary!A5 -> 36922 | K6: =K5*(1+Summary!B5) -> 0.93065505 | L6: =L5*(1+Summary!E5) -> 1.0394595 | M6: =MAX($K$3:K6) -> 0.99069493 | N6: =K6/M6-1 -> -0.060603802 | O6: =L6/MAX($L$3:L6)-1 -> 0
J7: =Summary!A6 -> 36950 | K7: =K6*(1+Summary!B6) -> 0.8418876 | L7: =L6*(1+Summary!E6) -> 1.0440065 | M7: =MAX($K$3:K7) -> 0.99069493 | N7: =K7/M7-1 -> -0.15020499 | O7: =L7/MAX($L$3:L7)-1 -> 0
J8: =Summary!A7 -> 36981 | K8: =K7*(1+Summary!B7) -> 0.78428476 | L8: =L7*(1+Summary!E7) -> 1.0713476 | M8: =MAX($K$3:K8) -> 0.99069493 | N8: =K8/M8-1 -> -0.20834886 | O8: =L8/MAX($L$3:L8)-1 -> 0
A9: PERFORMANCE AND RISK SCORECARD | J9: =Summary!A8 -> 37011 | K9: =K8*(1+Summary!B8) -> 0.8412968 | L9: =L8*(1+Summary!E8) -> 1.0821366 | M9: =MAX($K$3:K9) -> 0.99069493 | N9: =K9/M9-1 -> -0.15080134 | O9: =L9/MAX($L$3:L9)-1 -> 0
A10: Metric | B10: S&P 500 | C10: Leveraged Strategy | D10: Strategy Advantage | J10: =Summary!A9 -> 37042 | K10: =K9*(1+Summary!B9) -> 0.84343845 | L10: =L9*(1+Summary!E9) -> 1.0821152 | M10: =MAX($K$3:K10) -> 0.99069493 | N10: =K10/M10-1 -> -0.14863958 | O10: =L10/MAX($L$3:L10)-1 -> -1.973969e-05
A11: Annualized return | B11: =Summary!V5 -> 0.078300905 | C11: =Summary!X5 -> 0.17377247 | D11: =C11-B11 -> 0.095471566 | J11: =Summary!A10 -> 37072 | K11: =K10*(1+Summary!B10) -> 0.81965881 | L11: =L10*(1+Summary!E10) -> 1.083072 | M11: =MAX($K$3:K11) -> 0.99069493 | N11: =K11/M11-1 -> -0.17264256 | O11: =L11/MAX($L$3:L11)-1 -> 0
A12: Annualized volatility | B12: =Summary!V6 -> 0.1528659 | C12: =Summary!X6 -> 0.15020709 | D12: =C12-B12 -> -0.0026588145 | J12: =Summary!A11 -> 37103 | K12: =K11*(1+Summary!B11) -> 0.80872905 | L12: =L11*(1+Summary!E11) -> 1.1009857 | M12: =MAX($K$3:K12) -> 0.99069493 | N12: =K12/M12-1 -> -0.18367499 | O12: =L12/MAX($L$3:L12)-1 -> 0
A13: Sharpe ratio | B13: =Summary!V7 -> 0.38732378 | C13: =Summary!X7 -> 1.0297794 | D13: =C13-B13 -> 0.64245562 | J13: =Summary!A12 -> 37134 | K13: =K12*(1+Summary!B12) -> 0.75533565 | L13: =L12*(1+Summary!E12) -> 1.0660052 | M13: =MAX($K$3:K13) -> 0.99069493 | N13: =K13/M13-1 -> -0.23756988 | O13: =L13/MAX($L$3:L13)-1 -> -0.031771926
A14: Maximum drawdown | B14: =MIN(N3:N312) -> -0.56071562 | C14: =MIN(O3:O312) -> -0.30022448 | D14: =C14-B14 -> 0.26049114 | J14: =Summary!A13 -> 37164 | K14: =K13*(1+Summary!B13) -> 0.67683332 | L14: =L13*(1+Summary!E13) -> 1.0324824 | M14: =MAX($K$3:K14) -> 0.99069493 | N14: =K14/M14-1 -> -0.31680954 | O14: =L14/MAX($L$3:L14)-1 -> -0.062219901
A15: Average return in S&P down months | B15: =AVERAGEIF(Summary!B2:B311,"<0",Summary!B2:B311) -> -0.037328582 | C15: =AVERAGEIF(Summary!B2:B311,"<0",Summary!E2:E311) -> -0.017394788 | D15: =C15-B15 -> 0.019933794 | J15: =Summary!A14 -> 37195 | K15: =K14*(1+Summary!B14) -> 0.68783694 | L15: =L14*(1+Summary!E14) -> 1.0626073 | M15: =MAX($K$3:K15) -> 0.99069493 | N15: =K15/M15-1 -> -0.30570257 | O15: =L15/MAX($L$3:L15)-1 -> -0.034858206
A16: Positive in S&P down months | B16: 0 | C16: =COUNTIFS(Summary!B2:B311,"<0",Summary!E2:E311,">0")/COUNTIF(Summary!B2:B311,"<0") -> 0.33050847 | D16: =C16-B16 -> 0.33050847 | J16: =Summary!A15 -> 37225 | K16: =K15*(1+Summary!B15) -> 0.73923639 | L16: =L15*(1+Summary!E15) -> 1.0686098 | M16: =MAX($K$3:K16) -> 0.99069493 | N16: =K16/M16-1 -> -0.25382035 | O16: =L16/MAX($L$3:L16)-1 -> -0.029406297
A17: Correlation with S&P 500 | B17: 1 | C17: =CORREL(Summary!B2:B311,Summary!E2:E311) -> 0.65003735 | D17: =C17-B17 -> -0.34996265 | J17: =Summary!A16 -> 37256 | K17: =K16*(1+Summary!B16) -> 0.74433203 | L17: =L16*(1+Summary!E16) -> 1.0820576 | M17: =MAX($K$3:K17) -> 0.99069493 | N17: =K17/M17-1 -> -0.24867685 | O17: =L17/MAX($L$3:L17)-1 -> -0.017191927
J18: =Summary!A17 -> 37287 | K18: =K17*(1+Summary!B17) -> 0.73222066 | L18: =L17*(1+Summary!E17) -> 1.07248 | M18: =MAX($K$3:K18) -> 0.99069493 | N18: =K18/M18-1 -> -0.26090198 | O18: =L18/MAX($L$3:L18)-1 -> -0.025891034
A19: THREE MOST IMPORTANT TAKEAWAYS | J19: =Summary!A18 -> 37315 | K19: =K18*(1+Summary!B18) -> 0.71700761 | L19: =L18*(1+Summary!E18) -> 1.1014785 | M19: =MAX($K$3:K19) -> 0.99069493 | N19: =K19/M19-1 -> -0.27625792 | O19: =L19/MAX($L$3:L19)-1 -> 0
A20: ="1 | Return efficiency — The leveraged strategy delivered "&TEXT(C11,"0.0%")&" annualized return at "&TEXT(C12,"0.0%")&" volatility, compared with "&TEXT(B11,"0.0%")&" return and "&TEXT(B12,"0.0%")&" volatility for the S&P 500; its Sharpe ratio was "&TEXT(C13,"0.00")&" versus "&TEXT(B13,"0.00")&"." -> 1 | Return efficiency — The leveraged strategy delivered 17.4% annualized return at 15.0% volatility, compared with 7.8% return and 15.3% volatility for the S&P 500; its Sharpe ratio was 1.03 versus 0.39. | J20: =Summary!A19 -> 37346 | K20: =K19*(1+Summary!B19) -> 0.74263348 | L20: =L19*(1+Summary!E19) -> 1.0910694 | M20: =MAX($K$3:K20) -> 0.99069493 | N20: =K20/M20-1 -> -0.25039135 | O20: =L20/MAX($L$3:L20)-1 -> -0.0094500869
J21: =Summary!A20 -> 37376 | K21: =K20*(1+Summary!B20) -> 0.69610812 | L21: =L20*(1+Summary!E20) -> 1.0860984 | M21: =MAX($K$3:K21) -> 0.99069493 | N21: =K21/M21-1 -> -0.29735371 | O21: =L21/MAX($L$3:L21)-1 -> -0.013963096
A22: ="2 | Drawdown control — Maximum drawdown improved from "&TEXT(B14,"0.0%")&" for the S&P 500 to "&TEXT(C14,"0.0%")&" for the leveraged strategy, a "&TEXT(D14,"0.0%")&" reduction in drawdown depth." -> 2 | Drawdown control — Maximum drawdown improved from -56.1% for the S&P 500 to -30.0% for the leveraged strategy, a 26.0% reduction in drawdown depth. | J22: =Summary!A21 -> 37407 | K22: =K21*(1+Summary!B21) -> 0.68983088 | L22: =L21*(1+Summary!E21) -> 1.1168028 | M22: =MAX($K$3:K22) -> 0.99069493 | N22: =K22/M22-1 -> -0.3036899 | O22: =L22/MAX($L$3:L22)-1 -> 0
J23: =Summary!A22 -> 37437 | K23: =K22*(1+Summary!B22) -> 0.63909608 | L23: =L22*(1+Summary!E22) -> 1.0749342 | M23: =MAX($K$3:K23) -> 0.99069493 | N23: =K23/M23-1 -> -0.35490123 | O23: =L23/MAX($L$3:L23)-1 -> -0.037489675
A24: ="3 | Down-market resilience — Across "&COUNTIF(Summary!B2:B311,"<0")&" negative S&P months, the index averaged "&TEXT(B15,"0.0%")&" while the leveraged strategy averaged "&TEXT(C15,"0.0%")&" and produced a positive return in "&TEXT(C16,"0.0%")&" of those months." -> 3 | Down-market resilience — Across 118 negative S&P months, the index averaged -3.7% while the leveraged strategy averaged -1.7% and produced a positive return in 33.1% of those months. | J24: =Summary!A23 -> 37468 | K24: =K23*(1+Summary!B23) -> 0.58843512 | L24: =L23*(1+Summary!E23) -> 1.046335 | M24: =MAX($K$3:K24) -> 0.99069493 | N24: =K24/M24-1 -> -0.40603802 | O24: =L24/MAX($L$3:L24)-1 -> -0.063097796
J25: =Summary!A24 -> 37499 | K25: =K24*(1+Summary!B24) -> 0.59131526 | L25: =L24*(1+Summary!E24) -> 1.0894681 | M25: =MAX($K$3:K25) -> 0.99069493 | N25: =K25/M25-1 -> -0.40313082 | O25: =L25/MAX($L$3:L25)-1 -> -0.024475868
J26: =Summary!A25 -> 37529 | K26: =K25*(1+Summary!B25) -> 0.5259582 | L26: =L25*(1+Summary!E25) -> 1.0827966 | M26: =MAX($K$3:K26) -> 0.99069493 | N26: =K26/M26-1 -> -0.46910175 | O26: =L26/MAX($L$3:L26)-1 -> -0.030449574
J27: =Summary!A26 -> 37560 | K27: =K26*(1+Summary!B26) -> 0.57144967 | L27: =L26*(1+Summary!E26) -> 1.1008863 | M27: =MAX($K$3:K27) -> 0.99069493 | N27: =K27/M27-1 -> -0.423183 | O27: =L27/MAX($L$3:L27)-1 -> -0.014251819
J28: =Summary!A27 -> 37590 | K28: =K27*(1+Summary!B27) -> 0.60409128 | L28: =L27*(1+Summary!E27) -> 1.1067904 | M28: =MAX($K$3:K28) -> 0.99069493 | N28: =K28/M28-1 -> -0.39023481 | O28: =L28/MAX($L$3:L28)-1 -> -0.0089652741
J29: =Summary!A28 -> 37621 | K29: =K28*(1+Summary!B28) -> 0.56790488 | L29: =L28*(1+Summary!E28) -> 1.1565423 | M29: =MAX($K$3:K29) -> 0.99069493 | N29: =K29/M29-1 -> -0.42676109 | O29: =L29/MAX($L$3:L29)-1 -> 0
J30: =Summary!A29 -> 37652 | K30: =K29*(1+Summary!B29) -> 0.55224873 | L30: =L29*(1+Summary!E29) -> 1.172964 | M30: =MAX($K$3:K30) -> 0.99069493 | N30: =K30/M30-1 -> -0.44256429 | O30: =L30/MAX($L$3:L30)-1 -> 0
J31: =Summary!A30 -> 37680 | K31: =K30*(1+Summary!B30) -> 0.54338675 | L31: =L30*(1+Summary!E30) -> 1.1960298 | M31: =MAX($K$3:K31) -> 0.99069493 | N31: =K31/M31-1 -> -0.4515095 | O31: =L31/MAX($L$3:L31)-1 -> 0
J32: =Summary!A31 -> 37711 | K32: =K31*(1+Summary!B31) -> 0.54803929 | L32: =L31*(1+Summary!E31) -> 1.1648007 | M32: =MAX($K$3:K32) -> 0.99069493 | N32: =K32/M32-1 -> -0.44681327 | O32: =L32/MAX($L$3:L32)-1 -> -0.026110619
J33: =Summary!A32 -> 37741 | K33: =K32*(1+Summary!B32) -> 0.59271841 | L33: =L32*(1+Summary!E32) -> 1.2017545 | M33: =MAX($K$3:K33) -> 0.99069493 | N33: =K33/M33-1 -> -0.4017145 | O33: =L33/MAX($L$3:L33)-1 -> 0
J34: =Summary!A33 -> 37772 | K34: =K33*(1+Summary!B33) -> 0.62329222 | L34: =L33*(1+Summary!E33) -> 1.2956676 | M34: =MAX($K$3:K34) -> 0.99069493 | N34: =K34/M34-1 -> -0.37085352 | O34: =L34/MAX($L$3:L34)-1 -> 0
J35: =Summary!A34 -> 37802 | K35: =K34*(1+Summary!B34) -> 0.6305295 | L35: =L34*(1+Summary!E34) -> 1.2429524 | M35: =MAX($K$3:K35) -> 0.99069493 | N35: =K35/M35-1 -> -0.36354827 | O35: =L35/MAX($L$3:L35)-1 -> -0.040685768
J36: =Summary!A35 -> 37833 | K36: =K35*(1+Summary!B35) -> 0.64094232 | L36: =L35*(1+Summary!E35) -> 1.2345351 | M36: =MAX($K$3:K36) -> 0.99069493 | N36: =K36/M36-1 -> -0.35303764 | O36: =L36/MAX($L$3:L36)-1 -> -0.047182204
J37: =Summary!A36 -> 37864 | K37: =K36*(1+Summary!B36) -> 0.65290599 | L37: =L36*(1+Summary!E36) -> 1.220195 | M37: =MAX($K$3:K37) -> 0.99069493 | N37: =K37/M37-1 -> -0.34096161 | O37: =L37/MAX($L$3:L37)-1 -> -0.058249949
A38: DATA QUALITY AND INTERPRETATION | J38: =Summary!A37 -> 37894 | K38: =K37*(1+Summary!B37) -> 0.64493021 | L38: =L37*(1+Summary!E37) -> 1.245721 | M38: =MAX($K$3:K38) -> 0.99069493 | N38: =K38/M38-1 -> -0.3490123 | O38: =L38/MAX($L$3:L38)-1 -> -0.038548896
A39: The confirmed period contains 310 matched monthly observations in the core price, return, trend, and strategy series. One existing formula error remains in Summary!J2 because its RANK formula evaluates the text value in Summary!G2 against Nasdaq returns; that field is not used in this analysis. Earlier-history source errors fall outside the selected window, but the leveraged result assumes 3.9x exposure and the workbook does not visibly model transaction costs, financing slippage, or capacity constraints. | J39: =Summary!A38 -> 37925 | K39: =K38*(1+Summary!B38) -> 0.68096891 | L39: =L38*(1+Summary!E38) -> 1.3222875 | M39: =MAX($K$3:K39) -> 0.99069493 | N39: =K39/M39-1 -> -0.31263511 | O39: =L39/MAX($L$3:L39)-1 -> 0
J40: =Summary!A39 -> 37955 | K40: =K39*(1+Summary!B39) -> 0.68628609 | L40: =L39*(1+Summary!E39) -> 1.3358062 | M40: =MAX($K$3:K40) -> 0.99069493 | N40: =K40/M40-1 -> -0.30726798 | O40: =L40/MAX($L$3:L40)-1 -> 0
J41: =Summary!A40 -> 37986 | K41: =K40*(1+Summary!B40) -> 0.72151244 | L41: =L40*(1+Summary!E40) -> 1.4635908 | M41: =MAX($K$3:K41) -> 0.99069493 | N41: =K41/M41-1 -> -0.27171077 | O41: =L41/MAX($L$3:L41)-1 -> 0
J42: =Summary!A41 -> 38017 | K42: =K41*(1+Summary!B41) -> 0.73421461 | L42: =L41*(1+Summary!E41) -> 1.4666079 | M42: =MAX($K$3:K42) -> 0.99069493 | N42: =K42/M42-1 -> -0.2588893 | O42: =L42/MAX($L$3:L42)-1 -> 0
A43: QUESTIONS FOR DEEPER ANALYSIS | J43: =Summary!A42 -> 38046 | K43: =K42*(1+Summary!B42) -> 0.74366738 | L43: =L42*(1+Summary!E42) -> 1.4684883 | M43: =MAX($K$3:K43) -> 0.99069493 | N43: =K43/M43-1 -> -0.24934775 | O43: =L43/MAX($L$3:L43)-1 -> 0
A44: 1. Which market regimes matter most: recessions, inflation shocks, rapid rate hikes, or equity crashes? 2. Should the 3.9x leverage assumption be stress-tested at lower caps such as 2x and 3x? 3. Would you like attribution by trend, volatility weighting, and underlying asset sleeve? 4. Should the existing formula errors and pre-2000 missing-history issues be repaired in the source model? | J44: =Summary!A43 -> 38077 | K44: =K43*(1+Summary!B43) -> 0.73177756 | L44: =L43*(1+Summary!E43) -> 1.549888 | M44: =MAX($K$3:K44) -> 0.99069493 | N44: =K44/M44-1 -> -0.26134924 | O44: =L44/MAX($L$3:L44)-1 -> 0
J45: =Summary!A44 -> 38107 | K45: =K44*(1+Summary!B44) -> 0.71944465 | L45: =L44*(1+Summary!E44) -> 1.4260424 | M45: =MAX($K$3:K45) -> 0.99069493 | N45: =K45/M45-1 -> -0.27379799 | O45: =L45/MAX($L$3:L45)-1 -> -0.079906185
J46: =Summary!A45 -> 38138 | K46: =K45*(1+Summary!B45) -> 0.72867587 | L46: =L45*(1+Summary!E45) -> 1.4564239 | M46: =MAX($K$3:K46) -> 0.99069493 | N46: =K46/M46-1 -> -0.26448006 | O46: =L46/MAX($L$3:L46)-1 -> -0.060303747
J47: =Summary!A46 -> 38168 | K47: =K46*(1+Summary!B46) -> 0.74204269 | L47: =L46*(1+Summary!E46) -> 1.51844 | M47: =MAX($K$3:K47) -> 0.99069493 | N47: =K47/M47-1 -> -0.2509877 | O47: =L47/MAX($L$3:L47)-1 -> -0.020290475
J48: =Summary!A47 -> 38199 | K48: =K47*(1+Summary!B47) -> 0.71634296 | L48: =L47*(1+Summary!E47) -> 1.4597965 | M48: =MAX($K$3:K48) -> 0.99069493 | N48: =K48/M48-1 -> -0.27692881 | O48: =L48/MAX($L$3:L48)-1 -> -0.058127762
J49: =Summary!A48 -> 38230 | K49: =K48*(1+Summary!B48) -> 0.71826305 | L49: =L48*(1+Summary!E48) -> 1.4612179 | M49: =MAX($K$3:K49) -> 0.99069493 | N49: =K49/M49-1 -> -0.27499068 | O49: =L49/MAX($L$3:L49)-1 -> -0.057210634
J50: =Summary!A49 -> 38260 | K50: =K49*(1+Summary!B49) -> 0.72498338 | L50: =L49*(1+Summary!E49) -> 1.5530174 | M50: =MAX($K$3:K50) -> 0.99069493 | N50: =K50/M50-1 -> -0.26820723 | O50: =L50/MAX($L$3:L50)-1 -> 0
J51: =Summary!A50 -> 38291 | K51: =K50*(1+Summary!B50) -> 0.73487926 | L51: =L50*(1+Summary!E50) -> 1.643333 | M51: =MAX($K$3:K51) -> 0.99069493 | N51: =K51/M51-1 -> -0.25821841 | O51: =L51/MAX($L$3:L51)-1 -> 0
J52: =Summary!A51 -> 38321 | K52: =K51*(1+Summary!B51) -> 0.76331142 | L52: =L51*(1+Summary!E51) -> 1.7625914 | M52: =MAX($K$3:K52) -> 0.99069493 | N52: =K52/M52-1 -> -0.22951919 | O52: =L52/MAX($L$3:L52)-1 -> 0
J53: =Summary!A52 -> 38352 | K53: =K52*(1+Summary!B52) -> 0.78782955 | L53: =L52*(1+Summary!E52) -> 1.8036649 | M53: =MAX($K$3:K53) -> 0.99069493 | N53: =K53/M53-1 -> -0.20477078 | O53: =L53/MAX($L$3:L53)-1 -> 0
J54: =Summary!A53 -> 38383 | K54: =K53*(1+Summary!B53) -> 0.76707776 | L54: =L53*(1+Summary!E53) -> 1.7454605 | M54: =MAX($K$3:K54) -> 0.99069493 | N54: =K54/M54-1 -> -0.22571748 | O54: =L54/MAX($L$3:L54)-1 -> -0.032270073
J55: =Summary!A54 -> 38411 | K55: =K54*(1+Summary!B54) -> 0.78147847 | L55: =L54*(1+Summary!E54) -> 1.7855243 | M55: =MAX($K$3:K55) -> 0.99069493 | N55: =K55/M55-1 -> -0.21118151 | O55: =L55/MAX($L$3:L55)-1 -> -0.010057647
J56: =Summary!A55 -> 38442 | K56: =K55*(1+Summary!B55) -> 0.76567462 | L56: =L55*(1+Summary!E55) -> 1.7619803 | M56: =MAX($K$3:K56) -> 0.99069493 | N56: =K56/M56-1 -> -0.22713381 | O56: =L56/MAX($L$3:L56)-1 -> -0.023111047
... J312: =Summary!A311 -> 46234 | K312: =K311*(1+Summary!B311) -> 4.4193191 | L312: =L311*(1+Summary!E311) -> 41.076559 | M312: =MAX($K$3:K312) -> 4.5020309 | N312: =K312/M312-1 -> -0.018372101 | O312: =L312/MAX($L$3:L312)-1 -> -0.020655453

Sheet Trend Insights
A1: Trend Return Insights | S&P 500 Benchmark
A2: October 31, 2000–July 31, 2026 | 310 matched monthly observations | J2: Date | K2: S&P 500 | L2: Trend Return | M2: Trend Levered Return | N2: S&P Peak | O2: Trend Peak | P2: S&P DD | Q2: Trend DD | R2: Trend Levered DD | T2: Date | U2: GSCI Gasoil | V2: GSCI Gold | W2: Japan Gov’t Bond | X2: US 10Y Gov’t Bond | Y2: S&P 500 | Z2: Nasdaq 100 | AA2: JPY/USD | AB2: EUR/USD | AC2: Sleeve Sum | AD2: Trend Levered Return | AE2: Difference | AF2: Log Growth | AH2: Event Start | AI2: Event End
J3: =Summary!A2 -> 36830 | K3: =1+Summary!B2 -> 0.99069493 | L3: =1+Summary!H2 -> 1.0064456 | M3: =1+Summary!I2 -> 1.0272006 | N3: =K3 -> 0.99069493 | O3: =L3 -> 1.0064456 | P3: =K3/N3-1 -> 0 | Q3: =L3/O3-1 -> 0 | R3: =M3/MAX($M$3:M3)-1 -> 0 | T3: =Summary!A2 -> 36830 | U3: =Trend_Simulation!B98*Trend_Simulation!K98*4.31 -> -0.0021680541 | V3: =Trend_Simulation!C98*Trend_Simulation!L98*4.31 -> 0.019020215 | W3: =Trend_Simulation!D98*Trend_Simulation!M98*4.31 -> 0.012197079 | X3: =Trend_Simulation!E98*Trend_Simulation!N98*4.31 -> 0.0044703058 | Y3: =Trend_Simulation!F98*Trend_Simulation!O98*4.31 -> -0.0028215034 | Z3: =Trend_Simulation!G98*Trend_Simulation!P98*4.31 -> -0.010853795 | AA3: =Trend_Simulation!H98*Trend_Simulation!Q98*4.31 -> 0.0079364158 | AB3: =Trend_Simulation!#REF!*Trend_Simulation!#REF!*4.31 -> #REF! | AC3: =SUM(U3:AB3) -> #REF! | AD3: =Summary!I2 -> 0.027200557 | AE3: =AC3-AD3 -> #REF! | AF3: =LN(1+AD3) -> 0.026837196 | AH3: 36830 | AI3: 37621
A4: STORY IN BRIEF | J4: =Summary!A3 -> 36860 | K4: =K3*(1+Summary!B3) -> 0.90901706 | L4: =L3*(1+Summary!H3) -> 1.0212136 | M4: =M3*(1+Summary!I3) -> 1.0908068 | N4: =MAX($K$3:K4) -> 0.99069493 | O4: =MAX($L$3:L4) -> 1.0212136 | P4: =K4/N4-1 -> -0.082445024 | Q4: =L4/O4-1 -> 0 | R4: =M4/MAX($M$3:M4)-1 -> 0 | T4: =Summary!A3 -> 36860 | U4: =Trend_Simulation!B99*Trend_Simulation!K99*4.31 -> 0.015564116 | V4: =Trend_Simulation!C99*Trend_Simulation!L99*4.31 -> -0.0079689133 | W4: =Trend_Simulation!D99*Trend_Simulation!M99*4.31 -> 0.028755084 | X4: =Trend_Simulation!E99*Trend_Simulation!N99*4.31 -> 0.020263531 | Y4: =Trend_Simulation!F99*Trend_Simulation!O99*4.31 -> 0.024999149 | Z4: =Trend_Simulation!G99*Trend_Simulation!P99*4.31 -> -0.0285683 | AA4: =Trend_Simulation!H99*Trend_Simulation!Q99*4.31 -> 0.010197851 | AB4: =Trend_Simulation!#REF!*Trend_Simulation!#REF!*4.31 -> #REF! | AC4: =SUM(U4:AB4) -> #REF! | AD4: =Summary!I3 -> 0.061921908 | AE4: =AC4-AD4 -> #REF! | AF4: =LN(1+AD4) -> 0.060080387 | AH4: 37652 | AI4: 39416
A5: ="Unlevered trend produced "&TEXT(C11,"0.0%")&" annualized with only "&TEXT(C12,"0.0%")&" volatility and a "&TEXT(C14,"0.0%")&" maximum drawdown. At approximately 4.3x leverage, trend delivered "&TEXT(D11,"0.0%")&" annualized at volatility similar to the S&P 500, while retaining negative equity correlation and a shallower drawdown. The strongest evidence is crisis resilience: leveraged trend averaged "&TEXT(D15,"0.0%")&" in negative S&P months and "&TEXT(D17,"0.0%")&" when the S&P fell at least 5%." -> Unlevered trend produced 5.6% annualized with only 3.6% volatility and a -5.9% maximum drawdown. At approximately 4.3x leverage, trend delivered 17.1% annualized at volatility similar to the S&P 500, while retaining negative equity correlation and a shallower drawdown. The strongest evidence is crisis resilience: leveraged trend averaged 1.5% in negative S&P months and 3.6% when the S&P fell at least 5%. | J5: =Summary!A4 -> 36891 | K5: =K4*(1+Summary!B4) -> 0.90488147 | L5: =L4*(1+Summary!H4) -> 1.0249374 | M5: =M4*(1+Summary!I4) -> 1.1075918 | N5: =MAX($K$3:K5) -> 0.99069493 | O5: =MAX($L$3:L5) -> 1.0249374 | P5: =K5/N5-1 -> -0.086619456 | Q5: =L5/O5-1 -> 0 | R5: =M5/MAX($M$3:M5)-1 -> 0 | T5: =Summary!A4 -> 36891 | U5: =Trend_Simulation!B100*Trend_Simulation!K100*4.31 -> -0.028700111 | V5: =Trend_Simulation!C100*Trend_Simulation!L100*4.31 -> -0.00055194019 | W5: =Trend_Simulation!D100*Trend_Simulation!M100*4.31 -> -0.00018099217 | X5: =Trend_Simulation!E100*Trend_Simulation!N100*4.31 -> 0.016416674 | Y5: =Trend_Simulation!F100*Trend_Simulation!O100*4.31 -> 0.0013795137 | Z5: =Trend_Simulation!G100*Trend_Simulation!P100*4.31 -> 0.0094796628 | AA5: =Trend_Simulation!H100*Trend_Simulation!Q100*4.31 -> 0.017873055 | AB5: =Trend_Simulation!#REF!*Trend_Simulation!#REF!*4.31 -> #REF! | AC5: =SUM(U5:AB5) -> #REF! | AD5: =Summary!I4 -> 0.015387689 | AE5: =AC5-AD5 -> #REF! | AF5: =LN(1+AD5) -> 0.015270499 | AH5: 39447 | AI5: 39994
J6: =Summary!A5 -> 36922 | K6: =K5*(1+Summary!B5) -> 0.93065505 | L6: =L5*(1+Summary!H5) -> 1.0295976 | M6: =M5*(1+Summary!I5) -> 1.1288438 | N6: =MAX($K$3:K6) -> 0.99069493 | O6: =MAX($L$3:L6) -> 1.0295976 | P6: =K6/N6-1 -> -0.060603802 | Q6: =L6/O6-1 -> 0 | R6: =M6/MAX($M$3:M6)-1 -> 0 | T6: =Summary!A5 -> 36922 | U6: =Trend_Simulation!B101*Trend_Simulation!K101*4.31 -> -0.015884626 | V6: =Trend_Simulation!C101*Trend_Simulation!L101*4.31 -> 0.014507765 | W6: =Trend_Simulation!D101*Trend_Simulation!M101*4.31 -> 0.027039364 | X6: =Trend_Simulation!E101*Trend_Simulation!N101*4.31 -> 0.0031707392 | Y6: =Trend_Simulation!F101*Trend_Simulation!O101*4.31 -> -0.008636619 | Z6: =Trend_Simulation!G101*Trend_Simulation!P101*4.31 -> -0.012194475 | AA6: =Trend_Simulation!H101*Trend_Simulation!Q101*4.31 -> 0.011594632 | AB6: =Trend_Simulation!#REF!*Trend_Simulation!#REF!*4.31 -> #REF! | AC6: =SUM(U6:AB6) -> #REF! | AD6: =Summary!I5 -> 0.019187567 | AE6: =AC6-AD6 -> #REF! | AF6: =LN(1+AD6) -> 0.019005807 | AH6: 40025 | AI6: 41274
J7: =Summary!A6 -> 36950 | K7: =K6*(1+Summary!B6) -> 0.8418876 | L7: =L6*(1+Summary!H6) -> 1.0537792 | M7: =M6*(1+Summary!I6) -> 1.2407266 | N7: =MAX($K$3:K7) -> 0.99069493 | O7: =MAX($L$3:L7) -> 1.0537792 | P7: =K7/N7-1 -> -0.15020499 | Q7: =L7/O7-1 -> 0 | R7: =M7/MAX($M$3:M7)-1 -> 0 | T7: =Summary!A6 -> 36950 | U7: =Trend_Simulation!B102*Trend_Simulation!K102*4.31 -> 0.0047489551 | V7: =Trend_Simulation!C102*Trend_Simulation!L102*4.31 -> 0.00037465221 | W7: =Trend_Simulation!D102*Trend_Simulation!M102*4.31 -> 0.018579521 | X7: =Trend_Simulation!E102*Trend_Simulation!N102*4.31 -> 0.0094718755 | Y7: =Trend_Simulation!F102*Trend_Simulation!O102*4.31 -> 0.028921829 | Z7: =Trend_Simulation!G102*Trend_Simulation!P102*4.31 -> 0.032730728 | AA7: =Trend_Simulation!H102*Trend_Simulation!Q102*4.31 -> 0.0063989733 | AB7: =Trend_Simulation!#REF!*Trend_Simulation!#REF!*4.31 -> #REF! | AC7: =SUM(U7:AB7) -> #REF! | AD7: =Summary!I6 -> 0.099112756 | AE7: =AC7-AD7 -> #REF! | AF7: =LN(1+AD7) -> 0.094503269 | AH7: 41305 | AI7: 43830
J8: =Summary!A7 -> 36981 | K8: =K7*(1+Summary!B7) -> 0.78428476 | L8: =L7*(1+Summary!H7) -> 1.0786905 | M8: =M7*(1+Summary!I7) -> 1.3645027 | N8: =MAX($K$3:K8) -> 0.99069493 | O8: =MAX($L$3:L8) -> 1.0786905 | P8: =K8/N8-1 -> -0.20834886 | Q8: =L8/O8-1 -> 0 | R8: =M8/MAX($M$3:M8)-1 -> 0 | T8: =Summary!A7 -> 36981 | U8: =Trend_Simulation!B103*Trend_Simulation!K103*4.31 -> -0.0069272915 | V8: =Trend_Simulation!C103*Trend_Simulation!L103*4.31 -> 0.019275152 | W8: =Trend_Simulation!D103*Trend_Simulation!M103*4.31 -> 0.0095452265 | X8: =Trend_Simulation!E103*Trend_Simulation!N103*4.31 -> 0.0023190012 | Y8: =Trend_Simulation!F103*Trend_Simulation!O103*4.31 -> 0.020746771 | Z8: =Trend_Simulation!G103*Trend_Simulation!P103*4.31 -> 0.021993038 | AA8: =Trend_Simulation!H103*Trend_Simulation!Q103*4.31 -> 0.034936676 | AB8: =Trend_Simulation!#REF!*Trend_Simulation!#REF!*4.31 -> #REF! | AC8: =SUM(U8:AB8) -> #REF! | AD8: =Summary!I7 -> 0.099760969 | AE8: =AC8-AD8 -> #REF! | AF8: =LN(1+AD8) -> 0.095092856 | AH8: 43861 | AI8: 43951
A9: PERFORMANCE AND RISK SCORECARD | J9: =Summary!A8 -> 37011 | K9: =K8*(1+Summary!B8) -> 0.8412968 | L9: =L8*(1+Summary!H8) -> 1.0647233 | M9: =M8*(1+Summary!I8) -> 1.2899439 | N9: =MAX($K$3:K9) -> 0.99069493 | O9: =MAX($L$3:L9) -> 1.0786905 | P9: =K9/N9-1 -> -0.15080134 | Q9: =L9/O9-1 -> -0.012948277 | R9: =M9/MAX($M$3:M9)-1 -> -0.054641728 | T9: =Summary!A8 -> 37011 | U9: =Trend_Simulation!B104*Trend_Simulation!K104*4.31 -> 0.020004171 | V9: =Trend_Simulation!C104*Trend_Simulation!L104*4.31 -> -0.010062235 | W9: =Trend_Simulation!D104*Trend_Simulation!M104*4.31 -> 0.0037111662 | X9: =Trend_Simulation!E104*Trend_Simulation!N104*4.31 -> -0.021091457 | Y9: =Trend_Simulation!F104*Trend_Simulation!O104*4.31 -> -0.02204213 | Z9: =Trend_Simulation!G104*Trend_Simulation!P104*4.31 -> -0.020945012 | AA9: =Trend_Simulation!H104*Trend_Simulation!Q104*4.31 -> -0.0053815765 | AB9: =Trend_Simulation!#REF!*Trend_Simulation!#REF!*4.31 -> #REF! | AC9: =SUM(U9:AB9) -> #REF! | AD9: =Summary!I8 -> -0.054641728 | AE9: =AC9-AD9 -> #REF! | AF9: =LN(1+AD9) -> -0.056191299 | AH9: 43982 | AI9: 44620
A10: Metric | B10: S&P 500 | C10: Trend Return | D10: Trend Levered Return | J10: =Summary!A9 -> 37042 | K10: =K9*(1+Summary!B9) -> 0.84343845 | L10: =L9*(1+Summary!H9) -> 1.0641298 | M10: =M9*(1+Summary!I9) -> 1.286909 | N10: =MAX($K$3:K10) -> 0.99069493 | O10: =MAX($L$3:L10) -> 1.0786905 | P10: =K10/N10-1 -> -0.14863958 | Q10: =L10/O10-1 -> -0.013498569 | R10: =M10/MAX($M$3:M10)-1 -> -0.056865868 | T10: =Summary!A9 -> 37042 | U10: =Trend_Simulation!B105*Trend_Simulation!K105*4.31 -> -0.00010812901 | V10: =Trend_Simulation!C105*Trend_Simulation!L105*4.31 -> -0.0028996947 | W10: =Trend_Simulation!D105*Trend_Simulation!M105*4.31 -> 0.016470597 | X10: =Trend_Simulation!E105*Trend_Simulation!N105*4.31 -> -0.0007422444 | Y10: =Trend_Simulation!F105*Trend_Simulation!O105*4.31 -> -0.000771896 | Z10: =Trend_Simulation!G105*Trend_Simulation!P105*4.31 -> 0.0038795069 | AA10: =Trend_Simulation!H105*Trend_Simulation!Q105*4.31 -> -0.018231012 | AB10: =Trend_Simulation!#REF!*Trend_Simulation!#REF!*4.31 -> #REF! | AC10: =SUM(U10:AB10) -> #REF! | AD10: =Summary!I9 -> -0.0023526959 | AE10: =AC10-AD10 -> #REF! | AF10: =LN(1+AD10) -> -0.0023554679 | AH10: 44651 | AI10: 45535
A11: Annualized return | B11: =Summary!V43 -> 0.078300905 | C11: {=PRODUCT(1+Summary!H2:H311)^(12/COUNT(Summary!H2:H311))-1+Summary!Z43} -> 0.055532947 | D11: =Summary!X43 -> 0.17126707 | J11: =Summary!A10 -> 37072 | K11: =K10*(1+Summary!B10) -> 0.81965881 | L11: =L10*(1+Summary!H10) -> 1.0709455 | M11: =M10*(1+Summary!I10) -> 1.3216929 | N11: =MAX($K$3:K11) -> 0.99069493 | O11: =MAX($L$3:L11) -> 1.0786905 | P11: =K11/N11-1 -> -0.17264256 | Q11: =L11/O11-1 -> -0.0071800518 | R11: =M11/MAX($M$3:M11)-1 -> -0.031373901 | T11: =Summary!A10 -> 37072 | U11: =Trend_Simulation!B106*Trend_Simulation!K106*4.31 -> -0.0032096537 | V11: =Trend_Simulation!C106*Trend_Simulation!L106*4.31 -> -0.0082690333 | W11: =Trend_Simulation!D106*Trend_Simulation!M106*4.31 -> 0.0053587996 | X11: =Trend_Simulation!E106*Trend_Simulation!N106*4.31 -> 0.0018264959 | Y11: =Trend_Simulation!F106*Trend_Simulation!O106*4.31 -> 0.0085489447 | Z11: =Trend_Simulation!G106*Trend_Simulation!P106*4.31 -> -0.0023965865 | AA11: =Trend_Simulation!H106*Trend_Simulation!Q106*4.31 -> 0.025746475 | AB11: =Trend_Simulation!#REF!*Trend_Simulation!#REF!*4.31 -> #REF! | AC11: =SUM(U11:AB11) -> #REF! | AD11: =Summary!I10 -> 0.027028994 | AE11: =AC11-AD11 -> #REF! | AF11: =LN(1+AD11) -> 0.026670162 | AH11: 45565 | AI11: 46234
A12: Annualized volatility | B12: =Summary!V44 -> 0.1528659 | C12: =_xlfn.STDEV.S(Summary!H2:H311)*SQRT(12) -> 0.036215307 | D12: =Summary!X44 -> 0.1528286 | J12: =Summary!A11 -> 37103 | K12: =K11*(1+Summary!B11) -> 0.80872905 | L12: =L11*(1+Summary!H11) -> 1.0796573 | M12: =M11*(1+Summary!I11) -> 1.3670648 | N12: =MAX($K$3:K12) -> 0.99069493 | O12: =MAX($L$3:L12) -> 1.0796573 | P12: =K12/N12-1 -> -0.18367499 | Q12: =L12/O12-1 -> 0 | R12: =M12/MAX($M$3:M12)-1 -> 0 | T12: =Summary!A11 -> 37103 | U12: =Trend_Simulation!B107*Trend_Simulation!K107*4.31 -> -0.0070248749 | V12: =Trend_Simulation!C107*Trend_Simulation!L107*4.31 -> 0.0083457508 | W12: =Trend_Simulation!D107*Trend_Simulation!M107*4.31 -> -0.011251136 | X12: =Trend_Simulation!E107*Trend_Simulation!N107*4.31 -> 0.027768059 | Y12: =Trend_Simulation!F107*Trend_Simulation!O107*4.31 -> 0.0040433248 | Z12: =Trend_Simulation!G107*Trend_Simulation!P107*4.31 -> 0.010902859 | AA12: =Trend_Simulation!H107*Trend_Simulation!Q107*4.31 -> 0.0022767497 | AB12: =Trend_Simulation!#REF!*Trend_Simulation!#REF!*4.31 -> #REF! | AC12: =SUM(U12:AB12) -> #REF! | AD12: =Summary!I11 -> 0.034328606 | AE12: =AC12-AD12 -> #REF! | AF12: =LN(1+AD12) -> 0.033752526
A13: Sharpe ratio | B13: =Summary!V45 -> 0.38732378 | C13: =(C11-Summary!Z43)/C12 -> 1.0062221 | D13: =Summary!X45 -> 0.99572181 | J13: =Summary!A12 -> 37134 | K13: =K12*(1+Summary!B12) -> 0.75533565 | L13: =L12*(1+Summary!H12) -> 1.0843356 | M13: =M12*(1+Summary!I12) -> 1.3920626 | N13: =MAX($K$3:K13) -> 0.99069493 | O13: =MAX($L$3:L13) -> 1.0843356 | P13: =K13/N13-1 -> -0.23756988 | Q13: =L13/O13-1 -> 0 | R13: =M13/MAX($M$3:M13)-1 -> 0 | T13: =Summary!A12 -> 37134 | U13: =Trend_Simulation!B108*Trend_Simulation!K108*4.31 -> 0.0096214789 | V13: =Trend_Simulation!C108*Trend_Simulation!L108*4.31 -> -0.013602252 | W13: =Trend_Simulation!D108*Trend_Simulation!M108*4.31 -> 0.00063639722 | X13: =Trend_Simulation!E108*Trend_Simulation!N108*4.31 -> 0.0096037543 | Y13: =Trend_Simulation!F108*Trend_Simulation!O108*4.31 -> 0.020019134 | Z13: =Trend_Simulation!G108*Trend_Simulation!P108*4.31 -> 0.015946253 | AA13: =Trend_Simulation!H108*Trend_Simulation!Q108*4.31 -> -0.023549034 | AB13: =Trend_Simulation!#REF!*Trend_Simulation!#REF!*4.31 -> #REF! | AC13: =SUM(U13:AB13) -> #REF! | AD13: =Summary!I12 -> 0.01828575 | AE13: =AC13-AD13 -> #REF! | AF13: =LN(1+AD13) -> 0.018120577 | AH13: Macro Start | AI13: Macro End
A14: Maximum drawdown | B14: =MIN(P3:P312) -> -0.56071562 | C14: =MIN(Q3:Q312) -> -0.059125533 | D14: =MIN(R3:R312) -> -0.23846854 | J14: =Summary!A13 -> 37164 | K14: =K13*(1+Summary!B13) -> 0.67683332 | L14: =L13*(1+Summary!H13) -> 1.1003826 | M14: =M13*(1+Summary!I13) -> 1.4789991 | N14: =MAX($K$3:K14) -> 0.99069493 | O14: =MAX($L$3:L14) -> 1.1003826 | P14: =K14/N14-1 -> -0.31680954 | Q14: =L14/O14-1 -> 0 | R14: =M14/MAX($M$3:M14)-1 -> 0 | T14: =Summary!A13 -> 37164 | U14: =Trend_Simulation!B109*Trend_Simulation!K109*4.31 -> 0.016875281 | V14: =Trend_Simulation!C109*Trend_Simulation!L109*4.31 -> -0.031745338 | W14: =Trend_Simulation!D109*Trend_Simulation!M109*4.31 -> 6.7011004e-05 | X14: =Trend_Simulation!E109*Trend_Simulation!N109*4.31 -> 0.019818528 | Y14: =Trend_Simulation!F109*Trend_Simulation!O109*4.31 -> 0.031513984 | Z14: =Trend_Simulation!G109*Trend_Simulation!P109*4.31 -> 0.025361343 | AA14: =Trend_Simulation!H109*Trend_Simulation!Q109*4.31 -> 0.0018926587 | AB14: =Trend_Simulation!#REF!*Trend_Simulation!#REF!*4.31 -> #REF! | AC14: =SUM(U14:AB14) -> #REF! | AD14: =Summary!I13 -> 0.062451562 | AE14: =AC14-AD14 -> #REF! | AF14: =LN(1+AD14) -> 0.060579032 | AH14: 36830 | AI14: 38168
A15: Average return in S&P down months | B15: =AVERAGEIF(Summary!B2:B311,"<0",Summary!B2:B311) -> -0.037328582 | C15: =AVERAGEIF(Summary!B2:B311,"<0",Summary!H2:H311) -> 0.0035867751 | D15: =AVERAGEIF(Summary!B2:B311,"<0",Summary!I2:I311) -> 0.015136191 | J15: =Summary!A14 -> 37195 | K15: =K14*(1+Summary!B14) -> 0.68783694 | L15: =L14*(1+Summary!H14) -> 1.106513 | M15: =M14*(1+Summary!I14) -> 1.5137704 | N15: =MAX($K$3:K15) -> 0.99069493 | O15: =MAX($L$3:L15) -> 1.106513 | P15: =K15/N15-1 -> -0.30570257 | Q15: =L15/O15-1 -> 0 | R15: =M15/MAX($M$3:M15)-1 -> 0 | T15: =Summary!A14 -> 37195 | U15: =Trend_Simulation!B110*Trend_Simulation!K110*4.31 -> 0.020043059 | V15: =Trend_Simulation!C110*Trend_Simulation!L110*4.31 -> -0.023030999 | W15: =Trend_Simulation!D110*Trend_Simulation!M110*4.31 -> 0.014004772 | X15: =Trend_Simulation!E110*Trend_Simulation!N110*4.31 -> 0.023256762 | Y15: =Trend_Simulation!F110*Trend_Simulation!O110*4.31 -> -0.0049296327 | Z15: =Trend_Simulation!G110*Trend_Simulation!P110*4.31 -> -0.02021487 | AA15: =Trend_Simulation!H110*Trend_Simulation!Q110*4.31 -> 0.014882328 | AB15: =Trend_Simulation!#REF!*Trend_Simulation!#REF!*4.31 -> #REF! | AC15: =SUM(U15:AB15) -> #REF! | AD15: =Summary!I14 -> 0.02351002 | AE15: =AC15-AD15 -> #REF! | AF15: =LN(1+AD15) -> 0.023237916 | AH15: 38199 | AI15: 39294
A16: Correlation with S&P 500 | B16: 1 | C16: =CORREL(Summary!B2:B311,Summary!H2:H311) -> -0.13407461 | D16: =CORREL(Summary!B2:B311,Summary!I2:I311) -> -0.13407461 | J16: =Summary!A15 -> 37225 | K16: =K15*(1+Summary!B15) -> 0.73923639 | L16: =L15*(1+Summary!H15) -> 1.0887438 | M16: =M15*(1+Summary!I15) -> 1.4111856 | N16: =MAX($K$3:K16) -> 0.99069493 | O16: =MAX($L$3:L16) -> 1.106513 | P16: =K16/N16-1 -> -0.25382035 | Q16: =L16/O16-1 -> -0.016058705 | R16: =M16/MAX($M$3:M16)-1 -> -0.067767735 | T16: =Summary!A15 -> 37225 | U16: =Trend_Simulation!B111*Trend_Simulation!K111*4.31 -> 0.018874282 | V16: =Trend_Simulation!C111*Trend_Simulation!L111*4.31 -> -0.011072253 | W16: =Trend_Simulation!D111*Trend_Simulation!M111*4.31 -> -0.010610761 | X16: =Trend_Simulation!E111*Trend_Simulation!N111*4.31 -> -0.027230969 | Y16: =Trend_Simulation!F111*Trend_Simulation!O111*4.31 -> -0.022658637 | Z16: =Trend_Simulation!G111*Trend_Simulation!P111*4.31 -> -0.020480445 | AA16: =Trend_Simulation!H111*Trend_Simulation!Q111*4.31 -> 0.0039657629 | AB16: =Trend_Simulation!#REF!*Trend_Simulation!#REF!*4.31 -> #REF! | AC16: =SUM(U16:AB16) -> #REF! | AD16: =Summary!I15 -> -0.067767735 | AE16: =AC16-AD16 -> #REF! | AF16: =LN(1+AD16) -> -0.070173284 | AH16: 39325 | AI16: 39813
A17: Average return when S&P ≤ -5% | B17: =AVERAGEIF(Summary!B2:B311,"<=-5%",Summary!B2:B311) -> -0.078545405 | C17: =AVERAGEIF(Summary!B2:B311,"<=-5%",Summary!H2:H311) -> 0.008560294 | D17: =AVERAGEIF(Summary!B2:B311,"<=-5%",Summary!I2:I311) -> 0.036124441 | J17: =Summary!A16 -> 37256 | K17: =K16*(1+Summary!B16) -> 0.74433203 | L17: =L16*(1+Summary!H16) -> 1.0913748 | M17: =M16*(1+Summary!I16) -> 1.4255763 | N17: =MAX($K$3:K17) -> 0.99069493 | O17: =MAX($L$3:L17) -> 1.106513 | P17: =K17/N17-1 -> -0.24867685 | Q17: =L17/O17-1 -> -0.01368102 | R17: =M17/MAX($M$3:M17)-1 -> -0.058261211 | T17: =Summary!A16 -> 37256 | U17: =Trend_Simulation!B112*Trend_Simulation!K112*4.31 -> -0.0016393986 | V17: =Trend_Simulation!C112*Trend_Simulation!L112*4.31 -> -0.00748237 | W17: =Trend_Simulation!D112*Trend_Simulation!M112*4.31 -> 0.0038332286 | X17: =Trend_Simulation!E112*Trend_Simulation!N112*4.31 -> -0.015665356 | Y17: =Trend_Simulation!F112*Trend_Simulation!O112*4.31 -> -0.0020901419 | Z17: =Trend_Simulation!G112*Trend_Simulation!P112*4.31 -> 0.0016155165 | AA17: =Trend_Simulation!H112*Trend_Simulation!Q112*4.31 -> 0.031843598 | AB17: =Trend_Simulation!#REF!*Trend_Simulation!#REF!*4.31 -> #REF! | AC17: =SUM(U17:AB17) -> #REF! | AD17: =Summary!I16 -> 0.010197592 | AE17: =AC17-AD17 -> #REF! | AF17: =LN(1+AD17) -> 0.010145947 | AH17: 39844 | AI17: 42338
J18: =Summary!A17 -> 37287 | K18: =K17*(1+Summary!B17) -> 0.73222066 | L18: =L17*(1+Summary!H17) -> 1.0925357 | M18: =M17*(1+Summary!I17) -> 1.4319755 | N18: =MAX($K$3:K18) -> 0.99069493 | O18: =MAX($L$3:L18) -> 1.106513 | P18: =K18/N18-1 -> -0.26090198 | Q18: =L18/O18-1 -> -0.012631856 | R18: =M18/MAX($M$3:M18)-1 -> -0.054033856 | T18: =Summary!A17 -> 37287 | U18: =Trend_Simulation!B113*Trend_Simulation!K113*4.31 -> 0.010557454 | V18: =Trend_Simulation!C113*Trend_Simulation!L113*4.31 -> -0.0057301256 | W18: =Trend_Simulation!D113*Trend_Simulation!M113*4.31 -> -0.02508208 | X18: =Trend_Simulation!E113*Trend_Simulation!N113*4.31 -> 0.0064564947 | Y18: =Trend_Simulation!F113*Trend_Simulation!O113*4.31 -> 0.0049338639 | Z18: =Trend_Simulation!G113*Trend_Simulation!P113*4.31 -> 0.0023195492 | AA18: =Trend_Simulation!H113*Trend_Simulation!Q113*4.31 -> 0.011129461 | AB18: =Trend_Simulation!#REF!*Trend_Simulation!#REF!*4.31 -> #REF! | AC18: =SUM(U18:AB18) -> #REF! | AD18: =Summary!I17 -> 0.0044888826 | AE18: =AC18-AD18 -> #REF! | AF18: =LN(1+AD18) -> 0.0044788376 | AH18: 42369 | AI18: 43677
A19: THREE MOST IMPORTANT TAKEAWAYS | J19: =Summary!A18 -> 37315 | K19: =K18*(1+Summary!B18) -> 0.71700761 | L19: =L18*(1+Summary!H18) -> 1.1075646 | M19: =M18*(1+Summary!I18) -> 1.5151023 | N19: =MAX($K$3:K19) -> 0.99069493 | O19: =MAX($L$3:L19) -> 1.1075646 | P19: =K19/N19-1 -> -0.27625792 | Q19: =L19/O19-1 -> 0 | R19: =M19/MAX($M$3:M19)-1 -> 0 | T19: =Summary!A18 -> 37315 | U19: =Trend_Simulation!B114*Trend_Simulation!K114*4.31 -> -0.0094167297 | V19: =Trend_Simulation!C114*Trend_Simulation!L114*4.31 -> 0.025175663 | W19: =Trend_Simulation!D114*Trend_Simulation!M114*4.31 -> 0.0091327202 | X19: =Trend_Simulation!E114*Trend_Simulation!N114*4.31 -> 0.011973119 | Y19: =Trend_Simulation!F114*Trend_Simulation!O114*4.31 -> 0.0062999234 | Z19: =Trend_Simulation!G114*Trend_Simulation!P114*4.31 -> 0.015210764 | AA19: =Trend_Simulation!H114*Trend_Simulation!Q114*4.31 -> 0.00091301979 | AB19: =Trend_Simulation!#REF!*Trend_Simulation!#REF!*4.31 -> #REF! | AC19: =SUM(U19:AB19) -> #REF! | AD19: =Summary!I18 -> 0.058050437 | AE19: =AC19-AD19 -> #REF! | AF19: =LN(1+AD19) -> 0.056428005 | AH19: 43708 | AI19: 44620
A20: ="1 | Diversification — Trend correlation to the S&P 500 was "&TEXT(C16,"0.00")&" both before and after leverage, providing a distinct return stream rather than amplified equity beta." -> 1 | Diversification — Trend correlation to the S&P 500 was -0.13 both before and after leverage, providing a distinct return stream rather than amplified equity beta. | J20: =Summary!A19 -> 37346 | K20: =K19*(1+Summary!B19) -> 0.74263348 | L20: =L19*(1+Summary!H19) -> 1.0945598 | M20: =M19*(1+Summary!I19) -> 1.4400284 | N20: =MAX($K$3:K20) -> 0.99069493 | O20: =MAX($L$3:L20) -> 1.1075646 | P20: =K20/N20-1 -> -0.25039135 | Q20: =L20/O20-1 -> -0.011741799 | R20: =M20/MAX($M$3:M20)-1 -> -0.04955039 | T20: =Summary!A19 -> 37346 | U20: =Trend_Simulation!B115*Trend_Simulation!K115*4.31 -> -0.029101787 | V20: =Trend_Simulation!C115*Trend_Simulation!L115*4.31 -> 0.0094977996 | W20: =Trend_Simulation!D115*Trend_Simulation!M115*4.31 -> 0.022613607 | X20: =Trend_Simulation!E115*Trend_Simulation!N115*4.31 -> -0.030288986 | Y20: =Trend_Simulation!F115*Trend_Simulation!O115*4.31 -> -0.010837166 | Z20: =Trend_Simulation!G115*Trend_Simulation!P115*4.31 -> -0.0082317784 | AA20: =Trend_Simulation!H115*Trend_Simulation!Q115*4.31 -> -0.0042588408 | AB20: =Trend_Simulation!#REF!*Trend_Simulation!#REF!*4.31 -> #REF! | AC20: =SUM(U20:AB20) -> #REF! | AD20: =Summary!I19 -> -0.04955039 | AE20: =AC20-AD20 -> #REF! | AF20: =LN(1+AD20) -> -0.050820133 | AH20: 44651 | AI20: 45535
J21: =Summary!A20 -> 37376 | K21: =K20*(1+Summary!B20) -> 0.69610812 | L21: =L20*(1+Summary!H20) -> 1.1096323 | M21: =M20*(1+Summary!I20) -> 1.5237096 | N21: =MAX($K$3:K21) -> 0.99069493 | O21: =MAX($L$3:L21) -> 1.1096323 | P21: =K21/N21-1 -> -0.29735371 | Q21: =L21/O21-1 -> 0 | R21: =M21/MAX($M$3:M21)-1 -> 0 | T21: =Summary!A20 -> 37376 | U21: =Trend_Simulation!B116*Trend_Simulation!K116*4.31 -> -0.0047800081 | V21: =Trend_Simulation!C116*Trend_Simulation!L116*4.31 -> 0.0090848615 | W21: =Trend_Simulation!D116*Trend_Simulation!M116*4.31 -> 0.0086333022 | X21: =Trend_Simulation!E116*Trend_Simulation!N116*4.31 -> 0.028069913 | Y21: =Trend_Simulation!F116*Trend_Simulation!O116*4.31 -> 0.018996608 | Z21: =Trend_Simulation!G116*Trend_Simulation!P116*4.31 -> 0.01505794 | AA21: =Trend_Simulation!H116*Trend_Simulation!Q116*4.31 -> -0.015712503 | AB21: =Trend_Simulation!#REF!*Trend_Simulation!#REF!*4.31 -> #REF! | AC21: =SUM(U21:AB21) -> #REF! | AD21: =Summary!I20 -> 0.058110783 | AE21: =AC21-AD21 -> #REF! | AF21: =LN(1+AD21) -> 0.056485038 | AH21: 45565 | AI21: 46234
A22: ="2 | Crisis resilience — In 118 negative S&P months, leveraged trend averaged "&TEXT(D15,"0.0%")&" versus "&TEXT(B15,"0.0%")&" for equities; in the 37 months with S&P losses of at least 5%, it averaged "&TEXT(D17,"0.0%")&"." -> 2 | Crisis resilience — In 118 negative S&P months, leveraged trend averaged 1.5% versus -3.7% for equities; in the 37 months with S&P losses of at least 5%, it averaged 3.6%. | J22: =Summary!A21 -> 37407 | K22: =K21*(1+Summary!B21) -> 0.68983088 | L22: =L21*(1+Summary!H21) -> 1.1221627 | M22: =M21*(1+Summary!I21) -> 1.5963204 | N22: =MAX($K$3:K22) -> 0.99069493 | O22: =MAX($L$3:L22) -> 1.1221627 | P22: =K22/N22-1 -> -0.3036899 | Q22: =L22/O22-1 -> 0 | R22: =M22/MAX($M$3:M22)-1 -> 0 | T22: =Summary!A21 -> 37407 | U22: =Trend_Simulation!B117*Trend_Simulation!K117*4.31 -> 0.01342671 | V22: =Trend_Simulation!C117*Trend_Simulation!L117*4.31 -> 0.027947052 | W22: =Trend_Simulation!D117*Trend_Simulation!M117*4.31 -> 0.004872507 | X22: =Trend_Simulation!E117*Trend_Simulation!N117*4.31 -> 0.0098306496 | Y22: =Trend_Simulation!F117*Trend_Simulation!O117*4.31 -> 0.0027343384 | Z22: =Trend_Simulation!G117*Trend_Simulation!P117*4.31 -> 0.0067435773 | AA22: =Trend_Simulation!H117*Trend_Simulation!Q117*4.31 -> -0.016884504 | AB22: =Trend_Simulation!#REF!*Trend_Simulation!#REF!*4.31 -> #REF! | AC22: =SUM(U22:AB22) -> #REF! | AD22: =Summary!I21 -> 0.047654013 | AE22: =AC22-AD22 -> #REF! | AF22: =LN(1+AD22) -> 0.046553391
J23: =Summary!A22 -> 37437 | K23: =K22*(1+Summary!B22) -> 0.63909608 | L23: =L22*(1+Summary!H22) -> 1.1285714 | M23: =M22*(1+Summary!I22) -> 1.6347927 | N23: =MAX($K$3:K23) -> 0.99069493 | O23: =MAX($L$3:L23) -> 1.1285714 | P23: =K23/N23-1 -> -0.35490123 | Q23: =L23/O23-1 -> 0 | R23: =M23/MAX($M$3:M23)-1 -> 0 | T23: =Summary!A22 -> 37437 | U23: =Trend_Simulation!B118*Trend_Simulation!K118*4.31 -> -0.0073982915 | V23: =Trend_Simulation!C118*Trend_Simulation!L118*4.31 -> -0.020829354 | W23: =Trend_Simulation!D118*Trend_Simulation!M118*4.31 -> 0.014611839 | X23: =Trend_Simulation!E118*Trend_Simulation!N118*4.31 -> 0.017152104 | Y23: =Trend_Simulation!F118*Trend_Simulation!O118*4.31 -> 0.022300989 | Z23: =Trend_Simulation!G118*Trend_Simulation!P118*4.31 -> 0.016205742 | AA23: =Trend_Simulation!H118*Trend_Simulation!Q118*4.31 -> -0.017428477 | AB23: =Trend_Simulation!#REF!*Trend_Simulation!#REF!*4.31 -> #REF! | AC23: =SUM(U23:AB23) -> #REF! | AD23: =Summary!I22 -> 0.024100559 | AE23: =AC23-AD23 -> #REF! | AF23: =LN(1+AD23) -> 0.023814724
A24: ="3 | Leverage efficiency — Levered trend achieved "&TEXT(D11,"0.0%")&" annualized at "&TEXT(D12,"0.0%")&" volatility versus "&TEXT(B11,"0.0%")&" and "&TEXT(B12,"0.0%")&" for the S&P 500, though the "&TEXT(D14,"0.0%")&" drawdown shows leverage remains consequential." -> 3 | Leverage efficiency — Levered trend achieved 17.1% annualized at 15.3% volatility versus 7.8% and 15.3% for the S&P 500, though the -23.8% drawdown shows leverage remains consequential. | J24: =Summary!A23 -> 37468 | K24: =K23*(1+Summary!B23) -> 0.58843512 | L24: =L23*(1+Summary!H23) -> 1.1405618 | M24: =M23*(1+Summary!I23) -> 1.7080885 | N24: =MAX($K$3:K24) -> 0.99069493 | O24: =MAX($L$3:L24) -> 1.1405618 | P24: =K24/N24-1 -> -0.40603802 | Q24: =L24/O24-1 -> 0 | R24: =M24/MAX($M$3:M24)-1 -> 0 | T24: =Summary!A23 -> 37468 | U24: =Trend_Simulation!B119*Trend_Simulation!K119*4.31 -> -0.0038052811 | V24: =Trend_Simulation!C119*Trend_Simulation!L119*4.31 -> -0.017278239 | W24: =Trend_Simulation!D119*Trend_Simulation!M119*4.31 -> 0.0037075481 | X24: =Trend_Simulation!E119*Trend_Simulation!N119*4.31 -> 0.029099034 | Y24: =Trend_Simulation!F119*Trend_Simulation!O119*4.31 -> 0.024036321 | Z24: =Trend_Simulation!G119*Trend_Simulation!P119*4.31 -> 0.010396315 | AA24: =Trend_Simulation!H119*Trend_Simulation!Q119*4.31 -> -0.00036458564 | AB24: =Trend_Simulation!#REF!*Trend_Simulation!#REF!*4.31 -> #REF! | AC24: =SUM(U24:AB24) -> #REF! | AD24: =Summary!I23 -> 0.044834917 | AE24: =AC24-AD24 -> #REF! | AF24: =LN(1+AD24) -> 0.043858899
J25: =Summary!A24 -> 37499 | K25: =K24*(1+Summary!B24) -> 0.59131526 | L25: =L24*(1+Summary!H24) -> 1.1543449 | M25: =M24*(1+Summary!I24) -> 1.795195 | N25: =MAX($K$3:K25) -> 0.99069493 | O25: =MAX($L$3:L25) -> 1.1543449 | P25: =K25/N25-1 -> -0.40313082 | Q25: =L25/O25-1 -> 0 | R25: =M25/MAX($M$3:M25)-1 -> 0 | T25: =Summary!A24 -> 37499 | U25: =Trend_Simulation!B120*Trend_Simulation!K120*4.31 -> -0.013947473 | V25: =Trend_Simulation!C120*Trend_Simulation!L120*4.31 -> 0.014297668 | W25: =Trend_Simulation!D120*Trend_Simulation!M120*4.31 -> 0.024876495 | X25: =Trend_Simulation!E120*Trend_Simulation!N120*4.31 -> 0.021313554 | Y25: =Trend_Simulation!F120*Trend_Simulation!O120*4.31 -> -0.001484144 | Z25: =Trend_Simulation!G120*Trend_Simulation!P120*4.31 -> 0.0026660022 | AA25: =Trend_Simulation!H120*Trend_Simulation!Q120*4.31 -> 0.0043619871 | AB25: =Trend_Simulation!#REF!*Trend_Simulation!#REF!*4.31 -> #REF! | AC25: =SUM(U25:AB25) -> #REF! | AD25: =Summary!I24 -> 0.050996486 | AE25: =AC25-AD25 -> #REF! | AF25: =LN(1+AD25) -> 0.049738749
J26: =Summary!A25 -> 37529 | K26: =K25*(1+Summary!B25) -> 0.5259582 | L26: =L25*(1+Summary!H25) -> 1.182254 | M26: =M25*(1+Summary!I25) -> 1.9783567 | N26: =MAX($K$3:K26) -> 0.99069493 | O26: =MAX($L$3:L26) -> 1.182254 | P26: =K26/N26-1 -> -0.46910175 | Q26: =L26/O26-1 -> 0 | R26: =M26/MAX($M$3:M26)-1 -> 0 | T26: =Summary!A25 -> 37529 | U26: =Trend_Simulation!B121*Trend_Simulation!K121*4.31 -> -0.0083317943 | V26: =Trend_Simulation!C121*Trend_Simulation!L121*4.31 -> 0.01805692 | W26: =Trend_Simulation!D121*Trend_Simulation!M121*4.31 -> -0.0017745947 | X26: =Trend_Simulation!E121*Trend_Simulation!N121*4.31 -> 0.034140699 | Y26: =Trend_Simulation!F121*Trend_Simulation!O121*4.31 -> 0.033514613 | Z26: =Trend_Simulation!G121*Trend_Simulation!P121*4.31 -> 0.014489321 | AA26: =Trend_Simulation!H121*Trend_Simulation!Q121*4.31 -> 0.014109693 | AB26: =Trend_Simulation!#REF!*Trend_Simulation!#REF!*4.31 -> #REF! | AC26: =SUM(U26:AB26) -> #REF! | AD26: =Summary!I25 -> 0.10202889 | AE26: =AC26-AD26 -> #REF! | AF26: =LN(1+AD26) -> 0.097152923
J27: =Summary!A26 -> 37560 | K27: =K26*(1+Summary!B26) -> 0.57144967 | L27: =L26*(1+Summary!H26) -> 1.1655109 | M27: =M26*(1+Summary!I26) -> 1.860123 | N27: =MAX($K$3:K27) -> 0.99069493 | O27: =MAX($L$3:L27) -> 1.182254 | P27: =K27/N27-1 -> -0.423183 | Q27: =L27/O27-1 -> -0.014161995 | R27: =M27/MAX($M$3:M27)-1 -> -0.059763618 | T27: =Summary!A26 -> 37560 | U27: =Trend_Simulation!B122*Trend_Simulation!K122*4.31 -> -0.016097052 | V27: =Trend_Simulation!C122*Trend_Simulation!L122*4.31 -> -0.010488745 | W27: =Trend_Simulation!D122*Trend_Simulation!M122*4.31 -> 0.020009061 | X27: =Trend_Simulation!E122*Trend_Simulation!N122*4.31 -> -0.0094786306 | Y27: =Trend_Simulation!F122*Trend_Simulation!O122*4.31 -> -0.02622645 | Z27: =Trend_Simulation!G122*Trend_Simulation!P122*4.31 -> -0.022860493 | AA27: =Trend_Simulation!H122*Trend_Simulation!Q122*4.31 -> 0.0041041126 | AB27: =Trend_Simulation!#REF!*Trend_Simulation!#REF!*4.31 -> #REF! | AC27: =SUM(U27:AB27) -> #REF! | AD27: =Summary!I26 -> -0.059763618 | AE27: =AC27-AD27 -> #REF! | AF27: =LN(1+AD27) -> -0.061623965
J28: =Summary!A27 -> 37590 | K28: =K27*(1+Summary!B27) -> 0.60409128 | L28: =L27*(1+Summary!H27) -> 1.1528398 | M28: =M27*(1+Summary!I27) -> 1.774783 | N28: =MAX($K$3:K28) -> 0.99069493 | O28: =MAX($L$3:L28) -> 1.182254 | P28: =K28/N28-1 -> -0.39023481 | Q28: =L28/O28-1 -> -0.024879755 | R28: =M28/MAX($M$3:M28)-1 -> -0.10290042 | T28: =Summary!A27 -> 37590 | U28: =Trend_Simulation!B123*Trend_Simulation!K123*4.31 -> -0.00028979162 | V28: =Trend_Simulation!C123*Trend_Simulation!L123*4.31 -> -0.0020588819 | W28: =Trend_Simulation!D123*Trend_Simulation!M123*4.31 -> 0.0023121973 | X28: =Trend_Simulation!E123*Trend_Simulation!N123*4.31 -> -0.017082877 | Y28: =Trend_Simulation!F123*Trend_Simulation!O123*4.31 -> -0.016019826 | Z28: =Trend_Simulation!G123*Trend_Simulation!P123*4.31 -> -0.014300255 | AA28: =Trend_Simulation!H123*Trend_Simulation!Q123*4.31 -> 0.00058229855 | AB28: =Trend_Simulation!#REF!*Trend_Simulation!#REF!*4.31 -> #REF! | AC28: =SUM(U28:AB28) -> #REF! | AD28: =Summary!I27 -> -0.045878681 | AE28: =AC28-AD28 -> #REF! | AF28: =LN(1+AD28) -> -0.046964446
J29: =Summary!A28 -> 37621 | K29: =K28*(1+Summary!B28) -> 0.56790488 | L29: =L28*(1+Summary!H28) -> 1.1840878 | M29: =M28*(1+Summary!I28) -> 1.97779 | N29: =MAX($K$3:K29) -> 0.99069493 | O29: =MAX($L$3:L29) -> 1.1840878 | P29: =K29/N29-1 -> -0.42676109 | Q29: =L29/O29-1 -> 0 | R29: =M29/MAX($M$3:M29)-1 -> -0.00028643417 | T29: =Summary!A28 -> 37621 | U29: =Trend_Simulation!B124*Trend_Simulation!K124*4.31 -> 0.020859197 | V29: =Trend_Simulation!C124*Trend_Simulation!L124*4.31 -> 0.04573934 | W29: =Trend_Simulation!D124*Trend_Simulation!M124*4.31 -> 0.0054905997 | X29: =Trend_Simulation!E124*Trend_Simulation!N124*4.31 -> 0.030033525 | Y29: =Trend_Simulation!F124*Trend_Simulation!O124*4.31 -> 0.016475919 | Z29: =Trend_Simulation!G124*Trend_Simulation!P124*4.31 -> 0.013465593 | AA29: =Trend_Simulation!H124*Trend_Simulation!Q124*4.31 -> -0.015240534 | AB29: =Trend_Simulation!#REF!*Trend_Simulation!#REF!*4.31 -> #REF! | AC29: =SUM(U29:AB29) -> #REF! | AD29: =Summary!I28 -> 0.11438417 | AE29: =AC29-AD29 -> #REF! | AF29: =LN(1+AD29) -> 0.10830194
J30: =Summary!A29 -> 37652 | K30: =K29*(1+Summary!B29) -> 0.55224873 | L30: =L29*(1+Summary!H29) -> 1.1965232 | M30: =M29*(1+Summary!I29) -> 2.0654431 | N30: =MAX($K$3:K30) -> 0.99069493 | O30: =MAX($L$3:L30) -> 1.1965232 | P30: =K30/N30-1 -> -0.44256429 | Q30: =L30/O30-1 -> 0 | R30: =M30/MAX($M$3:M30)-1 -> 0 | T30: =Summary!A29 -> 37652 | U30: =Trend_Simulation!B125*Trend_Simulation!K125*4.31 -> 0.016365232 | V30: =Trend_Simulation!C125*Trend_Simulation!L125*4.31 -> 0.024159898 | W30: =Trend_Simulation!D125*Trend_Simulation!M125*4.31 -> 0.010491538 | X30: =Trend_Simulation!E125*Trend_Simulation!N125*4.31 -> -0.0080606406 | Y30: =Trend_Simulation!F125*Trend_Simulation!O125*4.31 -> 0.0075428045 | Z30: =Trend_Simulation!G125*Trend_Simulation!P125*4.31 -> 0.00029685265 | AA30: =Trend_Simulation!H125*Trend_Simulation!Q125*4.31 -> -0.0055318006 | AB30: =Trend_Simulation!#REF!*Trend_Simulation!#REF!*4.31 -> #REF! | AC30: =SUM(U30:AB30) -> #REF! | AD30: =Summary!I29 -> 0.044318699 | AE30: =AC30-AD30 -> #REF! | AF30: =LN(1+AD30) -> 0.04336471
J31: =Summary!A30 -> 37680 | K31: =K30*(1+Summary!B30) -> 0.54338675 | L31: =L30*(1+Summary!H30) -> 1.2081927 | M31: =M30*(1+Summary!I30) -> 2.1504503 | N31: =MAX($K$3:K31) -> 0.99069493 | O31: =MAX($L$3:L31) -> 1.2081927 | P31: =K31/N31-1 -> -0.4515095 | Q31: =L31/O31-1 -> 0 | R31: =M31/MAX($M$3:M31)-1 -> 0 | T31: =Summary!A30 -> 37680 | U31: =Trend_Simulation!B126*Trend_Simulation!K126*4.31 -> 0.028748028 | V31: =Trend_Simulation!C126*Trend_Simulation!L126*4.31 -> -0.020899992 | W31: =Trend_Simulation!D126*Trend_Simulation!M126*4.31 -> 0.0058584902 | X31: =Trend_Simulation!E126*Trend_Simulation!N126*4.31 -> 0.020444732 | Y31: =Trend_Simulation!F126*Trend_Simulation!O126*4.31 -> 0.0044184796 | Z31: =Trend_Simulation!G126*Trend_Simulation!P126*4.31 -> -0.00309028 | AA31: =Trend_Simulation!H126*Trend_Simulation!Q126*4.31 -> 0.0065551808 | AB31: =Trend_Simulation!#REF!*Trend_Simulation!#REF!*4.31 -> #REF! | AC31: =SUM(U31:AB31) -> #REF! | AD31: =Summary!I30 -> 0.041156884 | AE31: =AC31-AD31 -> #REF! | AF31: =LN(1+AD31) -> 0.040332484
J32: =Summary!A31 -> 37711 | K32: =K31*(1+Summary!B31) -> 0.54803929 | L32: =L31*(1+Summary!H31) -> 1.1959274 | M32: =M31*(1+Summary!I31) -> 2.0583243 | N32: =MAX($K$3:K32) -> 0.99069493 | O32: =MAX($L$3:L32) -> 1.2081927 | P32: =K32/N32-1 -> -0.44681327 | Q32: =L32/O32-1 -> -0.010151735 | R32: =M32/MAX($M$3:M32)-1 -> -0.04284032 | T32: =Summary!A31 -> 37711 | U32: =Trend_Simulation!B127*Trend_Simulation!K127*4.31 -> -0.026131079 | V32: =Trend_Simulation!C127*Trend_Simulation!L127*4.31 -> -0.015824953 | W32: =Trend_Simulation!D127*Trend_Simulation!M127*4.31 -> 0.0068016183 | X32: =Trend_Simulation!E127*Trend_Simulation!N127*4.31 -> -0.0034532392 | Y32: =Trend_Simulation!F127*Trend_Simulation!O127*4.31 -> -0.002301669 | Z32: =Trend_Simulation!G127*Trend_Simulation!P127*4.31 -> -0.00093732532 | AA32: =Trend_Simulation!H127*Trend_Simulation!Q127*4.31 -> -0.0019073293 | AB32: =Trend_Simulation!#REF!*Trend_Simulation!#REF!*4.31 -> #REF! | AC32: =SUM(U32:AB32) -> #REF! | AD32: =Summary!I31 -> -0.04284032 | AE32: =AC32-AD32 -> #REF! | AF32: =LN(1+AD32) -> -0.043785047
J33: =Summary!A32 -> 37741 | K33: =K32*(1+Summary!B32) -> 0.59271841 | L33: =L32*(1+Summary!H32) -> 1.1854558 | M33: =M32*(1+Summary!I32) -> 1.982268 | N33: =MAX($K$3:K33) -> 0.99069493 | O33: =MAX($L$3:L33) -> 1.2081927 | P33: =K33/N33-1 -> -0.4017145 | Q33: =L33/O33-1 -> -0.01881891 | R33: =M33/MAX($M$3:M33)-1 -> -0.078207937 | T33: =Summary!A32 -> 37741 | U33: =Trend_Simulation!B128*Trend_Simulation!K128*4.31 -> -0.013933046 | V33: =Trend_Simulation!C128*Trend_Simulation!L128*4.31 -> 0.0028883683 | W33: =Trend_Simulation!D128*Trend_Simulation!M128*4.31 -> 0.0078485975 | X33: =Trend_Simulation!E128*Trend_Simulation!N128*4.31 -> 0.0017285846 | Y33: =Trend_Simulation!F128*Trend_Simulation!O128*4.31 -> -0.022793284 | Z33: =Trend_Simulation!G128*Trend_Simulation!P128*4.31 -> -0.010013281 | AA33: =Trend_Simulation!H128*Trend_Simulation!Q128*4.31 -> -0.0034645761 | AB33: =Trend_Simulation!#REF!*Trend_Simulation!#REF!*4.31 -> #REF! | AC33: =SUM(U33:AB33) -> #REF! | AD33: =Summary!I32 -> -0.036950592 | AE33: =AC33-AD33 -> #REF! | AF33: =LN(1+AD33) -> -0.037650562
J34: =Summary!A33 -> 37772 | K34: =K33*(1+Summary!B33) -> 0.62329222 | L34: =L33*(1+Summary!H33) -> 1.2013054 | M34: =M33*(1+Summary!I33) -> 2.0941105 | N34: =MAX($K$3:K34) -> 0.99069493 | O34: =MAX($L$3:L34) -> 1.2081927 | P34: =K34/N34-1 -> -0.37085352 | Q34: =L34/O34-1 -> -0.0057005031 | R34: =M34/MAX($M$3:M34)-1 -> -0.026199077 | T34: =Summary!A33 -> 37772 | U34: =Trend_Simulation!B129*Trend_Simulation!K129*4.31 -> 0.0096437396 | V34: =Trend_Simulation!C129*Trend_Simulation!L129*4.31 -> 0.029094941 | W34: =Trend_Simulation!D129*Trend_Simulation!M129*4.31 -> 0.01730106 | X34: =Trend_Simulation!E129*Trend_Simulation!N129*4.31 -> 0.02700729 | Y34: =Trend_Simulation!F129*Trend_Simulation!O129*4.31 -> -0.013679889 | Z34: =Trend_Simulation!G129*Trend_Simulation!P129*4.31 -> -0.0095789036 | AA34: =Trend_Simulation!H129*Trend_Simulation!Q129*4.31 -> -0.0021634694 | AB34: =Trend_Simulation!#REF!*Trend_Simulation!#REF!*4.31 -> #REF! | AC34: =SUM(U34:AB34) -> #REF! | AD34: =Summary!I33 -> 0.056421467 | AE34: =AC34-AD34 -> #REF! | AF34: =LN(1+AD34) -> 0.054887222
J35: =Summary!A34 -> 37802 | K35: =K34*(1+Summary!B34) -> 0.6305295 | L35: =L34*(1+Summary!H34) -> 1.1828222 | M35: =M34*(1+Summary!I34) -> 1.9581431 | N35: =MAX($K$3:K35) -> 0.99069493 | O35: =MAX($L$3:L35) -> 1.2081927 | P35: =K35/N35-1 -> -0.36354827 | Q35: =L35/O35-1 -> -0.020998691 | R35: =M35/MAX($M$3:M35)-1 -> -0.089426488 | T35: =Summary!A34 -> 37802 | U35: =Trend_Simulation!B130*Trend_Simulation!K130*4.31 -> 0.0090504253 | V35: =Trend_Simulation!C130*Trend_Simulation!L130*4.31 -> -0.019747169 | W35: =Trend_Simulation!D130*Trend_Simulation!M130*4.31 -> -0.043109554 | X35: =Trend_Simulation!E130*Trend_Simulation!N130*4.31 -> -0.0066212279 | Y35: =Trend_Simulation!F130*Trend_Simulation!O130*4.31 -> -0.0030389715 | Z35: =Trend_Simulation!G130*Trend_Simulation!P130*4.31 -> -0.00025088811 | AA35: =Trend_Simulation!H130*Trend_Simulation!Q130*4.31 -> -0.0025958228 | AB35: =Trend_Simulation!#REF!*Trend_Simulation!#REF!*4.31 -> #REF! | AC35: =SUM(U35:AB35) -> #REF! | AD35: =Summary!I34 -> -0.064928477 | AE35: =AC35-AD35 -> #REF! | AF35: =LN(1+AD35) -> -0.067132258
J36: =Summary!A35 -> 37833 | K36: =K35*(1+Summary!B35) -> 0.64094232 | L36: =L35*(1+Summary!H35) -> 1.1760406 | M36: =M35*(1+Summary!I35) -> 1.9107655 | N36: =MAX($K$3:K36) -> 0.99069493 | O36: =MAX($L$3:L36) -> 1.2081927 | P36: =K36/N36-1 -> -0.35303764 | Q36: =L36/O36-1 -> -0.026611748 | R36: =M36/MAX($M$3:M36)-1 -> -0.11145797 | T36: =Summary!A35 -> 37833 | U36: =Trend_Simulation!B131*Trend_Simulation!K131*4.31 -> 0.0042465014 | V36: =Trend_Simulation!C131*Trend_Simulation!L131*4.31 -> 0.0091956005 | W36: =Trend_Simulation!D131*Trend_Simulation!M131*4.31 -> 0.0039843162 | X36: =Trend_Simulation!E131*Trend_Simulation!N131*4.31 -> -0.048336642 | Y36: =Trend_Simulation!F131*Trend_Simulation!O131*4.31 -> -0.0046342077 | Z36: =Trend_Simulation!G131*Trend_Simulation!P131*4.31 -> 0.0079369536 | AA36: =Trend_Simulation!H131*Trend_Simulation!Q131*4.31 -> 0.0028963002 | AB36: =Trend_Simulation!#REF!*Trend_Simulation!#REF!*4.31 -> #REF! | AC36: =SUM(U36:AB36) -> #REF! | AD36: =Summary!I35 -> -0.024195167 | AE36: =AC36-AD36 -> #REF! | AF36: =LN(1+AD36) -> -0.024492678
J37: =Summary!A36 -> 37864 | K37: =K36*(1+Summary!B36) -> 0.65290599 | L37: =L36*(1+Summary!H36) -> 1.1669646 | M37: =M36*(1+Summary!I36) -> 1.848537 | N37: =MAX($K$3:K37) -> 0.99069493 | O37: =MAX($L$3:L37) -> 1.2081927 | P37: =K37/N37-1 -> -0.34096161 | Q37: =L37/O37-1 -> -0.034123746 | R37: =M37/MAX($M$3:M37)-1 -> -0.14039539 | T37: =Summary!A36 -> 37864 | U37: =Trend_Simulation!B132*Trend_Simulation!K132*4.31 -> 0.0061953773 | V37: =Trend_Simulation!C132*Trend_Simulation!L132*4.31 -> 0.024670589 | W37: =Trend_Simulation!D132*Trend_Simulation!M132*4.31 -> -0.062514743 | X37: =Trend_Simulation!E132*Trend_Simulation!N132*4.31 -> 0.0060391165 | Y37: =Trend_Simulation!F132*Trend_Simulation!O132*4.31 -> 0.0053255042 | Z37: =Trend_Simulation!G132*Trend_Simulation!P132*4.31 -> 0.0064053215 | AA37: =Trend_Simulation!H132*Trend_Simulation!Q132*4.31 -> -0.019383035 | AB37: =Trend_Simulation!#REF!*Trend_Simulation!#REF!*4.31 -> #REF! | AC37: =SUM(U37:AB37) -> #REF! | AD37: =Summary!I36 -> -0.032567306 | AE37: =AC37-AD37 -> #REF! | AF37: =LN(1+AD37) -> -0.033109423
A38: DATA QUALITY AND INTERPRETATION | J38: =Summary!A37 -> 37894 | K38: =K37*(1+Summary!B37) -> 0.64493021 | L38: =L37*(1+Summary!H37) -> 1.1778524 | M38: =M37*(1+Summary!I37) -> 1.9213188 | N38: =MAX($K$3:K38) -> 0.99069493 | O38: =MAX($L$3:L38) -> 1.2081927 | P38: =K38/N38-1 -> -0.3490123 | Q38: =L38/O38-1 -> -0.025112117 | R38: =M38/MAX($M$3:M38)-1 -> -0.1065505 | T38: =Summary!A37 -> 37894 | U38: =Trend_Simulation!B133*Trend_Simulation!K133*4.31 -> -0.014009157 | V38: =Trend_Simulation!C133*Trend_Simulation!L133*4.31 -> 0.010819096 | W38: =Trend_Simulation!D133*Trend_Simulation!M133*4.31 -> -0.011717732 | X38: =Trend_Simulation!E133*Trend_Simulation!N133*4.31 -> 0.035253708 | Y38: =Trend_Simulation!F133*Trend_Simulation!O133*4.31 -> -0.0038230448 | Z38: =Trend_Simulation!G133*Trend_Simulation!P133*4.31 -> -0.0040834721 | AA38: =Trend_Simulation!H133*Trend_Simulation!Q133*4.31 -> 0.027772918 | AB38: =Trend_Simulation!#REF!*Trend_Simulation!#REF!*4.31 -> #REF! | AC38: =SUM(U38:AB38) -> #REF! | AD38: =Summary!I37 -> 0.039372616 | AE38: =AC38-AD38 -> #REF! | AF38: =LN(1+AD38) -> 0.038617278
A39: All 310 observations in Summary!B2:B311, Summary!H2:H311, and Summary!I2:I311 are numeric and complete. The existing #VALUE! in Summary!J2 is an unrelated percentile formula and is excluded. Trend Levered Return uses approximately 4.31x exposure; the workbook does not visibly deduct financing costs, trading costs, slippage, or capacity effects, so reported leveraged results are best treated as gross backtest outcomes. | J39: =Summary!A38 -> 37925 | K39: =K38*(1+Summary!B38) -> 0.68096891 | L39: =L38*(1+Summary!H38) -> 1.1861633 | M39: =M38*(1+Summary!I38) -> 1.9785281 | N39: =MAX($K$3:K39) -> 0.99069493 | O39: =MAX($L$3:L39) -> 1.2081927 | P39: =K39/N39-1 -> -0.31263511 | Q39: =L39/O39-1 -> -0.018233368 | R39: =M39/MAX($M$3:M39)-1 -> -0.079947096 | T39: =Summary!A38 -> 37925 | U39: =Trend_Simulation!B134*Trend_Simulation!K134*4.31 -> 0.0076110319 | V39: =Trend_Simulation!C134*Trend_Simulation!L134*4.31 -> -0.0017276573 | W39: =Trend_Simulation!D134*Trend_Simulation!M134*4.31 -> 0.00026690278 | X39: =Trend_Simulation!E134*Trend_Simulation!N134*4.31 -> -0.015511313 | Y39: =Trend_Simulation!F134*Trend_Simulation!O134*4.31 -> 0.017870381 | Z39: =Trend_Simulation!G134*Trend_Simulation!P134*4.31 -> 0.012515345 | AA39: =Trend_Simulation!H134*Trend_Simulation!Q134*4.31 -> 0.0093864051 | AB39: =Trend_Simulation!#REF!*Trend_Simulation!#REF!*4.31 -> #REF! | AC39: =SUM(U39:AB39) -> #REF! | AD39: =Summary!I38 -> 0.029776062 | AE39: =AC39-AD39 -> #REF! | AF39: =LN(1+AD39) -> 0.029341363
J40: =Summary!A39 -> 37955 | K40: =K39*(1+Summary!B39) -> 0.68628609 | L40: =L39*(1+Summary!H39) -> 1.1879771 | M40: =M39*(1+Summary!I39) -> 1.9912954 | N40: =MAX($K$3:K40) -> 0.99069493 | O40: =MAX($L$3:L40) -> 1.2081927 | P40: =K40/N40-1 -> -0.30726798 | Q40: =L40/O40-1 -> -0.016732115 | R40: =M40/MAX($M$3:M40)-1 -> -0.074010045 | T40: =Summary!A39 -> 37955 | U40: =Trend_Simulation!B135*Trend_Simulation!K135*4.31 -> 0.0076639005 | V40: =Trend_Simulation!C135*Trend_Simulation!L135*4.31 -> 0.014595306 | W40: =Trend_Simulation!D135*Trend_Simulation!M135*4.31 -> -0.020645117 | X40: =Trend_Simulation!E135*Trend_Simulation!N135*4.31 -> -6.9767956e-05 | Y40: =Trend_Simulation!F135*Trend_Simulation!O135*4.31 -> 0.0024523796 | Z40: =Trend_Simulation!G135*Trend_Simulation!P135*4.31 -> 0.00071768102 | AA40: =Trend_Simulation!H135*Trend_Simulation!Q135*4.31 -> 0.0018761851 | AB40: =Trend_Simulation!#REF!*Trend_Simulation!#REF!*4.31 -> #REF! | AC40: =SUM(U40:AB40) -> #REF! | AD40: =Summary!I39 -> 0.0064529451 | AE40: =AC40-AD40 -> #REF! | AF40: =LN(1+AD40) -> 0.006432214
J41: =Summary!A40 -> 37986 | K41: =K40*(1+Summary!B40) -> 0.72151244 | L41: =L40*(1+Summary!H40) -> 1.2105025 | M41: =M40*(1+Summary!I40) -> 2.1506311 | N41: =MAX($K$3:K41) -> 0.99069493 | O41: =MAX($L$3:L41) -> 1.2105025 | P41: =K41/N41-1 -> -0.27171077 | Q41: =L41/O41-1 -> 0 | R41: =M41/MAX($M$3:M41)-1 -> 0 | T41: =Summary!A40 -> 37986 | U41: =Trend_Simulation!B136*Trend_Simulation!K136*4.31 -> 0.016029377 | V41: =Trend_Simulation!C136*Trend_Simulation!L136*4.31 -> 0.020310602 | W41: =Trend_Simulation!D136*Trend_Simulation!M136*4.31 -> 0.0024955641 | X41: =Trend_Simulation!E136*Trend_Simulation!N136*4.31 -> 0.0092390341 | Y41: =Trend_Simulation!F136*Trend_Simulation!O136*4.31 -> 0.016329423 | Z41: =Trend_Simulation!G136*Trend_Simulation!P136*4.31 -> 0.0045405839 | AA41: =Trend_Simulation!H136*Trend_Simulation!Q136*4.31 -> 0.012778012 | AB41: =Trend_Simulation!#REF!*Trend_Simulation!#REF!*4.31 -> #REF! | AC41: =SUM(U41:AB41) -> #REF! | AD41: =Summary!I40 -> 0.080016092 | AE41: =AC41-AD41 -> #REF! | AF41: =LN(1+AD41) -> 0.076975941
J42: =Summary!A41 -> 38017 | K42: =K41*(1+Summary!B41) -> 0.73421461 | L42: =L41*(1+Summary!H41) -> 1.2065361 | M42: =M41*(1+Summary!I41) -> 2.1208937 | N42: =MAX($K$3:K42) -> 0.99069493 | O42: =MAX($L$3:L42) -> 1.2105025 | P42: =K42/N42-1 -> -0.2588893 | Q42: =L42/O42-1 -> -0.0032766027 | R42: =M42/MAX($M$3:M42)-1 -> -0.013827263 | T42: =Summary!A41 -> 38017 | U42: =Trend_Simulation!B137*Trend_Simulation!K137*4.31 -> -0.0060665375 | V42: =Trend_Simulation!C137*Trend_Simulation!L137*4.31 -> -0.015004909 | W42: =Trend_Simulation!D137*Trend_Simulation!M137*4.31 -> -0.016030873 | X42: =Trend_Simulation!E137*Trend_Simulation!N137*4.31 -> 0.007786467 | Y42: =Trend_Simulation!F137*Trend_Simulation!O137*4.31 -> 0.005502385 | Z42: =Trend_Simulation!G137*Trend_Simulation!P137*4.31 -> 0.0024666718 | AA42: =Trend_Simulation!H137*Trend_Simulation!Q137*4.31 -> 0.0072246391 | AB42: =Trend_Simulation!#REF!*Trend_Simulation!#REF!*4.31 -> #REF! | AC42: =SUM(U42:AB42) -> #REF! | AD42: =Summary!I41 -> -0.013827263 | AE42: =AC42-AD42 -> #REF! | AF42: =LN(1+AD42) -> -0.01392375
A43: QUESTIONS FOR DEEPER ANALYSIS | J43: =Summary!A42 -> 38046 | K43: =K42*(1+Summary!B42) -> 0.74366738 | L43: =L42*(1+Summary!H42) -> 1.203528 | M43: =M42*(1+Summary!I42) -> 2.0985793 | N43: =MAX($K$3:K43) -> 0.99069493 | O43: =MAX($L$3:L43) -> 1.2105025 | P43: =K43/N43-1 -> -0.24934775 | Q43: =L43/O43-1 -> -0.0057616195 | R43: =M43/MAX($M$3:M43)-1 -> -0.024203028 | T43: =Summary!A42 -> 38046 | U43: =Trend_Simulation!B138*Trend_Simulation!K138*4.31 -> 0.014269793 | V43: =Trend_Simulation!C138*Trend_Simulation!L138*4.31 -> -0.0065682121 | W43: =Trend_Simulation!D138*Trend_Simulation!M138*4.31 -> -0.012846093 | X43: =Trend_Simulation!E138*Trend_Simulation!N138*4.31 -> 0.012724279 | Y43: =Trend_Simulation!F138*Trend_Simulation!O138*4.31 -> 0.0039894112 | Z43: =Trend_Simulation!G138*Trend_Simulation!P138*4.31 -> -0.0023798171 | AA43: =Trend_Simulation!H138*Trend_Simulation!Q138*4.31 -> -0.019934993 | AB43: =Trend_Simulation!#REF!*Trend_Simulation!#REF!*4.31 -> #REF! | AC43: =SUM(U43:AB43) -> #REF! | AD43: =Summary!I42 -> -0.010521245 | AE43: =AC43-AD43 -> #REF! | AF43: =LN(1+AD43) -> -0.010576985
A44: 1. How do trend results change with 2x, 3x, and volatility-capped leverage? 2. Which regimes contributed most: equity crashes, inflation shocks, or rate-hike cycles? 3. Which underlying asset sleeves generated the trend gains and drawdown periods? 4. How robust are results after financing costs, turnover, slippage, and signal delays? | J44: =Summary!A43 -> 38077 | K44: =K43*(1+Summary!B43) -> 0.73177756 | L44: =L43*(1+Summary!H43) -> 1.2291682 | M44: =M43*(1+Summary!I43) -> 2.2872495 | N44: =MAX($K$3:K44) -> 0.99069493 | O44: =MAX($L$3:L44) -> 1.2291682 | P44: =K44/N44-1 -> -0.26134924 | Q44: =L44/O44-1 -> 0 | R44: =M44/MAX($M$3:M44)-1 -> 0 | T44: =Summary!A43 -> 38077 | U44: =Trend_Simulation!B139*Trend_Simulation!K139*4.31 -> 0.0029030878 | V44: =Trend_Simulation!C139*Trend_Simulation!L139*4.31 -> 0.032915033 | W44: =Trend_Simulation!D139*Trend_Simulation!M139*4.31 -> 0.025021033 | X44: =Trend_Simulation!E139*Trend_Simulation!N139*4.31 -> 0.0098267611 | Y44: =Trend_Simulation!F139*Trend_Simulation!O139*4.31 -> -0.0051342877 | Z44: =Trend_Simulation!G139*Trend_Simulation!P139*4.31 -> -0.0036282747 | AA44: =Trend_Simulation!H139*Trend_Simulation!Q139*4.31 -> 0.029917819 | AB44: =Trend_Simulation!#REF!*Trend_Simulation!#REF!*4.31 -> #REF! | AC44: =SUM(U44:AB44) -> #REF! | AD44: =Summary!I43 -> 0.089903792 | AE44: =AC44-AD44 -> #REF! | AF44: =LN(1+AD44) -> 0.086089428
J45: =Summary!A44 -> 38107 | K45: =K44*(1+Summary!B44) -> 0.71944465 | L45: =L44*(1+Summary!H44) -> 1.2025514 | M45: =M44*(1+Summary!I44) -> 2.0782373 | N45: =MAX($K$3:K45) -> 0.99069493 | O45: =MAX($L$3:L45) -> 1.2291682 | P45: =K45/N45-1 -> -0.27379799 | Q45: =L45/O45-1 -> -0.021654377 | R45: =M45/MAX($M$3:M45)-1 -> -0.091381472 | T45: =Summary!A44 -> 38107 | U45: =Trend_Simulation!B140*Trend_Simulation!K140*4.31 -> 0.023595089 | V45: =Trend_Simulation!C140*Trend_Simulation!L140*4.31 -> -0.040469979 | W45: =Trend_Simulation!D140*Trend_Simulation!M140*4.31 -> 0.0026267356 | X45: =Trend_Simulation!E140*Trend_Simulation!N140*4.31 -> -0.031220844 | Y45: =Trend_Simulation!F140*Trend_Simulation!O140*4.31 -> -0.0055734754 | Z45: =Trend_Simulation!G140*Trend_Simulation!P140*4.31 -> -0.0046127625 | AA45: =Trend_Simulation!H140*Trend_Simulation!Q140*4.31 -> -0.037675128 | AB45: =Trend_Simulation!#REF!*Trend_Simulation!#REF!*4.31 -> #REF! | AC45: =SUM(U45:AB45) -> #REF! | AD45: =Summary!I44 -> -0.091381472 | AE45: =AC45-AD45 -> #REF! | AF45: =LN(1+AD45) -> -0.095829934
J46: =Summary!A45 -> 38138 | K46: =K45*(1+Summary!B45) -> 0.72867587 | L46: =L45*(1+Summary!H45) -> 1.2070411 | M46: =M45*(1+Summary!I45) -> 2.1109804 | N46: =MAX($K$3:K46) -> 0.99069493 | O46: =MAX($L$3:L46) -> 1.2291682 | P46: =K46/N46-1 -> -0.26448006 | Q46: =L46/O46-1 -> -0.018001752 | R46: =M46/MAX($M$3:M46)-1 -> -0.077065961 | T46: =Summary!A45 -> 38138 | U46: =Trend_Simulation!B141*Trend_Simulation!K141*4.31 -> 0.010696743 | V46: =Trend_Simulation!C141*Trend_Simulation!L141*4.31 -> 0.0064820605 | W46: =Trend_Simulation!D141*Trend_Simulation!M141*4.31 -> -0.0083313757 | X46: =Trend_Simulation!E141*Trend_Simulation!N141*4.31 -> -0.0042680711 | Y46: =Trend_Simulation!F141*Trend_Simulation!O141*4.31 -> 0.0044770534 | Z46: =Trend_Simulation!G141*Trend_Simulation!P141*4.31 -> 0.008448864 | AA46: =Trend_Simulation!H141*Trend_Simulation!Q141*4.31 -> -0.0014140132 | AB46: =Trend_Simulation!#REF!*Trend_Simulation!#REF!*4.31 -> #REF! | AC46: =SUM(U46:AB46) -> #REF! | AD46: =Summary!I45 -> 0.015755248 | AE46: =AC46-AD46 -> #REF! | AF46: =LN(1+AD46) -> 0.015632423
J47: =Summary!A46 -> 38168 | K47: =K46*(1+Summary!B46) -> 0.74204269 | L47: =L46*(1+Summary!H46) -> 1.2182283 | M47: =M46*(1+Summary!I46) -> 2.1935458 | N47: =MAX($K$3:K47) -> 0.99069493 | O47: =MAX($L$3:L47) -> 1.2291682 | P47: =K47/N47-1 -> -0.2509877 | Q47: =L47/O47-1 -> -0.0089002783 | R47: =M47/MAX($M$3:M47)-1 -> -0.04096788 | T47: =Summary!A46 -> 38168 | U47: =Trend_Simulation!B142*Trend_Simulation!K142*4.31 -> 0.0067583891 | V47: =Trend_Simulation!C142*Trend_Simulation!L142*4.31 -> -0.0018892822 | W47: =Trend_Simulation!D142*Trend_Simulation!M142*4.31 -> 0.021362885 | X47: =Trend_Simulation!E142*Trend_Simulation!N142*4.31 -> -0.00628963 | Y47: =Trend_Simulation!F142*Trend_Simulation!O142*4.31 -> 0.0063530001 | Z47: =Trend_Simulation!G142*Trend_Simulation!P142*4.31 -> 0.0061991019 | AA47: =Trend_Simulation!H142*Trend_Simulation!Q142*4.31 -> 0.0074519937 | AB47: =Trend_Simulation!#REF!*Trend_Simulation!#REF!*4.31 -> #REF! | AC47: =SUM(U47:AB47) -> #REF! | AD47: =Summary!I46 -> 0.039112309 | AE47: =AC47-AD47 -> #REF! | AF47: =LN(1+AD47) -> 0.0383668
J48: =Summary!A47 -> 38199 | K48: =K47*(1+Summary!B47) -> 0.71634296 | L48: =L47*(1+Summary!H47) -> 1.2134086 | M48: =M47*(1+Summary!I47) -> 2.1569227 | N48: =MAX($K$3:K48) -> 0.99069493 | O48: =MAX($L$3:L48) -> 1.2291682 | P48: =K48/N48-1 -> -0.27692881 | Q48: =L48/O48-1 -> -0.012821419 | R48: =M48/MAX($M$3:M48)-1 -> -0.056979699 | T48: =Summary!A47 -> 38199 | U48: =Trend_Simulation!B143*Trend_Simulation!K143*4.31 -> 0.031715138 | V48: =Trend_Simulation!C143*Trend_Simulation!L143*4.31 -> -0.0019756634 | W48: =Trend_Simulation!D143*Trend_Simulation!M143*4.31 -> 0.0033473936 | X48: =Trend_Simulation!E143*Trend_Simulation!N143*4.31 -> -0.0091251974 | Y48: =Trend_Simulation!F143*Trend_Simulation!O143*4.31 -> -0.012048853 | Z48: =Trend_Simulation!G143*Trend_Simulation!P143*4.31 -> -0.014324409 | AA48: =Trend_Simulation!H143*Trend_Simulation!Q143*4.31 -> -0.014640292 | AB48: =Trend_Simulation!#REF!*Trend_Simulation!#REF!*4.31 -> #REF! | AC48: =SUM(U48:AB48) -> #REF! | AD48: =Summary!I47 -> -0.016695812 | AE48: =AC48-AD48 -> #REF! | AF48: =LN(1+AD48) -> -0.016836758
A49: REGIME AND SLEEVE ATTRIBUTION | J49: =Summary!A48 -> 38230 | K49: =K48*(1+Summary!B48) -> 0.71826305 | L49: =L48*(1+Summary!H48) -> 1.2129898 | M49: =M48*(1+Summary!I48) -> 2.1537812 | N49: =MAX($K$3:K49) -> 0.99069493 | O49: =MAX($L$3:L49) -> 1.2291682 | P49: =K49/N49-1 -> -0.27499068 | Q49: =L49/O49-1 -> -0.013162132 | R49: =M49/MAX($M$3:M49)-1 -> -0.058353192 | T49: =Summary!A48 -> 38230 | U49: =Trend_Simulation!B144*Trend_Simulation!K144*4.31 -> -0.0067938995 | V49: =Trend_Simulation!C144*Trend_Simulation!L144*4.31 -> 0.018706958 | W49: =Trend_Simulation!D144*Trend_Simulation!M144*4.31 -> -0.037745122 | X49: =Trend_Simulation!E144*Trend_Simulation!N144*4.31 -> 0.018359179 | Y49: =Trend_Simulation!F144*Trend_Simulation!O144*4.31 -> 0.00092518083 | Z49: =Trend_Simulation!G144*Trend_Simulation!P144*4.31 -> -0.0042636383 | AA49: =Trend_Simulation!H144*Trend_Simulation!Q144*4.31 -> 0.0093237974 | AB49: =Trend_Simulation!#REF!*Trend_Simulation!#REF!*4.31 -> #REF! | AC49: =SUM(U49:AB49) -> #REF! | AD49: =Summary!I48 -> -0.0014564827 | AE49: =AC49-AD49 -> #REF! | AF49: =LN(1+AD49) -> -0.0014575444
A50: The strongest cumulative regimes were the post-2000 easing period and the 2009–2015 zero-rate/QE phase, when bond, equity-trend, and JPY sleeves contributed broadly. The GFC was especially favorable because short equity trends and long US duration produced positive contributions. The maximum drawdown from October 2022 through January 2024 was different: Japan bonds, EUR/USD, gold, and gasoil detracted together, overwhelming gains from JPY/USD, Nasdaq, and US 10Y trends. | J50: =Summary!A49 -> 38260 | K50: =K49*(1+Summary!B49) -> 0.72498338 | L50: =L49*(1+Summary!H49) -> 1.2349193 | M50: =M49*(1+Summary!I49) -> 2.3180994 | N50: =MAX($K$3:K50) -> 0.99069493 | O50: =MAX($L$3:L50) -> 1.2349193 | P50: =K50/N50-1 -> -0.26820723 | Q50: =L50/O50-1 -> 0 | R50: =M50/MAX($M$3:M50)-1 -> 0 | T50: =Summary!A49 -> 38260 | U50: =Trend_Simulation!B145*Trend_Simulation!K145*4.31 -> 0.046123276 | V50: =Trend_Simulation!C145*Trend_Simulation!L145*4.31 -> 0.0077083987 | W50: =Trend_Simulation!D145*Trend_Simulation!M145*4.31 -> 0.016639365 | X50: =Trend_Simulation!E145*Trend_Simulation!N145*4.31 -> 0.0020350437 | Y50: =Trend_Simulation!F145*Trend_Simulation!O145*4.31 -> 0.0033697466 | Z50: =Trend_Simulation!G145*Trend_Simulation!P145*4.31 -> 0.0060019244 | AA50: =Trend_Simulation!H145*Trend_Simulation!Q145*4.31 -> -0.003957747 | AB50: =Trend_Simulation!#REF!*Trend_Simulation!#REF!*4.31 -> #REF! | AC50: =SUM(U50:AB50) -> #REF! | AD50: =Summary!I49 -> 0.076292908 | AE50: =AC50-AD50 -> #REF! | AF50: =LN(1+AD50) -> 0.073522644
J51: =Summary!A50 -> 38291 | K51: =K50*(1+Summary!B50) -> 0.73487926 | L51: =L50*(1+Summary!H50) -> 1.2540662 | M51: =M50*(1+Summary!I50) -> 2.4697713 | N51: =MAX($K$3:K51) -> 0.99069493 | O51: =MAX($L$3:L51) -> 1.2540662 | P51: =K51/N51-1 -> -0.25821841 | Q51: =L51/O51-1 -> 0 | R51: =M51/MAX($M$3:M51)-1 -> 0 | T51: =Summary!A50 -> 38291 | U51: =Trend_Simulation!B146*Trend_Simulation!K146*4.31 -> 0.0091237356 | V51: =Trend_Simulation!C146*Trend_Simulation!L146*4.31 -> 0.0086226797 | W51: =Trend_Simulation!D146*Trend_Simulation!M146*4.31 -> 0.0022412872 | X51: =Trend_Simulation!E146*Trend_Simulation!N146*4.31 -> 0.0060807825 | Y51: =Trend_Simulation!F146*Trend_Simulation!O146*4.31 -> 0.005249778 | Z51: =Trend_Simulation!G146*Trend_Simulation!P146*4.31 -> 0.010631679 | AA51: =Trend_Simulation!H146*Trend_Simulation!Q146*4.31 -> 0.024874884 | AB51: =Trend_Simulation!#REF!*Trend_Simulation!#REF!*4.31 -> #REF! | AC51: =SUM(U51:AB51) -> #REF! | AD51: =Summary!I50 -> 0.065429412 | AE51: =AC51-AD51 -> #REF! | AF51: =LN(1+AD51) -> 0.063377922
J52: =Summary!A51 -> 38321 | K52: =K51*(1+Summary!B51) -> 0.76331142 | L52: =L51*(1+Summary!H51) -> 1.2707818 | M52: =M51*(1+Summary!I51) -> 2.6086931 | N52: =MAX($K$3:K52) -> 0.99069493 | O52: =MAX($L$3:L52) -> 1.2707818 | P52: =K52/N52-1 -> -0.22951919 | Q52: =L52/O52-1 -> 0 | R52: =M52/MAX($M$3:M52)-1 -> 0 | T52: =Summary!A51 -> 38321 | U52: =Trend_Simulation!B147*Trend_Simulation!K147*4.31 -> -0.0031527659 | V52: =Trend_Simulation!C147*Trend_Simulation!L147*4.31 -> 0.020704656 | W52: =Trend_Simulation!D147*Trend_Simulation!M147*4.31 -> 0.0060672946 | X52: =Trend_Simulation!E147*Trend_Simulation!N147*4.31 -> -0.014127017 | Y52: =Trend_Simulation!F147*Trend_Simulation!O147*4.31 -> 0.014743291 | Z52: =Trend_Simulation!G147*Trend_Simulation!P147*4.31 -> 0.012071875 | AA52: =Trend_Simulation!H147*Trend_Simulation!Q147*4.31 -> 0.021141128 | AB52: =Trend_Simulation!#REF!*Trend_Simulation!#REF!*4.31 -> #REF! | AC52: =SUM(U52:AB52) -> #REF! | AD52: =Summary!I51 -> 0.056248843 | AE52: =AC52-AD52 -> #REF! | AF52: =LN(1+AD52) -> 0.054723804
J53: =Summary!A52 -> 38352 | K53: =K52*(1+Summary!B52) -> 0.78782955 | L53: =L52*(1+Summary!H52) -> 1.2692647 | M53: =M52*(1+Summary!I52) -> 2.5955509 | N53: =MAX($K$3:K53) -> 0.99069493 | O53: =MAX($L$3:L53) -> 1.2707818 | P53: =K53/N53-1 -> -0.20477078 | Q53: =L53/O53-1 -> -0.001193804 | R53: =M53/MAX($M$3:M53)-1 -> -0.005037853 | T53: =Summary!A52 -> 38352 | U53: =Trend_Simulation!B148*Trend_Simulation!K148*4.31 -> -0.026950218 | V53: =Trend_Simulation!C148*Trend_Simulation!L148*4.31 -> -0.013177671 | W53: =Trend_Simulation!D148*Trend_Simulation!M148*4.31 -> 0.0069649018 | X53: =Trend_Simulation!E148*Trend_Simulation!N148*4.31 -> 0.0078758182 | Y53: =Trend_Simulation!F148*Trend_Simulation!O148*4.31 -> 0.012464186 | Z53: =Trend_Simulation!G148*Trend_Simulation!P148*4.31 -> 0.0067754722 | AA53: =Trend_Simulation!H148*Trend_Simulation!Q148*4.31 -> 0.00090221542 | AB53: =Trend_Simulation!#REF!*Trend_Simulation!#REF!*4.31 -> #REF! | AC53: =SUM(U53:AB53) -> #REF! | AD53: =Summary!I52 -> -0.005037853 | AE53: =AC53-AD53 -> #REF! | AF53: =LN(1+AD53) -> -0.0050505858
J54: =Summary!A53 -> 38383 | K54: =K53*(1+Summary!B53) -> 0.76707776 | L54: =L53*(1+Summary!H53) -> 1.2649373 | M54: =M53*(1+Summary!I53) -> 2.5582066 | N54: =MAX($K$3:K54) -> 0.99069493 | O54: =MAX($L$3:L54) -> 1.2707818 | P54: =K54/N54-1 -> -0.22571748 | Q54: =L54/O54-1 -> -0.0045991641 | R54: =M54/MAX($M$3:M54)-1 -> -0.019353165 | T54: =Summary!A53 -> 38383 | U54: =Trend_Simulation!B149*Trend_Simulation!K149*4.31 -> 0.015335354 | V54: =Trend_Simulation!C149*Trend_Simulation!L149*4.31 -> -0.014714802 | W54: =Trend_Simulation!D149*Trend_Simulation!M149*4.31 -> 0.015058646 | X54: =Trend_Simulation!E149*Trend_Simulation!N149*4.31 -> 0.0021494485 | Y54: =Trend_Simulation!F149*Trend_Simulation!O149*4.31 -> -0.010005112 | Z54: =Trend_Simulation!G149*Trend_Simulation!P149*4.31 -> -0.014368601 | AA54: =Trend_Simulation!H149*Trend_Simulation!Q149*4.31 -> -0.0081495782 | AB54: =Trend_Simulation!#REF!*Trend_Simulation!#REF!*4.31 -> #REF! | AC54: =SUM(U54:AB54) -> #REF! | AD54: =Summary!I53 -> -0.014387796 | AE54: =AC54-AD54 -> #REF! | AF54: =LN(1+AD54) -> -0.014492304
A55: MAJOR MARKET EVENT ATTRIBUTION | J55: =Summary!A54 -> 38411 | K55: =K54*(1+Summary!B54) -> 0.78147847 | L55: =L54*(1+Summary!H54) -> 1.2679865 | M55: =M54*(1+Summary!I54) -> 2.5842301 | N55: =MAX($K$3:K55) -> 0.99069493 | O55: =MAX($L$3:L55) -> 1.2707818 | P55: =K55/N55-1 -> -0.21118151 | Q55: =L55/O55-1 -> -0.0021996962 | R55: =M55/MAX($M$3:M55)-1 -> -0.0093774961 | T55: =Summary!A54 -> 38411 | U55: =Trend_Simulation!B150*Trend_Simulation!K150*4.31 -> 0.026825317 | V55: =Trend_Simulation!C150*Trend_Simulation!L150*4.31 -> 0.01205341 | W55: =Trend_Simulation!D150*Trend_Simulation!M150*4.31 -> -0.017323195 | X55: =Trend_Simulation!E150*Trend_Simulation!N150*4.31 -> -0.0094436049 | Y55: =Trend_Simulation!F150*Trend_Simulation!O150*4.31 -> 0.0070100536 | Z55: =Trend_Simulation!G150*Trend_Simulation!P150*4.31 -> -0.0015784765 | AA55: =Trend_Simulation!H150*Trend_Simulation!Q150*4.31 -> -0.0071540148 | AB55: =Trend_Simulation!#REF!*Trend_Simulation!#REF!*4.31 -> #REF! | AC55: =SUM(U55:AB55) -> #REF! | AD55: =Summary!I54 -> 0.01017254 | AE55: =AC55-AD55 -> #REF! | AF55: =LN(1+AD55) -> 0.010121148
A56: Regime | B56: Levered Trend Return | C56: Commodities | D56: Bonds | E56: Equities | F56: FX | G56: Top Driver | H56: Top Detractor | J56: =Summary!A55 -> 38442 | K56: =K55*(1+Summary!B55) -> 0.76567462 | L56: =L55*(1+Summary!H55) -> 1.2695076 | M56: =M55*(1+Summary!I55) -> 2.5973126 | N56: =MAX($K$3:K56) -> 0.99069493 | O56: =MAX($L$3:L56) -> 1.2707818 | P56: =K56/N56-1 -> -0.22713381 | Q56: =L56/O56-1 -> -0.0010027105 | R56: =M56/MAX($M$3:M56)-1 -> -0.0043625537 | T56: =Summary!A55 -> 38442 | U56: =Trend_Simulation!B151*Trend_Simulation!K151*4.31 -> 0.027209957 | V56: =Trend_Simulation!C151*Trend_Simulation!L151*4.31 -> -0.0079446488 | W56: =Trend_Simulation!D151*Trend_Simulation!M151*4.31 -> 0.02212178 | X56: =Trend_Simulation!E151*Trend_Simulation!N151*4.31 -> -0.0040159582 | Y56: =Trend_Simulation!F151*Trend_Simulation!O151*4.31 -> -0.0076357592 | Z56: =Trend_Simulation!G151*Trend_Simulation!P151*4.31 -> -0.0047671416 | AA56: =Trend_Simulation!H151*Trend_Simulation!Q151*4.31 -> -0.019797847 | AB56: =Trend_Simulation!#REF!*Trend_Simulation!#REF!*4.31 -> #REF! | AC56: =SUM(U56:AB56) -> #REF! | AD56: =Summary!I55 -> 0.0050624152 | AE56: =AC56-AD56 -> #REF! | AF56: =LN(1+AD56) -> 0.0050496442
A57: Dot-com Bust / 2001 Recession | B57: =EXP(SUMIFS($AF$3:$AF$312,$T$3:$T$312,">="&$AH$3,$T$3:$T$312,"<="&$AI$3))-1 -> 0.97779004 | C57: =SUMIFS($U$3:$U$312,$T$3:$T$312,">="&$AH$3,$T$3:$T$312,"<="&$AI$3)+SUMIFS($V$3:$V$312,$T$3:$T$312,">="&$AH$3,$T$3:$T$312,"<="&$AI$3) -> 0.029996821 | D57: =SUMIFS($W$3:$W$312,$T$3:$T$312,">="&$AH$3,$T$3:$T$312,"<="&$AI$3)+SUMIFS($X$3:$X$312,$T$3:$T$312,">="&$AH$3,$T$3:$T$312,"<="&$AI$3) -> 0.41243286 | E57: =SUMIFS($Y$3:$Y$312,$T$3:$T$312,">="&$AH$3,$T$3:$T$312,"<="&$AI$3)+SUMIFS($Z$3:$Z$312,$T$3:$T$312,">="&$AH$3,$T$3:$T$312,"<="&$AI$3) -> 0.20836478 | F57: =SUMIFS($AA$3:$AA$312,$T$3:$T$312,">="&$AH$3,$T$3:$T$312,"<="&$AI$3)+SUMIFS($AB$3:$AB$312,$T$3:$T$312,">="&$AH$3,$T$3:$T$312,"<="&$AI$3) -> #REF! | G57: Japan Bonds | H57: Gasoil | J57: =Summary!A56 -> 38472 | K57: =K56*(1+Summary!B56) -> 0.74913226 | L57: =L56*(1+Summary!H56) -> 1.2546425 | M57: =M56*(1+Summary!I56) -> 2.4689707 | N57: =MAX($K$3:K57) -> 0.99069493 | O57: =MAX($L$3:L57) -> 1.2707818 | P57: =K57/N57-1 -> -0.24383153 | Q57: =L57/O57-1 -> -0.012700292 | R57: =M57/MAX($M$3:M57)-1 -> -0.053560328 | T57: =Summary!A56 -> 38472 | U57: =Trend_Simulation!B152*Trend_Simulation!K152*4.31 -> -0.014307352 | V57: =Trend_Simulation!C152*Trend_Simulation!L152*4.31 -> -0.0044312833 | W57: =Trend_Simulation!D152*Trend_Simulation!M152*4.31 -> 0.013298978 | X57: =Trend_Simulation!E152*Trend_Simulation!N152*4.31 -> -0.014814118 | Y57: =Trend_Simulation!F152*Trend_Simulation!O152*4.31 -> -0.0081761056 | Z57: =Trend_Simulation!G152*Trend_Simulation!P152*4.31 -> -0.010195191 | AA57: =Trend_Simulation!H152*Trend_Simulation!Q152*4.31 -> -0.01184211 | AB57: =Trend_Simulation!#REF!*Trend_Simulation!#REF!*4.31 -> #REF! | AC57: =SUM(U57:AB57) -> #REF! | AD57: =Summary!I56 -> -0.049413342 | AE57: =AC57-AD57 -> #REF! | AF57: =LN(1+AD57) -> -0.050675951
A58: Credit Expansion | B58: =EXP(SUMIFS($AF$3:$AF$312,$T$3:$T$312,">="&$AH$4,$T$3:$T$312,"<="&$AI$4))-1 -> 0.53723973 | C58: =SUMIFS($U$3:$U$312,$T$3:$T$312,">="&$AH$4,$T$3:$T$312,"<="&$AI$4)+SUMIFS($V$3:$V$312,$T$3:$T$312,">="&$AH$4,$T$3:$T$312,"<="&$AI$4) -> 0.48211571 | D58: =SUMIFS($W$3:$W$312,$T$3:$T$312,">="&$AH$4,$T$3:$T$312,"<="&$AI$4)+SUMIFS($X$3:$X$312,$T$3:$T$312,">="&$AH$4,$T$3:$T$312,"<="&$AI$4) -> -0.0039331281 | E58: =SUMIFS($Y$3:$Y$312,$T$3:$T$312,">="&$AH$4,$T$3:$T$312,"<="&$AI$4)+SUMIFS($Z$3:$Z$312,$T$3:$T$312,">="&$AH$4,$T$3:$T$312,"<="&$AI$4) -> -0.015481722 | F58: =SUMIFS($AA$3:$AA$312,$T$3:$T$312,">="&$AH$4,$T$3:$T$312,"<="&$AI$4)+SUMIFS($AB$3:$AB$312,$T$3:$T$312,">="&$AH$4,$T$3:$T$312,"<="&$AI$4) -> #REF! | G58: Gold | H58: Nasdaq 100 | J58: =Summary!A57 -> 38503 | K58: =K57*(1+Summary!B57) -> 0.7709918 | L58: =L57*(1+Summary!H57) -> 1.2433869 | M58: =M57*(1+Summary!I57) -> 2.3754999 | N58: =MAX($K$3:K58) -> 0.99069493 | O58: =MAX($L$3:L58) -> 1.2707818 | P58: =K58/N58-1 -> -0.22176668 | Q58: =L58/O58-1 -> -0.021557492 | R58: =M58/MAX($M$3:M58)-1 -> -0.089390824 | T58: =Summary!A57 -> 38503 | U58: =Trend_Simulation!B153*Trend_Simulation!K153*4.31 -> -0.0059253669 | V58: =Trend_Simulation!C153*Trend_Simulation!L153*4.31 -> -0.01722069 | W58: =Trend_Simulation!D153*Trend_Simulation!M153*4.31 -> 0.0022550207 | X58: =Trend_Simulation!E153*Trend_Simulation!N153*4.31 -> 0.01134831 | Y58: =Trend_Simulation!F153*Trend_Simulation!O153*4.31 -> 0.011283285 | Z58: =Trend_Simulation!G153*Trend_Simulation!P153*4.31 -> -0.02011974 | AA58: =Trend_Simulation!H153*Trend_Simulation!Q153*4.31 -> -0.020286414 | AB58: =Trend_Simulation!#REF!*Trend_Simulation!#REF!*4.31 -> #REF! | AC58: =SUM(U58:AB58) -> #REF! | AD58: =Summary!I57 -> -0.037858194 | AE58: =AC58-AD58 -> #REF! | AF58: =LN(1+AD58) -> -0.038593432
A59: Global Financial Crisis | B59: =EXP(SUMIFS($AF$3:$AF$312,$T$3:$T$312,">="&$AH$5,$T$3:$T$312,"<="&$AI$5))-1 -> 0.44133732 | C59: =SUMIFS($U$3:$U$312,$T$3:$T$312,">="&$AH$5,$T$3:$T$312,"<="&$AI$5)+SUMIFS($V$3:$V$312,$T$3:$T$312,">="&$AH$5,$T$3:$T$312,"<="&$AI$5) -> 0.0081018974 | D59: =SUMIFS($W$3:$W$312,$T$3:$T$312,">="&$AH$5,$T$3:$T$312,"<="&$AI$5)+SUMIFS($X$3:$X$312,$T$3:$T$312,">="&$AH$5,$T$3:$T$312,"<="&$AI$5) -> 0.18085662 | E59: =SUMIFS($Y$3:$Y$312,$T$3:$T$312,">="&$AH$5,$T$3:$T$312,"<="&$AI$5)+SUMIFS($Z$3:$Z$312,$T$3:$T$312,">="&$AH$5,$T$3:$T$312,"<="&$AI$5) -> 0.15612634 | F59: =SUMIFS($AA$3:$AA$312,$T$3:$T$312,">="&$AH$5,$T$3:$T$312,"<="&$AI$5)+SUMIFS($AB$3:$AB$312,$T$3:$T$312,">="&$AH$5,$T$3:$T$312,"<="&$AI$5) -> #REF! | G59: S&P 500 | H59: Nasdaq 100 | J59: =Summary!A58 -> 38533 | K59: =K58*(1+Summary!B58) -> 0.76988406 | L59: =L58*(1+Summary!H58) -> 1.2507157 | M59: =M58*(1+Summary!I58) -> 2.4345873 | N59: =MAX($K$3:K59) -> 0.99069493 | O59: =MAX($L$3:L59) -> 1.2707818 | P59: =K59/N59-1 -> -0.22288483 | Q59: =L59/O59-1 -> -0.01579032 | R59: =M59/MAX($M$3:M59)-1 -> -0.06674062 | T59: =Summary!A58 -> 38533 | U59: =Trend_Simulation!B154*Trend_Simulation!K154*4.31 -> 0.025875267 | V59: =Trend_Simulation!C154*Trend_Simulation!L154*4.31 -> 0.016467601 | W59: =Trend_Simulation!D154*Trend_Simulation!M154*4.31 -> 0.011694685 | X59: =Trend_Simulation!E154*Trend_Simulation!N154*4.31 -> 0.0013528005 | Y59: =Trend_Simulation!F154*Trend_Simulation!O154*4.31 -> -0.00055430161 | Z59: =Trend_Simulation!G154*Trend_Simulation!P154*4.31 -> -0.008225562 | AA59: =Trend_Simulation!H154*Trend_Simulation!Q154*4.31 -> -0.021206326 | AB59: =Trend_Simulation!#REF!*Trend_Simulation!#REF!*4.31 -> #REF! | AC59: =SUM(U59:AB59) -> #REF! | AD59: =Summary!I58 -> 0.024873683 | AE59: =AC59-AD59 -> #REF! | AF59: =LN(1+AD59) -> 0.024569369
A60: Post-GFC / Euro Stress | B60: =EXP(SUMIFS($AF$3:$AF$312,$T$3:$T$312,">="&$AH$6,$T$3:$T$312,"<="&$AI$6))-1 -> 0.96544114 | C60: =SUMIFS($U$3:$U$312,$T$3:$T$312,">="&$AH$6,$T$3:$T$312,"<="&$AI$6)+SUMIFS($V$3:$V$312,$T$3:$T$312,">="&$AH$6,$T$3:$T$312,"<="&$AI$6) -> 0.1872864 | D60: =SUMIFS($W$3:$W$312,$T$3:$T$312,">="&$AH$6,$T$3:$T$312,"<="&$AI$6)+SUMIFS($X$3:$X$312,$T$3:$T$312,">="&$AH$6,$T$3:$T$312,"<="&$AI$6) -> 0.29978329 | E60: =SUMIFS($Y$3:$Y$312,$T$3:$T$312,">="&$AH$6,$T$3:$T$312,"<="&$AI$6)+SUMIFS($Z$3:$Z$312,$T$3:$T$312,">="&$AH$6,$T$3:$T$312,"<="&$AI$6) -> 0.14126207 | F60: =SUMIFS($AA$3:$AA$312,$T$3:$T$312,">="&$AH$6,$T$3:$T$312,"<="&$AI$6)+SUMIFS($AB$3:$AB$312,$T$3:$T$312,">="&$AH$6,$T$3:$T$312,"<="&$AI$6) -> #REF! | G60: Japan Bonds | H60: EUR/USD | J60: =Summary!A59 -> 38564 | K60: =K59*(1+Summary!B59) -> 0.79646998 | L60: =L59*(1+Summary!H59) -> 1.2411867 | M60: =M59*(1+Summary!I59) -> 2.3563117 | N60: =MAX($K$3:K60) -> 0.99069493 | O60: =MAX($L$3:L60) -> 1.2707818 | P60: =K60/N60-1 -> -0.1960492 | Q60: =L60/O60-1 -> -0.023288855 | R60: =M60/MAX($M$3:M60)-1 -> -0.096746312 | T60: =Summary!A59 -> 38564 | U60: =Trend_Simulation!B155*Trend_Simulation!K155*4.31 -> -0.00069970813 | V60: =Trend_Simulation!C155*Trend_Simulation!L155*4.31 -> -0.0063182768 | W60: =Trend_Simulation!D155*Trend_Simulation!M155*4.31 -> -0.014919731 | X60: =Trend_Simulation!E155*Trend_Simulation!N155*4.31 -> -0.016438219 | Y60: =Trend_Simulation!F155*Trend_Simulation!O155*4.31 -> 0.01388732 | Z60: =Trend_Simulation!G155*Trend_Simulation!P155*4.31 -> -0.018096386 | AA60: =Trend_Simulation!H155*Trend_Simulation!Q155*4.31 -> 0.009747803 | AB60: =Trend_Simulation!#REF!*Trend_Simulation!#REF!*4.31 -> #REF! | AC60: =SUM(U60:AB60) -> #REF! | AD60: =Summary!I59 -> -0.032151503 | AE60: =AC60-AD60 -> #REF! | AF60: =LN(1+AD60) -> -0.032679715
A61: Low-Vol Expansion | B61: =EXP(SUMIFS($AF$3:$AF$312,$T$3:$T$312,">="&$AH$7,$T$3:$T$312,"<="&$AI$7))-1 -> 0.93718953 | C61: =SUMIFS($U$3:$U$312,$T$3:$T$312,">="&$AH$7,$T$3:$T$312,"<="&$AI$7)+SUMIFS($V$3:$V$312,$T$3:$T$312,">="&$AH$7,$T$3:$T$312,"<="&$AI$7) -> 0.15578289 | D61: =SUMIFS($W$3:$W$312,$T$3:$T$312,">="&$AH$7,$T$3:$T$312,"<="&$AI$7)+SUMIFS($X$3:$X$312,$T$3:$T$312,">="&$AH$7,$T$3:$T$312,"<="&$AI$7) -> 0.14117232 | E61: =SUMIFS($Y$3:$Y$312,$T$3:$T$312,">="&$AH$7,$T$3:$T$312,"<="&$AI$7)+SUMIFS($Z$3:$Z$312,$T$3:$T$312,">="&$AH$7,$T$3:$T$312,"<="&$AI$7) -> 0.30090211 | F61: =SUMIFS($AA$3:$AA$312,$T$3:$T$312,">="&$AH$7,$T$3:$T$312,"<="&$AI$7)+SUMIFS($AB$3:$AB$312,$T$3:$T$312,">="&$AH$7,$T$3:$T$312,"<="&$AI$7) -> #REF! | G61: Nasdaq 100 | H61: Gold | J61: =Summary!A60 -> 38595 | K61: =K60*(1+Summary!B60) -> 0.78664796 | L61: =L60*(1+Summary!H60) -> 1.2491979 | M61: =M60*(1+Summary!I60) -> 2.4204925 | N61: =MAX($K$3:K61) -> 0.99069493 | O61: =MAX($L$3:L61) -> 1.2707818 | P61: =K61/N61-1 -> -0.20596347 | Q61: =L61/O61-1 -> -0.016984709 | R61: =M61/MAX($M$3:M61)-1 -> -0.072143636 | T61: =Summary!A60 -> 38595 | U61: =Trend_Simulation!B156*Trend_Simulation!K156*4.31 -> 0.029706654 | V61: =Trend_Simulation!C156*Trend_Simulation!L156*4.31 -> 0.0020161861 | W61: =Trend_Simulation!D156*Trend_Simulation!M156*4.31 -> -0.0036069228 | X61: =Trend_Simulation!E156*Trend_Simulation!N156*4.31 -> 0.013225406 | Y61: =Trend_Simulation!F156*Trend_Simulation!O156*4.31 -> -0.0052822059 | Z61: =Trend_Simulation!G156*Trend_Simulation!P156*4.31 -> -0.0043662428 | AA61: =Trend_Simulation!H156*Trend_Simulation!Q156*4.31 -> -0.0038741356 | AB61: =Trend_Simulation!#REF!*Trend_Simulation!#REF!*4.31 -> #REF! | AC61: =SUM(U61:AB61) -> #REF! | AD61: =Summary!I60 -> 0.027237836 | AE61: =AC61-AD61 -> #REF! | AF61: =LN(1+AD61) -> 0.026873488
A62: COVID Shock | B62: =EXP(SUMIFS($AF$3:$AF$312,$T$3:$T$312,">="&$AH$8,$T$3:$T$312,"<="&$AI$8))-1 -> 0.051653053 | C62: =SUMIFS($U$3:$U$312,$T$3:$T$312,">="&$AH$8,$T$3:$T$312,"<="&$AI$8)+SUMIFS($V$3:$V$312,$T$3:$T$312,">="&$AH$8,$T$3:$T$312,"<="&$AI$8) -> 0.079850522 | D62: =SUMIFS($W$3:$W$312,$T$3:$T$312,">="&$AH$8,$T$3:$T$312,"<="&$AI$8)+SUMIFS($X$3:$X$312,$T$3:$T$312,">="&$AH$8,$T$3:$T$312,"<="&$AI$8) -> 0.03785766 | E62: =SUMIFS($Y$3:$Y$312,$T$3:$T$312,">="&$AH$8,$T$3:$T$312,"<="&$AI$8)+SUMIFS($Z$3:$Z$312,$T$3:$T$312,">="&$AH$8,$T$3:$T$312,"<="&$AI$8) -> -0.066717323 | F62: =SUMIFS($AA$3:$AA$312,$T$3:$T$312,">="&$AH$8,$T$3:$T$312,"<="&$AI$8)+SUMIFS($AB$3:$AB$312,$T$3:$T$312,">="&$AH$8,$T$3:$T$312,"<="&$AI$8) -> #REF! | G62: US 10Y | H62: S&P 500 | J62: =Summary!A61 -> 38625 | K62: =K61*(1+Summary!B61) -> 0.7907097 | L62: =L61*(1+Summary!H61) -> 1.2526078 | M62: =M61*(1+Summary!I61) -> 2.4483746 | N62: =MAX($K$3:K62) -> 0.99069493 | O62: =MAX($L$3:L62) -> 1.2707818 | P62: =K62/N62-1 -> -0.20186359 | Q62: =L62/O62-1 -> -0.014301406 | R62: =M62/MAX($M$3:M62)-1 -> -0.061455483 | T62: =Summary!A61 -> 38625 | U62: =Trend_Simulation!B157*Trend_Simulation!K157*4.31 -> -0.0039494469 | V62: =Trend_Simulation!C157*Trend_Simulation!L157*4.31 -> 0.029677282 | W62: =Trend_Simulation!D157*Trend_Simulation!M157*4.31 -> -0.019888648 | X62: =Trend_Simulation!E157*Trend_Simulation!N157*4.31 -> -0.014431877 | Y62: =Trend_Simulation!F157*Trend_Simulation!O157*4.31 -> 0.0021851872 | Z62: =Trend_Simulation!G157*Trend_Simulation!P157*4.31 -> 0.0026611864 | AA62: =Trend_Simulation!H157*Trend_Simulation!Q157*4.31 -> 0.015511175 | AB62: =Trend_Simulation!#REF!*Trend_Simulation!#REF!*4.31 -> #REF! | AC62: =SUM(U62:AB62) -> #REF! | AD62: =Summary!I61 -> 0.011519189 | AE62: =AC62-AD62 -> #REF! | AF62: =LN(1+AD62) -> 0.011453349
A63: Reopening & Inflation Surge | B63: =EXP(SUMIFS($AF$3:$AF$312,$T$3:$T$312,">="&$AH$9,$T$3:$T$312,"<="&$AI$9))-1 -> 0.086694255 | C63: =SUMIFS($U$3:$U$312,$T$3:$T$312,">="&$AH$9,$T$3:$T$312,"<="&$AI$9)+SUMIFS($V$3:$V$312,$T$3:$T$312,">="&$AH$9,$T$3:$T$312,"<="&$AI$9) -> -0.0049399225 | D63: =SUMIFS($W$3:$W$312,$T$3:$T$312,">="&$AH$9,$T$3:$T$312,"<="&$AI$9)+SUMIFS($X$3:$X$312,$T$3:$T$312,">="&$AH$9,$T$3:$T$312,"<="&$AI$9) -> -0.038886839 | E63: =SUMIFS($Y$3:$Y$312,$T$3:$T$312,">="&$AH$9,$T$3:$T$312,"<="&$AI$9)+SUMIFS($Z$3:$Z$312,$T$3:$T$312,">="&$AH$9,$T$3:$T$312,"<="&$AI$9) -> 0.14877464 | F63: =SUMIFS($AA$3:$AA$312,$T$3:$T$312,">="&$AH$9,$T$3:$T$312,"<="&$AI$9)+SUMIFS($AB$3:$AB$312,$T$3:$T$312,">="&$AH$9,$T$3:$T$312,"<="&$AI$9) -> #REF! | G63: Nasdaq 100 | H63: US 10Y | J63: =Summary!A62 -> 38656 | K63: =K62*(1+Summary!B62) -> 0.77497969 | L63: =L62*(1+Summary!H62) -> 1.2485983 | M63: =M62*(1+Summary!I62) -> 2.4153018 | N63: =MAX($K$3:K63) -> 0.99069493 | O63: =MAX($L$3:L63) -> 1.2707818 | P63: =K63/N63-1 -> -0.21774133 | Q63: =L63/O63-1 -> -0.01745659 | R63: =M63/MAX($M$3:M63)-1 -> -0.074133402 | T63: =Summary!A62 -> 38656 | U63: =Trend_Simulation!B158*Trend_Simulation!K158*4.31 -> -0.018973216 | V63: =Trend_Simulation!C158*Trend_Simulation!L158*4.31 -> -0.0041507626 | W63: =Trend_Simulation!D158*Trend_Simulation!M158*4.31 -> -0.0063294456 | X63: =Trend_Simulation!E158*Trend_Simulation!N158*4.31 -> 0.010094739 | Y63: =Trend_Simulation!F158*Trend_Simulation!O158*4.31 -> -0.0098308659 | Z63: =Trend_Simulation!G158*Trend_Simulation!P158*4.31 -> -0.004576272 | AA63: =Trend_Simulation!H158*Trend_Simulation!Q158*4.31 -> 0.019969673 | AB63: =Trend_Simulation!#REF!*Trend_Simulation!#REF!*4.31 -> #REF! | AC63: =SUM(U63:AB63) -> #REF! | AD63: =Summary!I62 -> -0.013508064 | AE63: =AC63-AD63 -> #REF! | AF63: =LN(1+AD63) -> -0.013600128
A64: Rapid Tightening | B64: =EXP(SUMIFS($AF$3:$AF$312,$T$3:$T$312,">="&$AH$10,$T$3:$T$312,"<="&$AI$10))-1 -> 0.097904678 | C64: =SUMIFS($U$3:$U$312,$T$3:$T$312,">="&$AH$10,$T$3:$T$312,"<="&$AI$10)+SUMIFS($V$3:$V$312,$T$3:$T$312,">="&$AH$10,$T$3:$T$312,"<="&$AI$10) -> -0.084582935 | D64: =SUMIFS($W$3:$W$312,$T$3:$T$312,">="&$AH$10,$T$3:$T$312,"<="&$AI$10)+SUMIFS($X$3:$X$312,$T$3:$T$312,">="&$AH$10,$T$3:$T$312,"<="&$AI$10) -> -0.046023582 | E64: =SUMIFS($Y$3:$Y$312,$T$3:$T$312,">="&$AH$10,$T$3:$T$312,"<="&$AI$10)+SUMIFS($Z$3:$Z$312,$T$3:$T$312,">="&$AH$10,$T$3:$T$312,"<="&$AI$10) -> 0.078108908 | F64: =SUMIFS($AA$3:$AA$312,$T$3:$T$312,">="&$AH$10,$T$3:$T$312,"<="&$AI$10)+SUMIFS($AB$3:$AB$312,$T$3:$T$312,">="&$AH$10,$T$3:$T$312,"<="&$AI$10) -> #REF! | G64: JPY/USD | H64: Japan Bonds | J64: =Summary!A63 -> 38686 | K64: =K63*(1+Summary!B63) -> 0.80141792 | L64: =L63*(1+Summary!H63) -> 1.2693555 | M64: =M63*(1+Summary!I63) -> 2.5847477 | N64: =MAX($K$3:K64) -> 0.99069493 | O64: =MAX($L$3:L64) -> 1.2707818 | P64: =K64/N64-1 -> -0.19105479 | Q64: =L64/O64-1 -> -0.0011223524 | R64: =M64/MAX($M$3:M64)-1 -> -0.0091790887 | T64: =Summary!A63 -> 38686 | U64: =Trend_Simulation!B159*Trend_Simulation!K159*4.31 -> -0.017322191 | V64: =Trend_Simulation!C159*Trend_Simulation!L159*4.31 -> 0.021253533 | W64: =Trend_Simulation!D159*Trend_Simulation!M159*4.31 -> 0.014931649 | X64: =Trend_Simulation!E159*Trend_Simulation!N159*4.31 -> -0.0017546992 | Y64: =Trend_Simulation!F159*Trend_Simulation!O159*4.31 -> 0.017808757 | Z64: =Trend_Simulation!G159*Trend_Simulation!P159*4.31 -> 0.016773604 | AA64: =Trend_Simulation!H159*Trend_Simulation!Q159*4.31 -> 0.019960701 | AB64: =Trend_Simulation!#REF!*Trend_Simulation!#REF!*4.31 -> #REF! | AC64: =SUM(U64:AB64) -> #REF! | AD64: =Summary!I63 -> 0.070155154 | AE64: =AC64-AD64 -> #REF! | AF64: =LN(1+AD64) -> 0.067803642
A65: Easing / Late Cycle | B65: =EXP(SUMIFS($AF$3:$AF$312,$T$3:$T$312,">="&$AH$11,$T$3:$T$312,"<="&$AI$11))-1 -> 0.8550697 | C65: =SUMIFS($U$3:$U$312,$T$3:$T$312,">="&$AH$11,$T$3:$T$312,"<="&$AI$11)+SUMIFS($V$3:$V$312,$T$3:$T$312,">="&$AH$11,$T$3:$T$312,"<="&$AI$11) -> 0.37398212 | D65: =SUMIFS($W$3:$W$312,$T$3:$T$312,">="&$AH$11,$T$3:$T$312,"<="&$AI$11)+SUMIFS($X$3:$X$312,$T$3:$T$312,">="&$AH$11,$T$3:$T$312,"<="&$AI$11) -> 0.089343767 | E65: =SUMIFS($Y$3:$Y$312,$T$3:$T$312,">="&$AH$11,$T$3:$T$312,"<="&$AI$11)+SUMIFS($Z$3:$Z$312,$T$3:$T$312,">="&$AH$11,$T$3:$T$312,"<="&$AI$11) -> 0.17779889 | F65: =SUMIFS($AA$3:$AA$312,$T$3:$T$312,">="&$AH$11,$T$3:$T$312,"<="&$AI$11)+SUMIFS($AB$3:$AB$312,$T$3:$T$312,">="&$AH$11,$T$3:$T$312,"<="&$AI$11) -> #REF! | G65: Gasoil | H65: EUR/USD | J65: =Summary!A64 -> 38717 | K65: =K64*(1+Summary!B64) -> 0.79861162 | L65: =L64*(1+Summary!H64) -> 1.2657922 | M65: =M64*(1+Summary!I64) -> 2.5541278 | N65: =MAX($K$3:K65) -> 0.99069493 | O65: =MAX($L$3:L65) -> 1.2707818 | P65: =K65/N65-1 -> -0.19388744 | Q65: =L65/O65-1 -> -0.0039264014 | R65: =M65/MAX($M$3:M65)-1 -> -0.020916732 | T65: =Summary!A64 -> 38717 | U65: =Trend_Simulation!B160*Trend_Simulation!K160*4.31 -> -0.00044729633 | V65: =Trend_Simulation!C160*Trend_Simulation!L160*4.31 -> 0.014256025 | W65: =Trend_Simulation!D160*Trend_Simulation!M160*4.31 -> -0.0056005607 | X65: =Trend_Simulation!E160*Trend_Simulation!N160*4.31 -> -0.0060546034 | Y65: =Trend_Simulation!F160*Trend_Simulation!O160*4.31 -> -0.0018780563 | Z65: =Trend_Simulation!G160*Trend_Simulation!P160*4.31 -> -0.0062257962 | AA65: =Trend_Simulation!H160*Trend_Simulation!Q160*4.31 -> -0.0061487428 | AB65: =Trend_Simulation!#REF!*Trend_Simulation!#REF!*4.31 -> #REF! | AC65: =SUM(U65:AB65) -> #REF! | AD65: =Summary!I64 -> -0.011846383 | AE65: =AC65-AD65 -> #REF! | AF65: =LN(1+AD65) -> -0.01191711
J66: =Summary!A65 -> 38748 | K66: =K65*(1+Summary!B65) -> 0.81692637 | L66: =L65*(1+Summary!H65) -> 1.2792943 | M66: =M65*(1+Summary!I65) -> 2.6691001 | N66: =MAX($K$3:K66) -> 0.99069493 | O66: =MAX($L$3:L66) -> 1.2792943 | P66: =K66/N66-1 -> -0.17540067 | Q66: =L66/O66-1 -> 0 | R66: =M66/MAX($M$3:M66)-1 -> 0 | T66: =Summary!A65 -> 38748 | U66: =Trend_Simulation!B161*Trend_Simulation!K161*4.31 -> 0.012610129 | V66: =Trend_Simulation!C161*Trend_Simulation!L161*4.31 -> 0.035574489 | W66: =Trend_Simulation!D161*Trend_Simulation!M161*4.31 -> -0.006123401 | X66: =Trend_Simulation!E161*Trend_Simulation!N161*4.31 -> 0.0066793472 | Y66: =Trend_Simulation!F161*Trend_Simulation!O161*4.31 -> 0.012958443 | Z66: =Trend_Simulation!G161*Trend_Simulation!P161*4.31 -> -0.012608424 | AA66: =Trend_Simulation!H161*Trend_Simulation!Q161*4.31 -> -0.003116253 | AB66: =Trend_Simulation!#REF!*Trend_Simulation!#REF!*4.31 -> #REF! | AC66: =SUM(U66:AB66) -> #REF! | AD66: =Summary!I65 -> 0.045014309 | AE66: =AC66-AD66 -> #REF! | AF66: =LN(1+AD66) -> 0.044030578
A67: UNDERLYING SLEEVE CONTRIBUTIONS | J67: =Summary!A66 -> 38776 | K67: =K66*(1+Summary!B66) -> 0.81626172 | L67: =L66*(1+Summary!H66) -> 1.273417 | M67: =M66*(1+Summary!I66) -> 2.6173534 | N67: =MAX($K$3:K67) -> 0.99069493 | O67: =MAX($L$3:L67) -> 1.2792943 | P67: =K67/N67-1 -> -0.17607156 | Q67: =L67/O67-1 -> -0.0045941514 | R67: =M67/MAX($M$3:M67)-1 -> -0.019387319 | T67: =Summary!A66 -> 38776 | U67: =Trend_Simulation!B162*Trend_Simulation!K162*4.31 -> -0.010501823 | V67: =Trend_Simulation!C162*Trend_Simulation!L162*4.31 -> -0.0068946628 | W67: =Trend_Simulation!D162*Trend_Simulation!M162*4.31 -> 0.0087789861 | X67: =Trend_Simulation!E162*Trend_Simulation!N162*4.31 -> 0.0028257584 | Y67: =Trend_Simulation!F162*Trend_Simulation!O162*4.31 -> -0.00047207715 | Z67: =Trend_Simulation!G162*Trend_Simulation!P162*4.31 -> -0.009031844 | AA67: =Trend_Simulation!H162*Trend_Simulation!Q162*4.31 -> -0.0045051301 | AB67: =Trend_Simulation!#REF!*Trend_Simulation!#REF!*4.31 -> #REF! | AC67: =SUM(U67:AB67) -> #REF! | AD67: =Summary!I66 -> -0.019387319 | AE67: =AC67-AD67 -> #REF! | AF67: =LN(1+AD67) -> -0.019577718
A68: Sleeve | B68: Full Period | C68: 2022–24 Drawdown | D68: Full-Period Rank | J68: =Summary!A67 -> 38807 | K68: =K67*(1+Summary!B67) -> 0.8230559 | L68: =L67*(1+Summary!H67) -> 1.2946121 | M68: =M67*(1+Summary!I67) -> 2.8011932 | N68: =MAX($K$3:K68) -> 0.99069493 | O68: =MAX($L$3:L68) -> 1.2946121 | P68: =K68/N68-1 -> -0.16921357 | Q68: =L68/O68-1 -> 0 | R68: =M68/MAX($M$3:M68)-1 -> 0 | T68: =Summary!A67 -> 38807 | U68: =Trend_Simulation!B163*Trend_Simulation!K163*4.31 -> 0.010645225 | V68: =Trend_Simulation!C163*Trend_Simulation!L163*4.31 -> 0.010647643 | W68: =Trend_Simulation!D163*Trend_Simulation!M163*4.31 -> 0.015168338 | X68: =Trend_Simulation!E163*Trend_Simulation!N163*4.31 -> 0.010742985 | Y68: =Trend_Simulation!F163*Trend_Simulation!O163*4.31 -> 0.004864802 | Z68: =Trend_Simulation!G163*Trend_Simulation!P163*4.31 -> 0.0054554927 | AA68: =Trend_Simulation!H163*Trend_Simulation!Q163*4.31 -> 0.014212326 | AB68: =Trend_Simulation!#REF!*Trend_Simulation!#REF!*4.31 -> #REF! | AC68: =SUM(U68:AB68) -> #REF! | AD68: =Summary!I67 -> 0.070238827 | AE68: =AC68-AD68 -> #REF! | AF68: =LN(1+AD68) -> 0.067881826
A69: GSCI Gasoil | B69: =SUM($U$3:$U$312) -> 0.61279199 | C69: =SUMIFS($U$3:$U$312,$T$3:$T$312,">="&EOMONTH(DATE(2022,9,1),0),$T$3:$T$312,"<="&EOMONTH(DATE(2024,1,1),0)) -> -0.092325772 | D69: =_xlfn.RANK.EQ(B69,$B$69:$B$76,0) -> #REF! | J69: =Summary!A68 -> 38837 | K69: =K68*(1+Summary!B68) -> 0.83110553 | L69: =L68*(1+Summary!H68) -> 1.3034341 | M69: =M68*(1+Summary!I68) -> 2.8817469 | N69: =MAX($K$3:K69) -> 0.99069493 | O69: =MAX($L$3:L69) -> 1.3034341 | P69: =K69/N69-1 -> -0.16108833 | Q69: =L69/O69-1 -> 0 | R69: =M69/MAX($M$3:M69)-1 -> 0 | T69: =Summary!A68 -> 38837 | U69: =Trend_Simulation!B164*Trend_Simulation!K164*4.31 -> -0.012572443 | V69: =Trend_Simulation!C164*Trend_Simulation!L164*4.31 -> 0.041115056 | W69: =Trend_Simulation!D164*Trend_Simulation!M164*4.31 -> 0.009476892 | X69: =Trend_Simulation!E164*Trend_Simulation!N164*4.31 -> 0.0058185407 | Y69: =Trend_Simulation!F164*Trend_Simulation!O164*4.31 -> 0.0057347611 | Z69: =Trend_Simulation!G164*Trend_Simulation!P164*4.31 -> -0.0017817041 | AA69: =Trend_Simulation!H164*Trend_Simulation!Q164*4.31 -> -0.018420873 | AB69: =Trend_Simulation!#REF!*Trend_Simulation!#REF!*4.31 -> #REF! | AC69: =SUM(U69:AB69) -> #REF! | AD69: =Summary!I68 -> 0.028756931 | AE69: =AC69-AD69 -> #REF! | AF69: =LN(1+AD69) -> 0.02835121
A70: GSCI Gold | B70: =SUM($V$3:$V$312) -> 0.61480151 | C70: =SUMIFS($V$3:$V$312,$T$3:$T$312,">="&EOMONTH(DATE(2022,9,1),0),$T$3:$T$312,"<="&EOMONTH(DATE(2024,1,1),0)) -> -0.075108402 | D70: =_xlfn.RANK.EQ(B70,$B$69:$B$76,0) -> #REF! | J70: =Summary!A69 -> 38868 | K70: =K69*(1+Summary!B69) -> 0.80333801 | L70: =L69*(1+Summary!H69) -> 1.2808586 | M70: =M69*(1+Summary!I69) -> 2.6711182 | N70: =MAX($K$3:K70) -> 0.99069493 | O70: =MAX($L$3:L70) -> 1.3034341 | P70: =K70/N70-1 -> -0.18911666 | Q70: =L70/O70-1 -> -0.017320059 | R70: =M70/MAX($M$3:M70)-1 -> -0.07309065 | T70: =Summary!A69 -> 38868 | U70: =Trend_Simulation!B165*Trend_Simulation!K165*4.31 -> -0.0038811058 | V70: =Trend_Simulation!C165*Trend_Simulation!L165*4.31 -> -0.0058845883 | W70: =Trend_Simulation!D165*Trend_Simulation!M165*4.31 -> -0.011586262 | X70: =Trend_Simulation!E165*Trend_Simulation!N165*4.31 -> 0.0035363649 | Y70: =Trend_Simulation!F165*Trend_Simulation!O165*4.31 -> -0.021906546 | Z70: =Trend_Simulation!G165*Trend_Simulation!P165*4.31 -> -0.026156915 | AA70: =Trend_Simulation!H165*Trend_Simulation!Q165*4.31 -> -0.0087704032 | AB70: =Trend_Simulation!#REF!*Trend_Simulation!#REF!*4.31 -> #REF! | AC70: =SUM(U70:AB70) -> #REF! | AD70: =Summary!I69 -> -0.07309065 | AE70: =AC70-AD70 -> #REF! | AF70: =LN(1+AD70) -> -0.075899507
A71: Japan Gov’t Bond | B71: =SUM($W$3:$W$312) -> 0.47334887 | C71: =SUMIFS($W$3:$W$312,$T$3:$T$312,">="&EOMONTH(DATE(2022,9,1),0),$T$3:$T$312,"<="&EOMONTH(DATE(2024,1,1),0)) -> -0.10478921 | D71: =_xlfn.RANK.EQ(B71,$B$69:$B$76,0) -> #REF! | J71: =Summary!A70 -> 38898 | K71: =K70*(1+Summary!B70) -> 0.80134407 | L71: =L70*(1+Summary!H70) -> 1.2837346 | M71: =M70*(1+Summary!I70) -> 2.6964279 | N71: =MAX($K$3:K71) -> 0.99069493 | O71: =MAX($L$3:L71) -> 1.3034341 | P71: =K71/N71-1 -> -0.19112933 | Q71: =L71/O71-1 -> -0.015113607 | R71: =M71/MAX($M$3:M71)-1 -> -0.064307865 | T71: =Summary!A70 -> 38898 | U71: =Trend_Simulation!B166*Trend_Simulation!K166*4.31 -> 0.0051609377 | V71: =Trend_Simulation!C166*Trend_Simulation!L166*4.31 -> -0.016753149 | W71: =Trend_Simulation!D166*Trend_Simulation!M166*4.31 -> 0.0059843092 | X71: =Trend_Simulation!E166*Trend_Simulation!N166*4.31 -> 0.00046367369 | Y71: =Trend_Simulation!F166*Trend_Simulation!O166*4.31 -> -0.0016194377 | Z71: =Trend_Simulation!G166*Trend_Simulation!P166*4.31 -> 0.0021295633 | AA71: =Trend_Simulation!H166*Trend_Simulation!Q166*4.31 -> 0.014311527 | AB71: =Trend_Simulation!#REF!*Trend_Simulation!#REF!*4.31 -> #REF! | AC71: =SUM(U71:AB71) -> #REF! | AD71: =Summary!I70 -> 0.0094753438 | AE71: =AC71-AD71 -> #REF! | AF71: =LN(1+AD71) -> 0.0094307344
A72: US 10Y Gov’t Bond | B72: =SUM($X$3:$X$312) -> 0.59925409 | C72: =SUMIFS($X$3:$X$312,$T$3:$T$312,">="&EOMONTH(DATE(2022,9,1),0),$T$3:$T$312,"<="&EOMONTH(DATE(2024,1,1),0)) -> 0.044043472 | D72: =_xlfn.RANK.EQ(B72,$B$69:$B$76,0) -> #REF! | J72: =Summary!A71 -> 38929 | K72: =K71*(1+Summary!B71) -> 0.80274721 | L72: =L71*(1+Summary!H71) -> 1.2780488 | M72: =M71*(1+Summary!I71) -> 2.6460297 | N72: =MAX($K$3:K72) -> 0.99069493 | O72: =MAX($L$3:L72) -> 1.3034341 | P72: =K72/N72-1 -> -0.18971301 | Q72: =L72/O72-1 -> -0.01947575 | R72: =M72/MAX($M$3:M72)-1 -> -0.081796632 | T72: =Summary!A71 -> 38929 | U72: =Trend_Simulation!B167*Trend_Simulation!K167*4.31 -> -0.0045090098 | V72: =Trend_Simulation!C167*Trend_Simulation!L167*4.31 -> 0.009275583 | W72: =Trend_Simulation!D167*Trend_Simulation!M167*4.31 -> -0.0039803758 | X72: =Trend_Simulation!E167*Trend_Simulation!N167*4.31 -> -0.0085662426 | Y72: =Trend_Simulation!F167*Trend_Simulation!O167*4.31 -> 0.0011196898 | Z72: =Trend_Simulation!G167*Trend_Simulation!P167*4.31 -> -0.015352588 | AA72: =Trend_Simulation!H167*Trend_Simulation!Q167*4.31 -> 0.0029235986 | AB72: =Trend_Simulation!#REF!*Trend_Simulation!#REF!*4.31 -> #REF! | AC72: =SUM(U72:AB72) -> #REF! | AD72: =Summary!I71 -> -0.018690728 | AE72: =AC72-AD72 -> #REF! | AF72: =LN(1+AD72) -> -0.018867607
A73: S&P 500 | B73: =SUM($Y$3:$Y$312) -> 0.73419919 | C73: =SUMIFS($Y$3:$Y$312,$T$3:$T$312,">="&EOMONTH(DATE(2022,9,1),0),$T$3:$T$312,"<="&EOMONTH(DATE(2024,1,1),0)) -> -0.0065090768 | D73: =_xlfn.RANK.EQ(B73,$B$69:$B$76,0) -> #REF! | J73: =Summary!A72 -> 38960 | K73: =K72*(1+Summary!B72) -> 0.81759102 | L73: =L72*(1+Summary!H72) -> 1.2664224 | M73: =M72*(1+Summary!I72) -> 2.5444502 | N73: =MAX($K$3:K73) -> 0.99069493 | O73: =MAX($L$3:L73) -> 1.3034341 | P73: =K73/N73-1 -> -0.17472978 | Q73: =L73/O73-1 -> -0.028395596 | R73: =M73/MAX($M$3:M73)-1 -> -0.11704592 | T73: =Summary!A72 -> 38960 | U73: =Trend_Simulation!B168*Trend_Simulation!K168*4.31 -> -0.0033324301 | V73: =Trend_Simulation!C168*Trend_Simulation!L168*4.31 -> -0.0061264278 | W73: =Trend_Simulation!D168*Trend_Simulation!M168*4.31 -> -0.032806231 | X73: =Trend_Simulation!E168*Trend_Simulation!N168*4.31 -> -0.010876929 | Y73: =Trend_Simulation!F168*Trend_Simulation!O168*4.31 -> 0.011504371 | Z73: =Trend_Simulation!G168*Trend_Simulation!P168*4.31 -> -0.013863512 | AA73: =Trend_Simulation!H168*Trend_Simulation!Q168*4.31 -> 0.016293016 | AB73: =Trend_Simulation!#REF!*Trend_Simulation!#REF!*4.31 -> #REF! | AC73: =SUM(U73:AB73) -> #REF! | AD73: =Summary!I72 -> -0.038389412 | AE73: =AC73-AD73 -> #REF! | AF73: =LN(1+AD73) -> -0.039145705
A74: Nasdaq 100 | B74: =SUM($Z$3:$Z$312) -> 0.39493951 | C74: =SUMIFS($Z$3:$Z$312,$T$3:$T$312,">="&EOMONTH(DATE(2022,9,1),0),$T$3:$T$312,"<="&EOMONTH(DATE(2024,1,1),0)) -> 0.034412065 | D74: =_xlfn.RANK.EQ(B74,$B$69:$B$76,0) -> #REF! | J74: =Summary!A73 -> 38990 | K74: =K73*(1+Summary!B73) -> 0.83538882 | L74: =L73*(1+Summary!H73) -> 1.268097 | M74: =M73*(1+Summary!I73) -> 2.5586489 | N74: =MAX($K$3:K74) -> 0.99069493 | O74: =MAX($L$3:L74) -> 1.3034341 | P74: =K74/N74-1 -> -0.15676482 | Q74: =L74/O74-1 -> -0.027110809 | R74: =M74/MAX($M$3:M74)-1 -> -0.11211881 | T74: =Summary!A73 -> 38990 | U74: =Trend_Simulation!B169*Trend_Simulation!K169*4.31 -> 0.023224205 | V74: =Trend_Simulation!C169*Trend_Simulation!L169*4.31 -> -0.014482031 | W74: =Trend_Simulation!D169*Trend_Simulation!M169*4.31 -> -0.0027081103 | X74: =Trend_Simulation!E169*Trend_Simulation!N169*4.31 -> -0.0053533283 | Y74: =Trend_Simulation!F169*Trend_Simulation!O169*4.31 -> 0.013093995 | Z74: =Trend_Simulation!G169*Trend_Simulation!P169*4.31 -> -0.013842424 | AA74: =Trend_Simulation!H169*Trend_Simulation!Q169*4.31 -> 0.00576696 | AB74: =Trend_Simulation!#REF!*Trend_Simulation!#REF!*4.31 -> #REF! | AC74: =SUM(U74:AB74) -> #REF! | AD74: =Summary!I73 -> 0.0055802557 | AE74: =AC74-AD74 -> #REF! | AF74: =LN(1+AD74) -> 0.0055647438
A75: JPY/USD | B75: =SUM($AA$3:$AA$312) -> 0.63436808 | C75: =SUMIFS($AA$3:$AA$312,$T$3:$T$312,">="&EOMONTH(DATE(2022,9,1),0),$T$3:$T$312,"<="&EOMONTH(DATE(2024,1,1),0)) -> 0.05609545 | D75: =_xlfn.RANK.EQ(B75,$B$69:$B$76,0) -> #REF! | J75: =Summary!A74 -> 39021 | K75: =K74*(1+Summary!B74) -> 0.85887305 | L75: =L74*(1+Summary!H74) -> 1.2700493 | M75: =M74*(1+Summary!I74) -> 2.5752719 | N75: =MAX($K$3:K75) -> 0.99069493 | O75: =MAX($L$3:L75) -> 1.3034341 | P75: =K75/N75-1 -> -0.13306001 | Q75: =L75/O75-1 -> -0.025613024 | R75: =M75/MAX($M$3:M75)-1 -> -0.10635044 | T75: =Summary!A74 -> 39021 | U75: =Trend_Simulation!B170*Trend_Simulation!K170*4.31 -> 0.0089840572 | V75: =Trend_Simulation!C170*Trend_Simulation!L170*4.31 -> 0.0012503651 | W75: =Trend_Simulation!D170*Trend_Simulation!M170*4.31 -> -0.0035766557 | X75: =Trend_Simulation!E170*Trend_Simulation!N170*4.31 -> -0.001315632 | Y75: =Trend_Simulation!F170*Trend_Simulation!O170*4.31 -> 0.016499579 | Z75: =Trend_Simulation!G170*Trend_Simulation!P170*4.31 -> -0.013185594 | AA75: =Trend_Simulation!H170*Trend_Simulation!Q170*4.31 -> -0.0020207769 | AB75: =Trend_Simulation!#REF!*Trend_Simulation!#REF!*4.31 -> #REF! | AC75: =SUM(U75:AB75) -> #REF! | AD75: =Summary!I74 -> 0.0064967857 | AE75: =AC75-AD75 -> #REF! | AF75: =LN(1+AD75) -> 0.0064757725
A76: EUR/USD | B76: =SUM($AB$3:$AB$312) -> #REF! | C76: =SUMIFS($AB$3:$AB$312,$T$3:$T$312,">="&EOMONTH(DATE(2022,9,1),0),$T$3:$T$312,"<="&EOMONTH(DATE(2024,1,1),0)) -> #REF! | D76: =_xlfn.RANK.EQ(B76,$B$69:$B$76,0) -> #REF! | J76: =Summary!A75 -> 39051 | K76: =K75*(1+Summary!B75) -> 0.87113212 | L76: =L75*(1+Summary!H75) -> 1.2804229 | M76: =M75*(1+Summary!I75) -> 2.6640378 | N76: =MAX($K$3:K76) -> 0.99069493 | O76: =MAX($L$3:L76) -> 1.3034341 | P76: =K76/N76-1 -> -0.1206858 | Q76: =L76/O76-1 -> -0.017654322 | R76: =M76/MAX($M$3:M76)-1 -> -0.075547619 | T76: =Summary!A75 -> 39051 | U76: =Trend_Simulation!B171*Trend_Simulation!K171*4.31 -> -0.010978781 | V76: =Trend_Simulation!C171*Trend_Simulation!L171*4.31 -> 0.018673378 | W76: =Trend_Simulation!D171*Trend_Simulation!M171*4.31 -> 0.0066996494 | X76: =Trend_Simulation!E171*Trend_Simulation!N171*4.31 -> 0.007421088 | Y76: =Trend_Simulation!F171*Trend_Simulation!O171*4.31 -> 0.0087228634 | Z76: =Trend_Simulation!G171*Trend_Simulation!P171*4.31 -> 0.0094169641 | AA76: =Trend_Simulation!H171*Trend_Simulation!Q171*4.31 -> -0.0047514861 | AB76: =Trend_Simulation!#REF!*Trend_Simulation!#REF!*4.31 -> #REF! | AC76: =SUM(U76:AB76) -> #REF! | AD76: =Summary!I75 -> 0.034468565 | AE76: =AC76-AD76 -> #REF! | AF76: =LN(1+AD76) -> 0.033887831
J77: =Summary!A76 -> 39082 | K77: =K76*(1+Summary!B76) -> 0.87932944 | L77: =L76*(1+Summary!H76) -> 1.2817365 | M77: =M76*(1+Summary!I76) -> 2.6755714 | N77: =MAX($K$3:K77) -> 0.99069493 | O77: =MAX($L$3:L77) -> 1.3034341 | P77: =K77/N77-1 -> -0.11241148 | Q77: =L77/O77-1 -> -0.016646514 | R77: =M77/MAX($M$3:M77)-1 -> -0.071545312 | T77: =Summary!A76 -> 39082 | U77: =Trend_Simulation!B172*Trend_Simulation!K172*4.31 -> 0.012656194 | V77: =Trend_Simulation!C172*Trend_Simulation!L172*4.31 -> -0.0063962822 | W77: =Trend_Simulation!D172*Trend_Simulation!M172*4.31 -> -0.0045633748 | X77: =Trend_Simulation!E172*Trend_Simulation!N172*4.31 -> -0.014430135 | Y77: =Trend_Simulation!F172*Trend_Simulation!O172*4.31 -> 0.0057244863 | Z77: =Trend_Simulation!G172*Trend_Simulation!P172*4.31 -> -0.0071945622 | AA77: =Trend_Simulation!H172*Trend_Simulation!Q172*4.31 -> 0.018625388 | AB77: =Trend_Simulation!#REF!*Trend_Simulation!#REF!*4.31 -> #REF! | AC77: =SUM(U77:AB77) -> #REF! | AD77: =Summary!I76 -> 0.0043293814 | AE77: =AC77-AD77 -> #REF! | AF77: =LN(1+AD77) -> 0.0043200366
A78: INFLATION AND RATE REGIME ATTRIBUTION | J78: =Summary!A77 -> 39113 | K78: =K77*(1+Summary!B77) -> 0.88826527 | L78: =L77*(1+Summary!H77) -> 1.2941551 | M78: =M77*(1+Summary!I77) -> 2.7849676 | N78: =MAX($K$3:K78) -> 0.99069493 | O78: =MAX($L$3:L78) -> 1.3034341 | P78: =K78/N78-1 -> -0.10339173 | Q78: =L78/O78-1 -> -0.007118929 | R78: =M78/MAX($M$3:M78)-1 -> -0.033583552 | T78: =Summary!A77 -> 39113 | U78: =Trend_Simulation!B173*Trend_Simulation!K173*4.31 -> 0.0030766698 | V78: =Trend_Simulation!C173*Trend_Simulation!L173*4.31 -> 0.0059037544 | W78: =Trend_Simulation!D173*Trend_Simulation!M173*4.31 -> 0.0050997033 | X78: =Trend_Simulation!E173*Trend_Simulation!N173*4.31 -> 0.0060312407 | Y78: =Trend_Simulation!F173*Trend_Simulation!O173*4.31 -> 0.0065806888 | Z78: =Trend_Simulation!G173*Trend_Simulation!P173*4.31 -> 0.0048184956 | AA78: =Trend_Simulation!H173*Trend_Simulation!Q173*4.31 -> 0.010248482 | AB78: =Trend_Simulation!#REF!*Trend_Simulation!#REF!*4.31 -> #REF! | AC78: =SUM(U78:AB78) -> #REF! | AD78: =Summary!I77 -> 0.040887036 | AE78: =AC78-AD78 -> #REF! | AF78: =LN(1+AD78) -> 0.040073269
A79: Macro Regime | B79: Levered Trend Return | C79: Commodities | D79: Bonds | E79: Equities | F79: FX | G79: Largest Positive Sleeve | J79: =Summary!A78 -> 39141 | K79: =K78*(1+Summary!B78) -> 0.86729193 | L79: =L78*(1+Summary!H78) -> 1.2820911 | M79: =M78*(1+Summary!I78) -> 2.6754109 | N79: =MAX($K$3:K79) -> 0.99069493 | O79: =MAX($L$3:L79) -> 1.3034341 | P79: =K79/N79-1 -> -0.12456206 | Q79: =L79/O79-1 -> -0.01637451 | R79: =M79/MAX($M$3:M79)-1 -> -0.071601021 | T79: =Summary!A78 -> 39141 | U79: =Trend_Simulation!B174*Trend_Simulation!K174*4.31 -> -0.0057849483 | V79: =Trend_Simulation!C174*Trend_Simulation!L174*4.31 -> 0.0062270985 | W79: =Trend_Simulation!D174*Trend_Simulation!M174*4.31 -> 0.0056572101 | X79: =Trend_Simulation!E174*Trend_Simulation!N174*4.31 -> -0.015405404 | Y79: =Trend_Simulation!F174*Trend_Simulation!O174*4.31 -> -0.015262758 | Z79: =Trend_Simulation!G174*Trend_Simulation!P174*4.31 -> -0.0063456107 | AA79: =Trend_Simulation!H174*Trend_Simulation!Q174*4.31 -> -0.009263161 | AB79: =Trend_Simulation!#REF!*Trend_Simulation!#REF!*4.31 -> #REF! | AC79: =SUM(U79:AB79) -> #REF! | AD79: =Summary!I78 -> -0.039338599 | AE79: =AC79-AD79 -> #REF! | AF79: =LN(1+AD79) -> -0.040133272
A80: Post-2000 Easing | B80: =EXP(SUMIFS($AF$3:$AF$312,$T$3:$T$312,">="&$AH$14,$T$3:$T$312,"<="&$AI$14))-1 -> 1.1935458 | C80: =SUMIFS($U$3:$U$312,$T$3:$T$312,">="&$AH$14,$T$3:$T$312,"<="&$AI$14)+SUMIFS($V$3:$V$312,$T$3:$T$312,">="&$AH$14,$T$3:$T$312,"<="&$AI$14) -> 0.18663306 | D80: =SUMIFS($W$3:$W$312,$T$3:$T$312,">="&$AH$14,$T$3:$T$312,"<="&$AI$14)+SUMIFS($X$3:$X$312,$T$3:$T$312,">="&$AH$14,$T$3:$T$312,"<="&$AI$14) -> 0.34751471 | E80: =SUMIFS($Y$3:$Y$312,$T$3:$T$312,">="&$AH$14,$T$3:$T$312,"<="&$AI$14)+SUMIFS($Z$3:$Z$312,$T$3:$T$312,">="&$AH$14,$T$3:$T$312,"<="&$AI$14) -> 0.23259914 | F80: =SUMIFS($AA$3:$AA$312,$T$3:$T$312,">="&$AH$14,$T$3:$T$312,"<="&$AI$14)+SUMIFS($AB$3:$AB$312,$T$3:$T$312,">="&$AH$14,$T$3:$T$312,"<="&$AI$14) -> #REF! | G80: US 10Y | J80: =Summary!A79 -> 39172 | K80: =K79*(1+Summary!B79) -> 0.87327376 | L80: =L79*(1+Summary!H79) -> 1.2780664 | M80: =M79*(1+Summary!I79) -> 2.6399691 | N80: =MAX($K$3:K80) -> 0.99069493 | O80: =MAX($L$3:L80) -> 1.3034341 | P80: =K80/N80-1 -> -0.11852404 | Q80: =L80/O80-1 -> -0.019462263 | R80: =M80/MAX($M$3:M80)-1 -> -0.083899741 | T80: =Summary!A79 -> 39172 | U80: =Trend_Simulation!B175*Trend_Simulation!K175*4.31 -> -0.011605447 | V80: =Trend_Simulation!C175*Trend_Simulation!L175*4.31 -> -0.0041622355 | W80: =Trend_Simulation!D175*Trend_Simulation!M175*4.31 -> 0.00071266254 | X80: =Trend_Simulation!E175*Trend_Simulation!N175*4.31 -> -0.0038899499 | Y80: =Trend_Simulation!F175*Trend_Simulation!O175*4.31 -> 0.0043448028 | Z80: =Trend_Simulation!G175*Trend_Simulation!P175*4.31 -> 0.00080556076 | AA80: =Trend_Simulation!H175*Trend_Simulation!Q175*4.31 -> 0.00026484648 | AB80: =Trend_Simulation!#REF!*Trend_Simulation!#REF!*4.31 -> #REF! | AC80: =SUM(U80:AB80) -> #REF! | AD80: =Summary!I79 -> -0.013247236 | AE80: =AC80-AD80 -> #REF! | AF80: =LN(1+AD80) -> -0.013335763
A81: 2004–07 Hiking Cycle | B81: =EXP(SUMIFS($AF$3:$AF$312,$T$3:$T$312,">="&$AH$15,$T$3:$T$312,"<="&$AI$15))-1 -> 0.21053867 | C81: =SUMIFS($U$3:$U$312,$T$3:$T$312,">="&$AH$15,$T$3:$T$312,"<="&$AI$15)+SUMIFS($V$3:$V$312,$T$3:$T$312,">="&$AH$15,$T$3:$T$312,"<="&$AI$15) -> 0.28194113 | D81: =SUMIFS($W$3:$W$312,$T$3:$T$312,">="&$AH$15,$T$3:$T$312,"<="&$AI$15)+SUMIFS($X$3:$X$312,$T$3:$T$312,">="&$AH$15,$T$3:$T$312,"<="&$AI$15) -> -0.04634205 | E81: =SUMIFS($Y$3:$Y$312,$T$3:$T$312,">="&$AH$15,$T$3:$T$312,"<="&$AI$15)+SUMIFS($Z$3:$Z$312,$T$3:$T$312,">="&$AH$15,$T$3:$T$312,"<="&$AI$15) -> -0.066008864 | F81: =SUMIFS($AA$3:$AA$312,$T$3:$T$312,">="&$AH$15,$T$3:$T$312,"<="&$AI$15)+SUMIFS($AB$3:$AB$312,$T$3:$T$312,">="&$AH$15,$T$3:$T$312,"<="&$AI$15) -> #REF! | G81: Gold | J81: =Summary!A80 -> 39202 | K81: =K80*(1+Summary!B80) -> 0.90820471 | L81: =L80*(1+Summary!H80) -> 1.2866783 | M81: =M80*(1+Summary!I80) -> 2.7150377 | N81: =MAX($K$3:K81) -> 0.99069493 | O81: =MAX($L$3:L81) -> 1.3034341 | P81: =K81/N81-1 -> -0.083265002 | Q81: =L81/O81-1 -> -0.012855155 | R81: =M81/MAX($M$3:M81)-1 -> -0.057850053 | T81: =Summary!A80 -> 39202 | U81: =Trend_Simulation!B176*Trend_Simulation!K176*4.31 -> -5.2538364e-05 | V81: =Trend_Simulation!C176*Trend_Simulation!L176*4.31 -> 0.0060724461 | W81: =Trend_Simulation!D176*Trend_Simulation!M176*4.31 -> 0.0023742422 | X81: =Trend_Simulation!E176*Trend_Simulation!N176*4.31 -> 0.0016577533 | Y81: =Trend_Simulation!F176*Trend_Simulation!O176*4.31 -> 0.024748994 | Z81: =Trend_Simulation!G176*Trend_Simulation!P176*4.31 -> -0.014855152 | AA81: =Trend_Simulation!H176*Trend_Simulation!Q176*4.31 -> 0.0090961098 | AB81: =Trend_Simulation!#REF!*Trend_Simulation!#REF!*4.31 -> #REF! | AC81: =SUM(U81:AB81) -> #REF! | AD81: =Summary!I80 -> 0.028435412 | AE81: =AC81-AD81 -> #REF! | AF81: =LN(1+AD81) -> 0.02803863
A82: GFC Easing / ZIRP Transition | B82: =EXP(SUMIFS($AF$3:$AF$312,$T$3:$T$312,">="&$AH$16,$T$3:$T$312,"<="&$AI$16))-1 -> 0.89663122 | C82: =SUMIFS($U$3:$U$312,$T$3:$T$312,">="&$AH$16,$T$3:$T$312,"<="&$AI$16)+SUMIFS($V$3:$V$312,$T$3:$T$312,">="&$AH$16,$T$3:$T$312,"<="&$AI$16) -> 0.04907921 | D82: =SUMIFS($W$3:$W$312,$T$3:$T$312,">="&$AH$16,$T$3:$T$312,"<="&$AI$16)+SUMIFS($X$3:$X$312,$T$3:$T$312,">="&$AH$16,$T$3:$T$312,"<="&$AI$16) -> 0.31442856 | E82: =SUMIFS($Y$3:$Y$312,$T$3:$T$312,">="&$AH$16,$T$3:$T$312,"<="&$AI$16)+SUMIFS($Z$3:$Z$312,$T$3:$T$312,">="&$AH$16,$T$3:$T$312,"<="&$AI$16) -> 0.25224294 | F82: =SUMIFS($AA$3:$AA$312,$T$3:$T$312,">="&$AH$16,$T$3:$T$312,"<="&$AI$16)+SUMIFS($AB$3:$AB$312,$T$3:$T$312,">="&$AH$16,$T$3:$T$312,"<="&$AI$16) -> #REF! | G82: US 10Y | J82: =Summary!A81 -> 39233 | K82: =K81*(1+Summary!B81) -> 0.93530758 | L82: =L81*(1+Summary!H81) -> 1.2929184 | M82: =M81*(1+Summary!I81) -> 2.7706041 | N82: =MAX($K$3:K82) -> 0.99069493 | O82: =MAX($L$3:L82) -> 1.3034341 | P82: =K82/N82-1 -> -0.055907566 | Q82: =L82/O82-1 -> -0.0080676977 | R82: =M82/MAX($M$3:M82)-1 -> -0.038567855 | T82: =Summary!A81 -> 39233 | U82: =Trend_Simulation!B177*Trend_Simulation!K177*4.31 -> 0.0021669379 | V82: =Trend_Simulation!C177*Trend_Simulation!L177*4.31 -> 0.0098519362 | W82: =Trend_Simulation!D177*Trend_Simulation!M177*4.31 -> -0.012808906 | X82: =Trend_Simulation!E177*Trend_Simulation!N177*4.31 -> -0.017559807 | Y82: =Trend_Simulation!F177*Trend_Simulation!O177*4.31 -> 0.017183392 | Z82: =Trend_Simulation!G177*Trend_Simulation!P177*4.31 -> 0.0080043586 | AA82: =Trend_Simulation!H177*Trend_Simulation!Q177*4.31 -> 0.014064737 | AB82: =Trend_Simulation!#REF!*Trend_Simulation!#REF!*4.31 -> #REF! | AC82: =SUM(U82:AB82) -> #REF! | AD82: =Summary!I81 -> 0.020466166 | AE82: =AC82-AD82 -> #REF! | AF82: =LN(1+AD82) -> 0.020259549
A83: ZIRP / QE Low Inflation | B83: =EXP(SUMIFS($AF$3:$AF$312,$T$3:$T$312,">="&$AH$17,$T$3:$T$312,"<="&$AI$17))-1 -> 2.5040501 | C83: =SUMIFS($U$3:$U$312,$T$3:$T$312,">="&$AH$17,$T$3:$T$312,"<="&$AI$17)+SUMIFS($V$3:$V$312,$T$3:$T$312,">="&$AH$17,$T$3:$T$312,"<="&$AI$17) -> 0.41551047 | D83: =SUMIFS($W$3:$W$312,$T$3:$T$312,">="&$AH$17,$T$3:$T$312,"<="&$AI$17)+SUMIFS($X$3:$X$312,$T$3:$T$312,">="&$AH$17,$T$3:$T$312,"<="&$AI$17) -> 0.40340028 | E83: =SUMIFS($Y$3:$Y$312,$T$3:$T$312,">="&$AH$17,$T$3:$T$312,"<="&$AI$17)+SUMIFS($Z$3:$Z$312,$T$3:$T$312,">="&$AH$17,$T$3:$T$312,"<="&$AI$17) -> 0.31926847 | F83: =SUMIFS($AA$3:$AA$312,$T$3:$T$312,">="&$AH$17,$T$3:$T$312,"<="&$AI$17)+SUMIFS($AB$3:$AB$312,$T$3:$T$312,">="&$AH$17,$T$3:$T$312,"<="&$AI$17) -> #REF! | G83: Japan Bonds | J83: =Summary!A82 -> 39263 | K83: =K82*(1+Summary!B82) -> 0.91581124 | L83: =L82*(1+Summary!H82) -> 1.2875332 | M83: =M82*(1+Summary!I82) -> 2.7219047 | N83: =MAX($K$3:K83) -> 0.99069493 | O83: =MAX($L$3:L83) -> 1.3034341 | P83: =K83/N83-1 -> -0.075587029 | Q83: =L83/O83-1 -> -0.012199305 | R83: =M83/MAX($M$3:M83)-1 -> -0.055467131 | T83: =Summary!A82 -> 39263 | U83: =Trend_Simulation!B178*Trend_Simulation!K178*4.31 -> -0.0073784778 | V83: =Trend_Simulation!C178*Trend_Simulation!L178*4.31 -> 0.0069112149 | W83: =Trend_Simulation!D178*Trend_Simulation!M178*4.31 -> -0.009676561 | X83: =Trend_Simulation!E178*Trend_Simulation!N178*4.31 -> -0.0061156948 | Y83: =Trend_Simulation!F178*Trend_Simulation!O178*4.31 -> -0.012013965 | Z83: =Trend_Simulation!G178*Trend_Simulation!P178*4.31 -> -0.00023132912 | AA83: =Trend_Simulation!H178*Trend_Simulation!Q178*4.31 -> 0.010552753 | AB83: =Trend_Simulation!#REF!*Trend_Simulation!#REF!*4.31 -> #REF! | AC83: =SUM(U83:AB83) -> #REF! | AD83: =Summary!I82 -> -0.017577191 | AE83: =AC83-AD83 -> #REF! | AF83: =LN(1+AD83) -> -0.017733504
A84: Gradual Tightening | B84: =EXP(SUMIFS($AF$3:$AF$312,$T$3:$T$312,">="&$AH$18,$T$3:$T$312,"<="&$AI$18))-1 -> -0.085595675 | C84: =SUMIFS($U$3:$U$312,$T$3:$T$312,">="&$AH$18,$T$3:$T$312,"<="&$AI$18)+SUMIFS($V$3:$V$312,$T$3:$T$312,">="&$AH$18,$T$3:$T$312,"<="&$AI$18) -> -0.098998469 | D84: =SUMIFS($W$3:$W$312,$T$3:$T$312,">="&$AH$18,$T$3:$T$312,"<="&$AI$18)+SUMIFS($X$3:$X$312,$T$3:$T$312,">="&$AH$18,$T$3:$T$312,"<="&$AI$18) -> 0.035807472 | E84: =SUMIFS($Y$3:$Y$312,$T$3:$T$312,">="&$AH$18,$T$3:$T$312,"<="&$AI$18)+SUMIFS($Z$3:$Z$312,$T$3:$T$312,">="&$AH$18,$T$3:$T$312,"<="&$AI$18) -> 0.016957041 | F84: =SUMIFS($AA$3:$AA$312,$T$3:$T$312,">="&$AH$18,$T$3:$T$312,"<="&$AI$18)+SUMIFS($AB$3:$AB$312,$T$3:$T$312,">="&$AH$18,$T$3:$T$312,"<="&$AI$18) -> #REF! | G84: Japan Bonds | J84: =Summary!A83 -> 39294 | K84: =K83*(1+Summary!B83) -> 0.88353888 | L84: =L83*(1+Summary!H83) -> 1.2800754 | M84: =M83*(1+Summary!I83) -> 2.655372 | N84: =MAX($K$3:K84) -> 0.99069493 | O84: =MAX($L$3:L84) -> 1.3034341 | P84: =K84/N84-1 -> -0.1081625 | Q84: =L84/O84-1 -> -0.017920929 | R84: =M84/MAX($M$3:M84)-1 -> -0.07855477 | T84: =Summary!A83 -> 39294 | U84: =Trend_Simulation!B179*Trend_Simulation!K179*4.31 -> -0.0047501647 | V84: =Trend_Simulation!C179*Trend_Simulation!L179*4.31 -> -0.0069658145 | W84: =Trend_Simulation!D179*Trend_Simulation!M179*4.31 -> 0.012655033 | X84: =Trend_Simulation!E179*Trend_Simulation!N179*4.31 -> 0.015693566 | Y84: =Trend_Simulation!F179*Trend_Simulation!O179*4.31 -> -0.019791051 | Z84: =Trend_Simulation!G179*Trend_Simulation!P179*4.31 -> -0.0015284819 | AA84: =Trend_Simulation!H179*Trend_Simulation!Q179*4.31 -> -0.02027784 | AB84: =Trend_Simulation!#REF!*Trend_Simulation!#REF!*4.31 -> #REF! | AC84: =SUM(U84:AB84) -> #REF! | AD84: =Summary!I83 -> -0.024443447 | AE84: =AC84-AD84 -> #REF! | AF84: =LN(1+AD84) -> -0.024747147
A85: Pre-COVID Easing + Pandemic ZIRP | B85: =EXP(SUMIFS($AF$3:$AF$312,$T$3:$T$312,">="&$AH$19,$T$3:$T$312,"<="&$AI$19))-1 -> 0.18163295 | C85: =SUMIFS($U$3:$U$312,$T$3:$T$312,">="&$AH$19,$T$3:$T$312,"<="&$AI$19)+SUMIFS($V$3:$V$312,$T$3:$T$312,">="&$AH$19,$T$3:$T$312,"<="&$AI$19) -> 0.10402891 | D85: =SUMIFS($W$3:$W$312,$T$3:$T$312,">="&$AH$19,$T$3:$T$312,"<="&$AI$19)+SUMIFS($X$3:$X$312,$T$3:$T$312,">="&$AH$19,$T$3:$T$312,"<="&$AI$19) -> -0.025526191 | E85: =SUMIFS($Y$3:$Y$312,$T$3:$T$312,">="&$AH$19,$T$3:$T$312,"<="&$AI$19)+SUMIFS($Z$3:$Z$312,$T$3:$T$312,">="&$AH$19,$T$3:$T$312,"<="&$AI$19) -> 0.11817217 | F85: =SUMIFS($AA$3:$AA$312,$T$3:$T$312,">="&$AH$19,$T$3:$T$312,"<="&$AI$19)+SUMIFS($AB$3:$AB$312,$T$3:$T$312,">="&$AH$19,$T$3:$T$312,"<="&$AI$19) -> #REF! | G85: Nasdaq 100 | J85: =Summary!A84 -> 39325 | K85: =K84*(1+Summary!B84) -> 0.89240086 | L85: =L84*(1+Summary!H84) -> 1.2933284 | M85: =M84*(1+Summary!I84) -> 2.7713877 | N85: =MAX($K$3:K85) -> 0.99069493 | O85: =MAX($L$3:L85) -> 1.3034341 | P85: =K85/N85-1 -> -0.099217294 | Q85: =L85/O85-1 -> -0.0077531611 | R85: =M85/MAX($M$3:M85)-1 -> -0.03829594 | T85: =Summary!A84 -> 39325 | U85: =Trend_Simulation!B180*Trend_Simulation!K180*4.31 -> 0.0037024279 | V85: =Trend_Simulation!C180*Trend_Simulation!L180*4.31 -> -0.0011089006 | W85: =Trend_Simulation!D180*Trend_Simulation!M180*4.31 -> 0.024136881 | X85: =Trend_Simulation!E180*Trend_Simulation!N180*4.31 -> 0.017807655 | Y85: =Trend_Simulation!F180*Trend_Simulation!O180*4.31 -> 0.0056594706 | Z85: =Trend_Simulation!G180*Trend_Simulation!P180*4.31 -> 0.0078681389 | AA85: =Trend_Simulation!H180*Trend_Simulation!Q180*4.31 -> -0.01344291 | AB85: =Trend_Simulation!#REF!*Trend_Simulation!#REF!*4.31 -> #REF! | AC85: =SUM(U85:AB85) -> #REF! | AD85: =Summary!I84 -> 0.043690964 | AE85: =AC85-AD85 -> #REF! | AF85: =LN(1+AD85) -> 0.042763434
A86: Inflation Surge + Rapid Hiking | B86: =EXP(SUMIFS($AF$3:$AF$312,$T$3:$T$312,">="&$AH$20,$T$3:$T$312,"<="&$AI$20))-1 -> 0.097904678 | C86: =SUMIFS($U$3:$U$312,$T$3:$T$312,">="&$AH$20,$T$3:$T$312,"<="&$AI$20)+SUMIFS($V$3:$V$312,$T$3:$T$312,">="&$AH$20,$T$3:$T$312,"<="&$AI$20) -> -0.084582935 | D86: =SUMIFS($W$3:$W$312,$T$3:$T$312,">="&$AH$20,$T$3:$T$312,"<="&$AI$20)+SUMIFS($X$3:$X$312,$T$3:$T$312,">="&$AH$20,$T$3:$T$312,"<="&$AI$20) -> -0.046023582 | E86: =SUMIFS($Y$3:$Y$312,$T$3:$T$312,">="&$AH$20,$T$3:$T$312,"<="&$AI$20)+SUMIFS($Z$3:$Z$312,$T$3:$T$312,">="&$AH$20,$T$3:$T$312,"<="&$AI$20) -> 0.078108908 | F86: =SUMIFS($AA$3:$AA$312,$T$3:$T$312,">="&$AH$20,$T$3:$T$312,"<="&$AI$20)+SUMIFS($AB$3:$AB$312,$T$3:$T$312,">="&$AH$20,$T$3:$T$312,"<="&$AI$20) -> #REF! | G86: JPY/USD | J86: =Summary!A85 -> 39355 | K86: =K85*(1+Summary!B85) -> 0.92134997 | L86: =L85*(1+Summary!H85) -> 1.3070872 | M86: =M85*(1+Summary!I85) -> 2.8958055 | N86: =MAX($K$3:K86) -> 0.99069493 | O86: =MAX($L$3:L86) -> 1.3070872 | P86: =K86/N86-1 -> -0.069996273 | Q86: =L86/O86-1 -> 0 | R86: =M86/MAX($M$3:M86)-1 -> 0 | T86: =Summary!A85 -> 39355 | U86: =Trend_Simulation!B181*Trend_Simulation!K181*4.31 -> -0.014750913 | V86: =Trend_Simulation!C181*Trend_Simulation!L181*4.31 -> 0.028750812 | W86: =Trend_Simulation!D181*Trend_Simulation!M181*4.31 -> -0.00064114737 | X86: =Trend_Simulation!E181*Trend_Simulation!N181*4.31 -> 0.002091095 | Y86: =Trend_Simulation!F181*Trend_Simulation!O181*4.31 -> 0.01800107 | Z86: =Trend_Simulation!G181*Trend_Simulation!P181*4.31 -> 0.014675485 | AA86: =Trend_Simulation!H181*Trend_Simulation!Q181*4.31 -> -0.0022752634 | AB86: =Trend_Simulation!#REF!*Trend_Simulation!#REF!*4.31 -> #REF! | AC86: =SUM(U86:AB86) -> #REF! | AD86: =Summary!I85 -> 0.04489369 | AE86: =AC86-AD86 -> #REF! | AF86: =LN(1+AD86) -> 0.043915148
A87: Disinflation + Easing | B87: =EXP(SUMIFS($AF$3:$AF$312,$T$3:$T$312,">="&$AH$21,$T$3:$T$312,"<="&$AI$21))-1 -> 0.8550697 | C87: =SUMIFS($U$3:$U$312,$T$3:$T$312,">="&$AH$21,$T$3:$T$312,"<="&$AI$21)+SUMIFS($V$3:$V$312,$T$3:$T$312,">="&$AH$21,$T$3:$T$312,"<="&$AI$21) -> 0.37398212 | D87: =SUMIFS($W$3:$W$312,$T$3:$T$312,">="&$AH$21,$T$3:$T$312,"<="&$AI$21)+SUMIFS($X$3:$X$312,$T$3:$T$312,">="&$AH$21,$T$3:$T$312,"<="&$AI$21) -> 0.089343767 | E87: =SUMIFS($Y$3:$Y$312,$T$3:$T$312,">="&$AH$21,$T$3:$T$312,"<="&$AI$21)+SUMIFS($Z$3:$Z$312,$T$3:$T$312,">="&$AH$21,$T$3:$T$312,"<="&$AI$21) -> 0.17779889 | F87: =SUMIFS($AA$3:$AA$312,$T$3:$T$312,">="&$AH$21,$T$3:$T$312,"<="&$AI$21)+SUMIFS($AB$3:$AB$312,$T$3:$T$312,">="&$AH$21,$T$3:$T$312,"<="&$AI$21) -> #REF! | G87: Gasoil | J87: =Summary!A86 -> 39386 | K87: =K86*(1+Summary!B86) -> 0.9314674 | L87: =L86*(1+Summary!H86) -> 1.3308993 | M87: =M86*(1+Summary!I86) -> 3.1184306 | N87: =MAX($K$3:K87) -> 0.99069493 | O87: =MAX($L$3:L87) -> 1.3308993 | P87: =K87/N87-1 -> -0.059783824 | Q87: =L87/O87-1 -> 0 | R87: =M87/MAX($M$3:M87)-1 -> 0 | T87: =Summary!A86 -> 39386 | U87: =Trend_Simulation!B182*Trend_Simulation!K182*4.31 -> 0.014442044 | V87: =Trend_Simulation!C182*Trend_Simulation!L182*4.31 -> 0.01634685 | W87: =Trend_Simulation!D182*Trend_Simulation!M182*4.31 -> 0.011730505 | X87: =Trend_Simulation!E182*Trend_Simulation!N182*4.31 -> 0.0065395824 | Y87: =Trend_Simulation!F182*Trend_Simulation!O182*4.31 -> 0.0059692382 | Z87: =Trend_Simulation!G182*Trend_Simulation!P182*4.31 -> 0.020053971 | AA87: =Trend_Simulation!H182*Trend_Simulation!Q182*4.31 -> 0.0034358348 | AB87: =Trend_Simulation!#REF!*Trend_Simulation!#REF!*4.31 -> #REF! | AC87: =SUM(U87:AB87) -> #REF! | AD87: =Summary!I86 -> 0.076878438 | AE87: =AC87-AD87 -> #REF! | AF87: =LN(1+AD87) -> 0.07406652
J88: =Summary!A87 -> 39416 | K88: =K87*(1+Summary!B87) -> 0.88885607 | L88: =L87*(1+Summary!H87) -> 1.3230014 | M88: =M87*(1+Summary!I87) -> 3.0403374 | N88: =MAX($K$3:K88) -> 0.99069493 | O88: =MAX($L$3:L88) -> 1.3308993 | P88: =K88/N88-1 -> -0.10279538 | Q88: =L88/O88-1 -> -0.0059342291 | R88: =M88/MAX($M$3:M88)-1 -> -0.025042447 | T88: =Summary!A87 -> 39416 | U88: =Trend_Simulation!B183*Trend_Simulation!K183*4.31 -> 0.00046291099 | V88: =Trend_Simulation!C183*Trend_Simulation!L183*4.31 -> -0.0043068874 | W88: =Trend_Simulation!D183*Trend_Simulation!M183*4.31 -> 0.011378191 | X88: =Trend_Simulation!E183*Trend_Simulation!N183*4.31 -> 0.034284311 | Y88: =Trend_Simulation!F183*Trend_Simulation!O183*4.31 -> -0.024815495 | Z88: =Trend_Simulation!G183*Trend_Simulation!P183*4.31 -> -0.0211191 | AA88: =Trend_Simulation!H183*Trend_Simulation!Q183*4.31 -> -0.021460457 | AB88: =Trend_Simulation!#REF!*Trend_Simulation!#REF!*4.31 -> #REF! | AC88: =SUM(U88:AB88) -> #REF! | AD88: =Summary!I87 -> -0.025042447 | AE88: =AC88-AD88 -> #REF! | AF88: =LN(1+AD88) -> -0.025361344
J89: =Summary!A88 -> 39447 | K89: =K88*(1+Summary!B88) -> 0.8786648 | L89: =L88*(1+Summary!H88) -> 1.3314459 | M89: =M88*(1+Summary!I88) -> 3.12223 | N89: =MAX($K$3:K89) -> 0.99069493 | O89: =MAX($L$3:L89) -> 1.3314459 | P89: =K89/N89-1 -> -0.11308237 | Q89: =L89/O89-1 -> 0 | R89: =M89/MAX($M$3:M89)-1 -> 0 | T89: =Summary!A88 -> 39447 | U89: =Trend_Simulation!B184*Trend_Simulation!K184*4.31 -> 0.0092670139 | V89: =Trend_Simulation!C184*Trend_Simulation!L184*4.31 -> 0.016996108 | W89: =Trend_Simulation!D184*Trend_Simulation!M184*4.31 -> 0.0010361461 | X89: =Trend_Simulation!E184*Trend_Simulation!N184*4.31 -> 0.0015415163 | Y89: =Trend_Simulation!F184*Trend_Simulation!O184*4.31 -> -0.0061142948 | Z89: =Trend_Simulation!G184*Trend_Simulation!P184*4.31 -> -0.0016084736 | AA89: =Trend_Simulation!H184*Trend_Simulation!Q184*4.31 -> 0.0063917913 | AB89: =Trend_Simulation!#REF!*Trend_Simulation!#REF!*4.31 -> #REF! | AC89: =SUM(U89:AB89) -> #REF! | AD89: =Summary!I88 -> 0.026935356 | AE89: =AC89-AD89 -> #REF! | AF89: =LN(1+AD89) -> 0.026578985
J90: =Summary!A89 -> 39478 | K90: =K89*(1+Summary!B89) -> 0.82054501 | L90: =L89*(1+Summary!H89) -> 1.3580617 | M90: =M89*(1+Summary!I89) -> 3.3856169 | N90: =MAX($K$3:K90) -> 0.99069493 | O90: =MAX($L$3:L90) -> 1.3580617 | P90: =K90/N90-1 -> -0.17174804 | Q90: =L90/O90-1 -> 0 | R90: =M90/MAX($M$3:M90)-1 -> 0 | T90: =Summary!A89 -> 39478 | U90: =Trend_Simulation!B185*Trend_Simulation!K185*4.31 -> -0.0066300467 | V90: =Trend_Simulation!C185*Trend_Simulation!L185*4.31 -> 0.026953418 | W90: =Trend_Simulation!D185*Trend_Simulation!M185*4.31 -> 0.010382291 | X90: =Trend_Simulation!E185*Trend_Simulation!N185*4.31 -> 0.027355413 | Y90: =Trend_Simulation!F185*Trend_Simulation!O185*4.31 -> 0.035623993 | Z90: =Trend_Simulation!G185*Trend_Simulation!P185*4.31 -> -0.036533557 | AA90: =Trend_Simulation!H185*Trend_Simulation!Q185*4.31 -> 0.029006187 | AB90: =Trend_Simulation!#REF!*Trend_Simulation!#REF!*4.31 -> #REF! | AC90: =SUM(U90:AB90) -> #REF! | AD90: =Summary!I89 -> 0.084358581 | AE90: =AC90-AD90 -> #REF! | AF90: =LN(1+AD90) -> 0.080988643
J91: =Summary!A90 -> 39507 | K91: =K90*(1+Summary!B90) -> 0.79181744 | L91: =L90*(1+Summary!H90) -> 1.3912459 | M91: =M90*(1+Summary!I90) -> 3.7347269 | N91: =MAX($K$3:K91) -> 0.99069493 | O91: =MAX($L$3:L91) -> 1.3912459 | P91: =K91/N91-1 -> -0.20074543 | Q91: =L91/O91-1 -> 0 | R91: =M91/MAX($M$3:M91)-1 -> 0 | T91: =Summary!A90 -> 39507 | U91: =Trend_Simulation!B186*Trend_Simulation!K186*4.31 -> 0.023448738 | V91: =Trend_Simulation!C186*Trend_Simulation!L186*4.31 -> 0.01401083 | W91: =Trend_Simulation!D186*Trend_Simulation!M186*4.31 -> 0.0083039846 | X91: =Trend_Simulation!E186*Trend_Simulation!N186*4.31 -> 0.015191971 | Y91: =Trend_Simulation!F186*Trend_Simulation!O186*4.31 -> 0.017806779 | Z91: =Trend_Simulation!G186*Trend_Simulation!P186*4.31 -> 0.015373738 | AA91: =Trend_Simulation!H186*Trend_Simulation!Q186*4.31 -> 0.011178744 | AB91: =Trend_Simulation!#REF!*Trend_Simulation!#REF!*4.31 -> #REF! | AC91: =SUM(U91:AB91) -> #REF! | AD91: =Summary!I90 -> 0.10311563 | AE91: =AC91-AD91 -> #REF! | AF91: =LN(1+AD91) -> 0.098138571
J92: =Summary!A91 -> 39538 | K92: =K91*(1+Summary!B91) -> 0.78635256 | L92: =L91*(1+Summary!H91) -> 1.4096064 | M92: =M91*(1+Summary!I91) -> 3.9427208 | N92: =MAX($K$3:K92) -> 0.99069493 | O92: =MAX($L$3:L92) -> 1.4096064 | P92: =K92/N92-1 -> -0.20626165 | Q92: =L92/O92-1 -> 0 | R92: =M92/MAX($M$3:M92)-1 -> 0 | T92: =Summary!A91 -> 39538 | U92: =Trend_Simulation!B187*Trend_Simulation!K187*4.31 -> 0.013288651 | V92: =Trend_Simulation!C187*Trend_Simulation!L187*4.31 -> -0.016306042 | W92: =Trend_Simulation!D187*Trend_Simulation!M187*4.31 -> 0.023996281 | X92: =Trend_Simulation!E187*Trend_Simulation!N187*4.31 -> 0.01301749 | Y92: =Trend_Simulation!F187*Trend_Simulation!O187*4.31 -> 0.0034142309 | Z92: =Trend_Simulation!G187*Trend_Simulation!P187*4.31 -> -0.0056626894 | AA92: =Trend_Simulation!H187*Trend_Simulation!Q187*4.31 -> 0.025131669 | AB92: =Trend_Simulation!#REF!*Trend_Simulation!#REF!*4.31 -> #REF! | AC92: =SUM(U92:AB92) -> #REF! | AD92: =Summary!I91 -> 0.055691849 | AE92: =AC92-AD92 -> #REF! | AF92: =LN(1+AD92) -> 0.054196333
J93: =Summary!A92 -> 39568 | K93: =K92*(1+Summary!B92) -> 0.82312975 | L93: =L92*(1+Summary!H92) -> 1.362033 | M93: =M92*(1+Summary!I92) -> 3.3811892 | N93: =MAX($K$3:K93) -> 0.99069493 | O93: =MAX($L$3:L93) -> 1.4096064 | P93: =K93/N93-1 -> -0.16913902 | Q93: =L93/O93-1 -> -0.033749376 | R93: =M93/MAX($M$3:M93)-1 -> -0.14242237 | T93: =Summary!A92 -> 39568 | U93: =Trend_Simulation!B188*Trend_Simulation!K188*4.31 -> 0.017541486 | V93: =Trend_Simulation!C188*Trend_Simulation!L188*4.31 -> -0.016423986 | W93: =Trend_Simulation!D188*Trend_Simulation!M188*4.31 -> -0.050604447 | X93: =Trend_Simulation!E188*Trend_Simulation!N188*4.31 -> -0.024254403 | Y93: =Trend_Simulation!F188*Trend_Simulation!O188*4.31 -> -0.023571507 | Z93: =Trend_Simulation!G188*Trend_Simulation!P188*4.31 -> -0.020851622 | AA93: =Trend_Simulation!H188*Trend_Simulation!Q188*4.31 -> -0.027295331 | AB93: =Trend_Simulation!#REF!*Trend_Simulation!#REF!*4.31 -> #REF! | AC93: =SUM(U93:AB93) -> #REF! | AD93: =Summary!I92 -> -0.14242237 | AE93: =AC93-AD93 -> #REF! | AF93: =LN(1+AD93) -> -0.15364357
J94: =Summary!A93 -> 39599 | K94: =K93*(1+Summary!B93) -> 0.83177018 | L94: =L93*(1+Summary!H93) -> 1.3517478 | M94: =M93*(1+Summary!I93) -> 3.2734414 | N94: =MAX($K$3:K94) -> 0.99069493 | O94: =MAX($L$3:L94) -> 1.4096064 | P94: =K94/N94-1 -> -0.16041744 | Q94: =L94/O94-1 -> -0.0410459 | R94: =M94/MAX($M$3:M94)-1 -> -0.16975063 | T94: =Summary!A93 -> 39599 | U94: =Trend_Simulation!B189*Trend_Simulation!K189*4.31 -> 0.024978245 | V94: =Trend_Simulation!C189*Trend_Simulation!L189*4.31 -> 0.0072551084 | W94: =Trend_Simulation!D189*Trend_Simulation!M189*4.31 -> -0.018365881 | X94: =Trend_Simulation!E189*Trend_Simulation!N189*4.31 -> -0.016222563 | Y94: =Trend_Simulation!F189*Trend_Simulation!O189*4.31 -> -0.0056172571 | Z94: =Trend_Simulation!G189*Trend_Simulation!P189*4.31 -> -0.017638256 | AA94: =Trend_Simulation!H189*Trend_Simulation!Q189*4.31 -> -0.006935837 | AB94: =Trend_Simulation!#REF!*Trend_Simulation!#REF!*4.31 -> #REF! | AC94: =SUM(U94:AB94) -> #REF! | AD94: =Summary!I93 -> -0.031866817 | AE94: =AC94-AD94 -> #REF! | AF94: =LN(1+AD94) -> -0.032385615
J95: =Summary!A94 -> 39629 | K95: =K94*(1+Summary!B94) -> 0.75954509 | L95: =L94*(1+Summary!H94) -> 1.3725271 | M95: =M94*(1+Summary!I94) -> 3.4857915 | N95: =MAX($K$3:K95) -> 0.99069493 | O95: =MAX($L$3:L95) -> 1.4096064 | P95: =K95/N95-1 -> -0.23332091 | Q95: =L95/O95-1 -> -0.026304684 | R95: =M95/MAX($M$3:M95)-1 -> -0.11589186 | T95: =Summary!A94 -> 39629 | U95: =Trend_Simulation!B190*Trend_Simulation!K190*4.31 -> 0.010387977 | V95: =Trend_Simulation!C190*Trend_Simulation!L190*4.31 -> 0.01203079 | W95: =Trend_Simulation!D190*Trend_Simulation!M190*4.31 -> 0.017250978 | X95: =Trend_Simulation!E190*Trend_Simulation!N190*4.31 -> 0.012971531 | Y95: =Trend_Simulation!F190*Trend_Simulation!O190*4.31 -> 0.047363689 | Z95: =Trend_Simulation!G190*Trend_Simulation!P190*4.31 -> -0.030361253 | AA95: =Trend_Simulation!H190*Trend_Simulation!Q190*4.31 -> -0.0033896147 | AB95: =Trend_Simulation!#REF!*Trend_Simulation!#REF!*4.31 -> #REF! | AC95: =SUM(U95:AB95) -> #REF! | AD95: =Summary!I94 -> 0.064870602 | AE95: =AC95-AD95 -> #REF! | AF95: =LN(1+AD95) -> 0.062853291
J96: =Summary!A95 -> 39660 | K96: =K95*(1+Summary!B95) -> 0.75127391 | L96: =L95*(1+Summary!H95) -> 1.3673383 | M96: =M95*(1+Summary!I95) -> 3.4301803 | N96: =MAX($K$3:K96) -> 0.99069493 | O96: =MAX($L$3:L96) -> 1.4096064 | P96: =K96/N96-1 -> -0.24166977 | Q96: =L96/O96-1 -> -0.029985734 | R96: =M96/MAX($M$3:M96)-1 -> -0.12999664 | T96: =Summary!A95 -> 39660 | U96: =Trend_Simulation!B191*Trend_Simulation!K191*4.31 -> -0.020534659 | V96: =Trend_Simulation!C191*Trend_Simulation!L191*4.31 -> -0.004935845 | W96: =Trend_Simulation!D191*Trend_Simulation!M191*4.31 -> 0.010327025 | X96: =Trend_Simulation!E191*Trend_Simulation!N191*4.31 -> 0.0077653134 | Y96: =Trend_Simulation!F191*Trend_Simulation!O191*4.31 -> 0.0052580997 | Z96: =Trend_Simulation!G191*Trend_Simulation!P191*4.31 -> -0.0012634903 | AA96: =Trend_Simulation!H191*Trend_Simulation!Q191*4.31 -> -0.012910378 | AB96: =Trend_Simulation!#REF!*Trend_Simulation!#REF!*4.31 -> #REF! | AC96: =SUM(U96:AB96) -> #REF! | AD96: =Summary!I95 -> -0.015953688 | AE96: =AC96-AD96 -> #REF! | AF96: =LN(1+AD96) -> -0.016082318
J97: =Summary!A96 -> 39691 | K97: =K96*(1+Summary!B96) -> 0.76043128 | L97: =L96*(1+Summary!H96) -> 1.3612437 | M97: =M96*(1+Summary!I96) -> 3.3656593 | N97: =MAX($K$3:K97) -> 0.99069493 | O97: =MAX($L$3:L97) -> 1.4096064 | P97: =K97/N97-1 -> -0.23242639 | Q97: =L97/O97-1 -> -0.034309377 | R97: =M97/MAX($M$3:M97)-1 -> -0.14636123 | T97: =Summary!A96 -> 39691 | U97: =Trend_Simulation!B192*Trend_Simulation!K192*4.31 -> -0.015390277 | V97: =Trend_Simulation!C192*Trend_Simulation!L192*4.31 -> -0.027985108 | W97: =Trend_Simulation!D192*Trend_Simulation!M192*4.31 -> 0.020818611 | X97: =Trend_Simulation!E192*Trend_Simulation!N192*4.31 -> 0.016239401 | Y97: =Trend_Simulation!F192*Trend_Simulation!O192*4.31 -> -0.0059206038 | Z97: =Trend_Simulation!G192*Trend_Simulation!P192*4.31 -> -0.0035153436 | AA97: =Trend_Simulation!H192*Trend_Simulation!Q192*4.31 -> -0.003457634 | AB97: =Trend_Simulation!#REF!*Trend_Simulation!#REF!*4.31 -> #REF! | AC97: =SUM(U97:AB97) -> #REF! | AD97: =Summary!I96 -> -0.018809797 | AE97: =AC97-AD97 -> #REF! | AF97: =LN(1+AD97) -> -0.018988951
J98: =Summary!A97 -> 39721 | K98: =K97*(1+Summary!B97) -> 0.69241563 | L98: =L97*(1+Summary!H97) -> 1.3856958 | M98: =M97*(1+Summary!I97) -> 3.6207901 | N98: =MAX($K$3:K98) -> 0.99069493 | O98: =MAX($L$3:L98) -> 1.4096064 | P98: =K98/N98-1 -> -0.30108088 | Q98: =L98/O98-1 -> -0.016962617 | R98: =M98/MAX($M$3:M98)-1 -> -0.081651897 | T98: =Summary!A97 -> 39721 | U98: =Trend_Simulation!B193*Trend_Simulation!K193*4.31 -> -0.022295488 | V98: =Trend_Simulation!C193*Trend_Simulation!L193*4.31 -> 0.01516225 | W98: =Trend_Simulation!D193*Trend_Simulation!M193*4.31 -> -0.010662609 | X98: =Trend_Simulation!E193*Trend_Simulation!N193*4.31 -> -0.0076867945 | Y98: =Trend_Simulation!F193*Trend_Simulation!O193*4.31 -> 0.043891461 | Z98: =Trend_Simulation!G193*Trend_Simulation!P193*4.31 -> 0.04576424 | AA98: =Trend_Simulation!H193*Trend_Simulation!Q193*4.31 -> 0.013247733 | AB98: =Trend_Simulation!#REF!*Trend_Simulation!#REF!*4.31 -> #REF! | AC98: =SUM(U98:AB98) -> #REF! | AD98: =Summary!I97 -> 0.075804117 | AE98: =AC98-AD98 -> #REF! | AF98: =LN(1+AD98) -> 0.073068398
J99: =Summary!A98 -> 39752 | K99: =K98*(1+Summary!B98) -> 0.57292667 | L99: =L98*(1+Summary!H98) -> 1.4022373 | M99: =M98*(1+Summary!I98) -> 3.8031895 | N99: =MAX($K$3:K99) -> 0.99069493 | O99: =MAX($L$3:L99) -> 1.4096064 | P99: =K99/N99-1 -> -0.42169214 | Q99: =L99/O99-1 -> -0.0052277656 | R99: =M99/MAX($M$3:M99)-1 -> -0.035389583 | T99: =Summary!A98 -> 39752 | U99: =Trend_Simulation!B194*Trend_Simulation!K194*4.31 -> -0.053749343 | V99: =Trend_Simulation!C194*Trend_Simulation!L194*4.31 -> -0.052519224 | W99: =Trend_Simulation!D194*Trend_Simulation!M194*4.31 -> 0.0046977276 | X99: =Trend_Simulation!E194*Trend_Simulation!N194*4.31 -> -0.014227489 | Y99: =Trend_Simulation!F194*Trend_Simulation!O194*4.31 -> 0.076285661 | Z99: =Trend_Simulation!G194*Trend_Simulation!P194*4.31 -> 0.046001932 | AA99: =Trend_Simulation!H194*Trend_Simulation!Q194*4.31 -> 0.044960671 | AB99: =Trend_Simulation!#REF!*Trend_Simulation!#REF!*4.31 -> #REF! | AC99: =SUM(U99:AB99) -> #REF! | AD99: =Summary!I98 -> 0.050375576 | AE99: =AC99-AD99 -> #REF! | AF99: =LN(1+AD99) -> 0.049147791
... J125: =Summary!A124 -> 40543 | K125: =K124*(1+Summary!B124) -> 0.76774241 | L125: =L124*(1+Summary!H124) -> 1.5676793 | M125: =M124*(1+Summary!I124) -> 5.8321691 | N125: =MAX($K$3:K125) -> 0.99069493 | O125: =MAX($L$3:L125) -> 1.5685974 | P125: =K125/N125-1 -> -0.22504659 | Q125: =L125/O125-1 -> -0.00058530616 | R125: =M125/MAX($M$3:M125)-1 -> -0.0041815375 | T125: =Summary!A124 -> 40543 | U125: =Trend_Simulation!B220*Trend_Simulation!K220*4.31 -> 0.0068224139 | V125: =Trend_Simulation!C220*Trend_Simulation!L220*4.31 -> 0.007480411 | W125: =Trend_Simulation!D220*Trend_Simulation!M220*4.31 -> 0.0079574924 | X125: =Trend_Simulation!E220*Trend_Simulation!N220*4.31 -> -0.024563784 | Y125: =Trend_Simulation!F220*Trend_Simulation!O220*4.31 -> 0.020071477 | Z125: =Trend_Simulation!G220*Trend_Simulation!P220*4.31 -> 0.011983463 | AA125: =Trend_Simulation!H220*Trend_Simulation!Q220*4.31 -> 0.017640008 | AB125: =Trend_Simulation!#REF!*Trend_Simulation!#REF!*4.31 -> #REF! | AC125: =SUM(U125:AB125) -> #REF! | AD125: =Summary!I124 -> 0.046401868 | AE125: =AC125-AD125 -> #REF! | AF125: =LN(1+AD125) -> 0.045357487
...

Sheet Prices_Daily
B1: Commodity | C1: Commodity | D1: Commodity | E1: Commodity | F1: Commodity | G1: Commodity | H1: Commodity | I1: Bonds | J1: Bonds | K1: Bonds | L1: Equity | M1: Equity | N1: Equity | O1: Currency/Alternative | P1: Currency/Alternative | Q1: Equity | R1: Currency/Alternative | S1: Equity
A2: date | B2: GSCI Brent Crude Oil | C2: GSCI Rbob Gas | D2: GSCI Gasoil | E2: GSCI Copper | F2: GSCI Gold | G2: GSCI Soybean | H2: GSCI Cocoa | I2: Japan Gov't Bond | J2: US 10Y Gov't Bond | K2: German 10y Gov't Bond FUTURES INDEX | L2: S&P 500 Futures Excess Rtn Index | M2: Russell 2000 Futures Excess Rtn Index | N2: Nasdaq 100 Futures Excess Rtn Index | O2: SGI FX Forwards JPY/USD in USD | P2: SGI FX Forwards EUR/USD in USD | Q2: MSCI EM Excess Rtn Index | R2: Long USD Currency | S2: China Eqty Fut Index
B3: SPGCBRP INDEX | C3: SPGCHUP INDEX | D3: SPGCGOP INDEX | E3: SPGCICP INDEX | F3: SPGCGCP INDEX | G3: SPGCSOP INDEX | H3: SPGCCCP INDEX | I3: SGIXBJB INDEX | J3: SGIXBTY INDEX | K3: SGIXBRX INDEX | L3: SPXFP INDEX | M3: RTYFPE INDEX | N3: NDXNQER INDEX | O3: SGIXFJPU INDEX | P3: SGIXFEUU INDEX | Q3: MXEFERUS INDEX | R3: DXY CURNCY | S3: FRSICNEE INDEX
A4: 32874 | B4: #N/A N/A | C4: 224.418 | D4: #N/A N/A | E4: 128.555 | F4: 74.612 | G4: 220.0402 | H4: 30.1438 | I4: 1184.181 | J4: 1708.328 | K4: #N/A N/A | L4: #N/A N/A | M4: #N/A N/A | N4: #N/A N/A | O4: #N/A N/A | P4: #N/A N/A | Q4: #N/A N/A | R4: 93.16 | S4: #N/A N/A
A5: 32875 | B5: #N/A N/A | C5: 238.737 | D5: #N/A N/A | E5: 128.3133 | F5: 74.0412 | G5: 217.5838 | H5: 30.2741 | I5: 1184.181 | J5: 1706.187 | K5: #N/A N/A | L5: #N/A N/A | M5: #N/A N/A | N5: #N/A N/A | O5: #N/A N/A | P5: #N/A N/A | Q5: #N/A N/A | R5: 94.25 | S5: #N/A N/A
A6: 32876 | B6: #N/A N/A | C6: 244.334 | D6: #N/A N/A | E6: 132.4817 | F6: 72.9916 | G6: 219.7568 | H6: 29.7201 | I6: 1184.181 | J6: 1702.44 | K6: #N/A N/A | L6: #N/A N/A | M6: #N/A N/A | N6: #N/A N/A | O6: #N/A N/A | P6: #N/A N/A | Q6: #N/A N/A | R6: 94.45 | S6: #N/A N/A
A7: 32877 | B7: #N/A N/A | C7: 237.283 | D7: #N/A N/A | E7: 131.1527 | F7: 73.8018 | G7: 217.8672 | H7: 30.6326 | I7: 1175.446 | J7: 1703.511 | K7: #N/A N/A | L7: #N/A N/A | M7: #N/A N/A | N7: #N/A N/A | O7: #N/A N/A | P7: #N/A N/A | Q7: #N/A N/A | R7: 92.54 | S7: #N/A N/A
A8: 32878 | B8: #N/A N/A | C8: 226.126 | D8: #N/A N/A | E8: 132.3005 | F8: 75.2197 | G8: 218.0562 | H8: 30.9259 | I8: 1173.032 | J8: 1702.975 | K8: #N/A N/A | L8: #N/A N/A | M8: #N/A N/A | N8: #N/A N/A | O8: #N/A N/A | P8: #N/A N/A | Q8: #N/A N/A | R8: 93.06 | S8: #N/A N/A
A9: 32881 | B9: #N/A N/A | C9: 213.088 | D9: #N/A N/A | E9: 134.5357 | F9: 74.5768 | G9: 220.5126 | H9: 30.6326 | I9: 1167.515 | J9: 1700.834 | K9: #N/A N/A | L9: #N/A N/A | M9: #N/A N/A | N9: #N/A N/A | O9: #N/A N/A | P9: #N/A N/A | Q9: #N/A N/A | R9: 92.05 | S9: #N/A N/A
A10: 32882 | B10: #N/A N/A | C10: 219.784 | D10: #N/A N/A | E10: 133.1462 | F10: 74.7966 | G10: 220.2292 | H10: 31.1866 | I10: 1152.918 | J10: 1700.299 | K10: #N/A N/A | L10: #N/A N/A | M10: #N/A N/A | N10: #N/A N/A | O10: #N/A N/A | P10: #N/A N/A | Q10: #N/A N/A | R10: 92.36 | S10: #N/A N/A
A11: 32883 | B11: #N/A N/A | C11: 231.118 | D11: #N/A N/A | E11: 130.609 | F11: 76.2809 | G11: 219.0954 | H11: 31.5125 | I11: 1148.55 | J11: 1699.764 | K11: #N/A N/A | L11: #N/A N/A | M11: #N/A N/A | N11: #N/A N/A | O11: #N/A N/A | P11: #N/A N/A | Q11: #N/A N/A | R11: 92.5 | S11: #N/A N/A
A12: 32884 | B12: #N/A N/A | C12: 233.94 | D12: #N/A N/A | E12: 131.938 | F12: 76.5507 | G12: 219.9457 | H12: 32.7834 | I12: 1145.217 | J12: 1699.228 | K12: #N/A N/A | L12: #N/A N/A | M12: #N/A N/A | N12: #N/A N/A | O12: #N/A N/A | P12: #N/A N/A | Q12: #N/A N/A | R12: 92.44 | S12: #N/A N/A
A13: 32885 | B13: #N/A N/A | C13: 233.977 | D13: #N/A N/A | E13: 127.9509 | F13: 76.4052 | G13: 218.3396 | H13: 32.1642 | I13: 1131.195 | J13: 1694.411 | K13: #N/A N/A | L13: #N/A N/A | M13: #N/A N/A | N13: #N/A N/A | O13: #N/A N/A | P13: #N/A N/A | Q13: #N/A N/A | R13: 92.56 | S13: #N/A N/A
A14: 32888 | B14: #N/A N/A | C14: 229.57 | D14: #N/A N/A | E14: 125.6553 | F14: 76.4962 | G14: 217.5838 | H14: 31.8384 | I14: 1131.195 | J14: 1686.382 | K14: #N/A N/A | L14: #N/A N/A | M14: #N/A N/A | N14: #N/A N/A | O14: #N/A N/A | P14: #N/A N/A | Q14: #N/A N/A | R14: 92.95 | S14: #N/A N/A
A15: 32889 | B15: #N/A N/A | C15: 232.411 | D15: #N/A N/A | E15: 126.2594 | F15: 75.9505 | G15: 214.6549 | H15: 31.2192 | I15: 1114.184 | J15: 1682.635 | K15: #N/A N/A | L15: #N/A N/A | M15: #N/A N/A | N15: #N/A N/A | O15: #N/A N/A | P15: #N/A N/A | Q15: #N/A N/A | R15: 92.87 | S15: #N/A N/A
... A503: 33571 | B503: #N/A N/A | C503: 356.187 | D503: #N/A N/A | E503: 158.3228 | F503: 60.4535 | G503: 171.8412 | H503: 28.5986 | I503: 1125.583 | J503: 1812.315 | K503: #N/A N/A | L503: #N/A N/A | M503: #N/A N/A | N503: #N/A N/A | O503: #N/A N/A | P503: #N/A N/A | Q503: #N/A N/A | R503: 88.19 | S503: #N/A N/A
A504: 33574 | B504: #N/A N/A | C504: 350.152 | D504: #N/A N/A | E504: 157.0587 | F504: 60.258 | G504: 174.1551 | H504: 28.4825 | I504: 1129.404 | J504: 1819.482 | K504: 1000 | L504: #N/A N/A | M504: #N/A N/A | N504: #N/A N/A | O504: #N/A N/A | P504: #N/A N/A | Q504: #N/A N/A | R504: 87.74 | S504: #N/A N/A
A505: 33575 | B505: #N/A N/A | C505: 338.5 | D505: #N/A N/A | E505: 157.2153 | F505: 59.6878 | G505: 171.3785 | H505: 29.1562 | I505: 1127.718 | J505: 1826.649 | K505: 1000.901 | L505: #N/A N/A | M505: #N/A N/A | N505: #N/A N/A | O505: #N/A N/A | P505: #N/A N/A | Q505: #N/A N/A | R505: 87.51 | S505: #N/A N/A
A506: 33576 | B506: #N/A N/A | C506: 341.129 | D506: #N/A N/A | E506: 156.1104 | F506: 59.9322 | G506: 173.6152 | H506: 29.6441 | I506: 1130.106 | J506: 1840.983 | K506: 1000.262 | L506: #N/A N/A | M506: #N/A N/A | N506: #N/A N/A | O506: #N/A N/A | P506: #N/A N/A | Q506: #N/A N/A | R506: 87.1 | S506: #N/A N/A
A507: 33577 | B507: #N/A N/A | C507: 334.497 | D507: #N/A N/A | E507: 154.2869 | F507: 60.2743 | G507: 172.0726 | H507: 29.9461 | I507: 1133.082 | J507: 1834.367 | K507: 1002.964 | L507: #N/A N/A | M507: #N/A N/A | N507: #N/A N/A | O507: #N/A N/A | P507: #N/A N/A | Q507: #N/A N/A | R507: 86.68 | S507: #N/A N/A
A508: 33578 | B508: #N/A N/A | C508: 328.641 | D508: #N/A N/A | E508: 154.3652 | F508: 60.5838 | G508: 171.3013 | H508: 29.8299 | I508: 1136.479 | J508: 1827.2 | K508: 1004.126 | L508: #N/A N/A | M508: #N/A N/A | N508: #N/A N/A | O508: #N/A N/A | P508: #N/A N/A | Q508: #N/A N/A | R508: 85.75 | S508: #N/A N/A
A509: 33581 | B509: #N/A N/A | C509: 318.448 | D509: #N/A N/A | E509: 153.7358 | F509: 60.5349 | G509: 170.9167 | H509: 29.3885 | I509: 1134.795 | J509: 1833.264 | K509: 1002.964 | L509: #N/A N/A | M509: #N/A N/A | N509: #N/A N/A | O509: #N/A N/A | P509: #N/A N/A | Q509: #N/A N/A | R509: 86.01 | S509: #N/A N/A
A510: 33582 | B510: #N/A N/A | C510: 322.858 | D510: #N/A N/A | E510: 151.3486 | F510: 60.4535 | G510: 169.0749 | H510: 29.6208 | I510: 1137.714 | J510: 1833.264 | K510: 1002.499 | L510: #N/A N/A | M510: #N/A N/A | N510: #N/A N/A | O510: #N/A N/A | P510: #N/A N/A | Q510: #N/A N/A | R510: 86.25 | S510: #N/A N/A
A511: 33583 | B511: #N/A N/A | C511: 319.339 | D511: #N/A N/A | E511: 152.5917 | F511: 60.0462 | G511: 169.1514 | H511: 29.3885 | I511: 1136.255 | J511: 1832.713 | K511: 1001.802 | L511: #N/A N/A | M511: #N/A N/A | N511: #N/A N/A | O511: #N/A N/A | P511: #N/A N/A | Q511: #N/A N/A | R511: 86.26 | S511: #N/A N/A
A512: 33584 | B512: #N/A N/A | C512: 325.8 | D512: #N/A N/A | E512: 152.4348 | F512: 58.629 | G512: 167.8534 | H512: 30.039 | I512: 1137.602 | J512: 1835.47 | K512: 1004.707 | L512: #N/A N/A | M512: #N/A N/A | N512: #N/A N/A | O512: #N/A N/A | P512: #N/A N/A | Q512: #N/A N/A | R512: 86.48 | S512: #N/A N/A
A513: 33585 | B513: #N/A N/A | C513: 326.507 | D513: #N/A N/A | E513: 152.6695 | F513: 58.857 | G513: 170.7475 | H513: 30.4339 | I513: 1136.704 | J513: 1829.956 | K513: 1003.196 | L513: #N/A N/A | M513: #N/A N/A | N513: #N/A N/A | O513: #N/A N/A | P513: #N/A N/A | Q513: #N/A N/A | R513: 86.62 | S513: #N/A N/A
A514: 33588 | B514: #N/A N/A | C514: 325.623 | D514: #N/A N/A | E514: 152.826 | F514: 58.7919 | G514: 169.8336 | H514: 30.9683 | I514: 1138.163 | J514: 1832.713 | K514: 1005.753 | L514: #N/A N/A | M514: #N/A N/A | N514: #N/A N/A | O514: #N/A N/A | P514: #N/A N/A | Q514: #N/A N/A | R514: 86.02 | S514: #N/A N/A
A515: 33589 | B515: #N/A N/A | C515: 323.915 | D515: #N/A N/A | E515: 153.2166 | F515: 58.4986 | G515: 169.6051 | H515: 30.5036 | I515: 1137.602 | J515: 1836.572 | K515: 1009.007 | L515: #N/A N/A | M515: #N/A N/A | N515: #N/A N/A | O515: #N/A N/A | P515: #N/A N/A | Q515: #N/A N/A | R515: 85.89 | S515: #N/A N/A
... A2009: 35681 | B2009: #N/A N/A | C2009: 370.119 | D2009: #N/A N/A | E2009: 193.3535 | F2009: 42.5604 | G2009: 199.7409 | H2009: 15.6315 | I2009: 1720.175 | J2009: 2255.397 | K2009: 1289.077 | L2009: #N/A N/A | M2009: #N/A N/A | N2009: #N/A N/A | O2009: #N/A N/A | P2009: #N/A N/A | Q2009: #N/A N/A | R2009: 99.07 | S2009: #N/A N/A
A2010: 35682 | B2010: #N/A N/A | C2010: 371.15 | D2010: #N/A N/A | E2010: 191.985 | F2010: 42.4948 | G2010: 202.3278 | H2010: 15.6597 | I2010: 1717.466 | J2010: 2254.749 | K2010: 1291.234 | L2010: 100 | M2010: #N/A N/A | N2010: #N/A N/A | O2010: #N/A N/A | P2010: #N/A N/A | Q2010: #N/A N/A | R2010: 99.05 | S2010: #N/A N/A
A2011: 35683 | B2011: #N/A N/A | C2011: 365.572 | D2011: #N/A N/A | E2011: 193.2716 | F2011: 42.4948 | G2011: 200.368 | H2011: 15.7161 | I2011: 1720.175 | J2011: 2252.805 | K2011: 1291.488 | L2011: 97.99 | M2011: #N/A N/A | N2011: #N/A N/A | O2011: #N/A N/A | P2011: #N/A N/A | Q2011: #N/A N/A | R2011: 98.71 | S2011: #N/A N/A
A2012: 35684 | B2012: #N/A N/A | C2012: 366.949 | D2012: #N/A N/A | E2012: 188.2002 | F2012: 42.8226 | G2012: 201.7007 | H2012: 15.2929 | I2012: 1718.414 | J2012: 2249.565 | K2012: 1290.346 | L2012: 97.28 | M2012: #N/A N/A | N2012: #N/A N/A | O2012: #N/A N/A | P2012: #N/A N/A | Q2012: #N/A N/A | R2012: 97.96 | S2012: #N/A N/A
A2013: 35685 | B2013: #N/A N/A | C2013: 366.063 | D2013: #N/A N/A | E2013: 187.9307 | F2013: 42.7701 | G2013: 197.9379 | H2013: 15.4246 | I2013: 1724.103 | J2013: 2261.878 | K2013: 1293.265 | L2013: 98.93 | M2013: #N/A N/A | N2013: #N/A N/A | O2013: #N/A N/A | P2013: #N/A N/A | Q2013: #N/A N/A | R2013: 97.73 | S2013: #N/A N/A
A2014: 35688 | B2014: #N/A N/A | C2014: 361.793 | D2014: #N/A N/A | E2014: 189.142 | F2014: 42.5735 | G2014: 199.0354 | H2014: 15.528 | I2014: 1724.103 | J2014: 2262.526 | K2014: 1293.265 | L2014: 98.68 | M2014: #N/A N/A | N2014: #N/A N/A | O2014: #N/A N/A | P2014: #N/A N/A | Q2014: #N/A N/A | R2014: 97.28 | S2014: #N/A N/A
A2015: 35689 | B2015: #N/A N/A | C2015: 368.134 | D2015: #N/A N/A | E2015: 185.3735 | F2015: 42.3244 | G2015: 202.7982 | H2015: 15.9795 | I2015: 1728.166 | J2015: 2285.208 | K2015: 1299.483 | L2015: 101.28 | M2015: #N/A N/A | N2015: #N/A N/A | O2015: #N/A N/A | P2015: #N/A N/A | Q2015: #N/A N/A | R2015: 97.68 | S2015: #N/A N/A
A2016: 35690 | B2016: #N/A N/A | C2016: 365.805 | D2016: #N/A N/A | E2016: 186.181 | F2016: 42.2457 | G2016: 201.9359 | H2016: 15.6879 | I2016: 1729.521 | J2016: 2287.152 | K2016: 1299.863 | L2016: 101.27 | M2016: #N/A N/A | N2016: #N/A N/A | O2016: #N/A N/A | P2016: #N/A N/A | Q2016: #N/A N/A | R2016: 97.7 | S2016: #N/A N/A
A2017: 35691 | B2017: #N/A N/A | C2017: 361.082 | D2017: #N/A N/A | E2017: 190.3981 | F2017: 42.3112 | G2017: 199.1138 | H2017: 15.782 | I2017: 1728.166 | J2017: 2285.856 | K2017: 1303.924 | L2017: 101.48 | M2017: #N/A N/A | N2017: #N/A N/A | O2017: #N/A N/A | P2017: #N/A N/A | Q2017: #N/A N/A | R2017: 97.99 | S2017: #N/A N/A
A2018: 35692 | B2018: #N/A N/A | C2018: 360.758 | D2018: #N/A N/A | E2018: 190.8467 | F2018: 42.3506 | G2018: 200.3681 | H2018: 15.5186 | I2018: 1728.166 | J2018: 2287.152 | K2018: 1301.259 | L2018: 101.77 | M2018: #N/A N/A | N2018: #N/A N/A | O2018: #N/A N/A | P2018: #N/A N/A | Q2018: #N/A N/A | R2018: 97.83 | S2018: #N/A N/A
A2019: 35695 | B2019: #N/A N/A | C2019: 367.81 | D2019: #N/A N/A | E2019: 187.9755 | F2019: 42.3637 | G2019: 199.2706 | H2019: 15.4528 | I2019: 1733.313 | J2019: 2291.688 | K2019: 1303.543 | L2019: 102.36 | M2019: #N/A N/A | N2019: #N/A N/A | O2019: #N/A N/A | P2019: #N/A N/A | Q2019: #N/A N/A | R2019: 98.43 | S2019: #N/A N/A
A2020: 35696 | B2020: #N/A N/A | C2020: 367.357 | D2020: #N/A N/A | E2020: 187.9755 | F2020: 42.5079 | G2020: 197.8596 | H2020: 15.5939 | I2020: 1733.313 | J2020: 2287.152 | K2020: 1304.051 | L2020: 101.92 | M2020: #N/A N/A | N2020: #N/A N/A | O2020: #N/A N/A | P2020: #N/A N/A | Q2020: #N/A N/A | R2020: 98.39 | S2020: #N/A N/A
A2021: 35697 | B2021: #N/A N/A | C2021: 368.587 | D2021: #N/A N/A | E2021: 188.3793 | F2021: 42.7308 | G2021: 200.1329 | H2021: 15.9042 | I2021: 1733.99 | J2021: 2292.985 | K2021: 1308.112 | L2021: 101.11 | M2021: #N/A N/A | N2021: #N/A N/A | O2021: #N/A N/A | P2021: #N/A N/A | Q2021: #N/A N/A | R2021: 97.49 | S2021: #N/A N/A
... A2357: 36167 | B2357: #N/A N/A | C2357: 191.805 | D2357: #N/A N/A | E2357: 121.4549 | F2357: 36.67 | G2357: 172.9699 | H2357: 11.3248 | I2357: 1806.458 | J2357: 2451.315 | K2357: 1506.275 | L2357: 129.81 | M2357: #N/A N/A | N2357: #N/A N/A | O2357: #N/A N/A | P2357: #N/A N/A | Q2357: #N/A N/A | R2357: 93.72 | S2357: #N/A N/A
A2358: 36168 | B2358: 100 | C2358: 188.498 | D2358: 100 | E2358: 123.085 | F2358: 36.6199 | G2358: 175.0197 | H2358: 11.26727 | I2358: 1782.724 | J2358: 2437.091 | K2358: 1508.732 | L2358: 130.85 | M2358: #N/A N/A | N2358: #N/A N/A | O2358: #N/A N/A | P2358: #N/A N/A | Q2358: #N/A N/A | R2358: 94.35 | S2358: #N/A N/A
A2359: 36171 | B2359: 102.0426 | C2359: 193.029 | D2359: 105.1044 | E2359: 124.2311 | F2359: 36.8203 | G2359: 172.4181 | H2359: 11.4152 | I2359: 1792.739 | J2359: 2431.919 | K2359: 1497.872 | L2359: 129.41 | M2359: #N/A N/A | N2359: #N/A N/A | O2359: #N/A N/A | P2359: #N/A N/A | Q2359: #N/A N/A | R2359: 94.66 | S2359: #N/A N/A
A2360: 36172 | B2360: 97.8724 | C2360: 187.479 | D2360: 101.1601 | E2360: 124.4001 | F2360: 36.2825 | G2360: 169.8165 | H2360: 11.43985 | I2360: 1791.367 | J2360: 2440.324 | K2360: 1507.827 | L2360: 127.1 | M2360: #N/A N/A | N2360: #N/A N/A | O2360: #N/A N/A | P2360: #N/A N/A | Q2360: #N/A N/A | R2360: 94.79 | S2360: #N/A N/A
A2361: 36173 | B2361: 94.383 | C2361: 179.89 | D2361: 95.5917 | E2361: 123.4128 | F2361: 35.9953 | G2361: 168.3186 | H2361: 11.33301 | I2361: 1797.129 | J2361: 2450.022 | K2361: 1511.447 | L2361: 125.88 | M2361: #N/A N/A | N2361: #N/A N/A | O2361: #N/A N/A | P2361: #N/A N/A | Q2361: #N/A N/A | R2361: 94.25 | S2361: #N/A N/A
A2362: 36174 | B2362: 93.3617 | C2362: 176.192 | D2362: 92.8075 | E2362: 122.4816 | F2362: 36.0452 | G2362: 168.3186 | H2362: 11.34945 | I2362: 1805.361 | J2362: 2462.306 | K2362: 1515.196 | L2362: 123.84 | M2362: #N/A N/A | N2362: #N/A N/A | O2362: #N/A N/A | P2362: #N/A N/A | Q2362: #N/A N/A | R2362: 94.03 | S2362: #N/A N/A
A2363: 36175 | B2363: 92.9362 | C2363: 174.757 | D2363: 91.4154 | E2363: 123.8493 | F2363: 36.0452 | G2363: 167.8456 | H2363: 11.09468 | I2363: 1805.361 | J2363: 2451.315 | K2363: 1513.515 | L2363: 126.84 | M2363: #N/A N/A | N2363: #N/A N/A | O2363: #N/A N/A | P2363: #N/A N/A | Q2363: #N/A N/A | R2363: 94.72 | S2363: #N/A N/A
A2364: 36178 | B2364: 92.9362 | C2364: 174.757 | D2364: 91.4154 | E2364: 123.8493 | F2364: 36.0452 | G2364: 167.8456 | H2364: 11.09468 | I2364: 1797.266 | J2364: 2451.315 | K2364: 1516.23 | L2364: 126.84 | M2364: #N/A N/A | N2364: #N/A N/A | O2364: #N/A N/A | P2364: #N/A N/A | Q2364: #N/A N/A | R2364: 94.67 | S2364: #N/A N/A
A2365: 36179 | B2365: 92.3404 | C2365: 174.518 | D2365: 93.5035 | E2365: 124.3122 | F2365: 35.9705 | G2365: 165.5593 | H2365: 10.99606 | I2365: 1786.977 | J2365: 2449.375 | K2365: 1517.264 | L2365: 127.71 | M2365: #N/A N/A | N2365: #N/A N/A | O2365: #N/A N/A | P2365: #N/A N/A | Q2365: #N/A N/A | R2365: 94.52 | S2365: #N/A N/A
A2366: 36180 | B2366: 90.5532 | C2366: 167.918 | D2366: 90.4873 | E2366: 122.7551 | F2366: 36.0577 | G2366: 166.5054 | H2366: 11.02071 | I2366: 1795.895 | J2366: 2443.556 | K2366: 1511.964 | L2366: 128.85 | M2366: #N/A N/A | N2366: #N/A N/A | O2366: #N/A N/A | P2366: #N/A N/A | Q2366: #N/A N/A | R2366: 94.72 | S2366: #N/A N/A
A2367: 36181 | B2367: 93.8723 | C2367: 171.266 | D2367: 91.1833 | E2367: 123.4074 | F2367: 36.1075 | G2367: 167.2938 | H2367: 11.09467 | I2367: 1790.956 | J2367: 2452.608 | K2367: 1517.781 | L2367: 125.27 | M2367: #N/A N/A | N2367: #N/A N/A | O2367: #N/A N/A | P2367: #N/A N/A | Q2367: #N/A N/A | R2367: 94.5 | S2367: #N/A N/A
A2368: 36182 | B2368: 95.0638 | C2368: 176.336 | D2368: 91.4154 | E2368: 122.3974 | F2368: 35.9456 | G2368: 165.7959 | H2368: 10.82347 | I2368: 1793.425 | J2368: 2463.599 | K2368: 1520.496 | L2368: 125.22 | M2368: #N/A N/A | N2368: #N/A N/A | O2368: #N/A N/A | P2368: #N/A N/A | Q2368: #N/A N/A | R2368: 94.66 | S2368: #N/A N/A
A2369: 36185 | B2369: 93.2766 | C2369: 172.27 | D2369: 90.2553 | E2369: 121.682 | F2369: 36.0826 | G2369: 163.1943 | H2369: 10.76594 | I2369: 1788.898 | J2369: 2463.599 | K2369: 1520.109 | L2369: 126.33 | M2369: #N/A N/A | N2369: #N/A N/A | O2369: #N/A N/A | P2369: #N/A N/A | Q2369: #N/A N/A | R2369: 94.73 | S2369: #N/A N/A
... A2377: 36195 | B2377: 90.8085 | C2377: 170.979 | D2377: 90.0233 | E2377: 122.3552 | F2377: 36.2569 | G2377: 160.435 | H2377: 10.81524 | I2377: 1755.835 | J2377: 2424.16 | K2377: 1499.424 | L2377: 127.93 | M2377: #N/A N/A | N2377: #N/A N/A | O2377: #N/A N/A | P2377: #N/A N/A | Q2377: #N/A N/A | R2377: 95.68 | S2377: #N/A N/A
A2378: 36196 | B2378: 89.5319 | C2378: 167.344 | D2378: 87.7031 | E2378: 122.9023 | F2378: 36.1697 | G2378: 162.0118 | H2378: 10.73306 | I2378: 1740.882 | J2378: 2418.988 | K2378: 1501.88 | L2378: 126.33 | M2378: #N/A N/A | N2378: #N/A N/A | O2378: #N/A N/A | P2378: 100 | Q2378: #N/A N/A | R2378: 96.22 | S2378: #N/A N/A
A2379: 36199 | B2379: 88.0227 | C2379: 166.321 | D2379: 86.7332 | E2379: 125.2134 | F2379: 36.2693 | G2379: 160.1856 | H2379: 10.57106 | I2379: 1764.89 | J2379: 2422.221 | K2379: 1494.123 | L2379: 126.71 | M2379: #N/A N/A | N2379: #N/A N/A | O2379: #N/A N/A | P2379: 99.6671 | Q2379: #N/A N/A | R2379: 96.01 | S2379: #N/A N/A
A2380: 36200 | B2380: 87.7697 | C2380: 164.863 | D2380: 85.8134 | E2380: 123.8708 | F2380: 36.0079 | G2380: 157.5447 | H2380: 10.54337 | I2380: 1785.468 | J2380: 2427.393 | K2380: 1502.268 | L2380: 123.84 | M2380: #N/A N/A | N2380: #N/A N/A | O2380: #N/A N/A | P2380: 100.1117 | Q2380: #N/A N/A | R2380: 96.28 | S2380: #N/A N/A
A2381: 36201 | B2381: 87.5852 | C2381: 162.073 | D2381: 86.9124 | E2381: 122.3793 | F2381: 35.9456 | G2381: 157.482 | H2381: 10.59364 | I2381: 1784.782 | J2381: 2425.453 | K2381: 1502.785 | L2381: 124.56 | M2381: #N/A N/A | N2381: #N/A N/A | O2381: #N/A N/A | P2381: 100.2949 | Q2381: #N/A N/A | R2381: 95.96 | S2381: #N/A N/A
A2382: 36202 | B2382: 87.9358 | C2382: 161.078 | D2382: 87.095 | E2382: 122.7557 | F2382: 36.0203 | G2382: 156.3546 | H2382: 10.4289 | I2382: 1784.782 | J2382: 2424.16 | K2382: 1505.371 | L2382: 128.26 | M2382: #N/A N/A | N2382: #N/A N/A | O2382: #N/A N/A | P2382: 100.066 | Q2382: #N/A N/A | R2382: 96.68 | S2382: #N/A N/A
A2383: 36203 | B2383: 88.2679 | C2383: 161.819 | D2383: 86.6402 | E2383: 121.9831 | F2383: 36.2569 | G2383: 155.3388 | H2383: 10.22773 | I2383: 1773.121 | J2383: 2403.471 | K2383: 1494.64 | L2383: 125.8 | M2383: #N/A N/A | N2383: #N/A N/A | O2383: #N/A N/A | P2383: 99.8923 | Q2383: #N/A N/A | R2383: 96.31 | S2383: #N/A N/A
A2384: 36206 | B2384: 88.2679 | C2384: 161.819 | D2384: 86.6402 | E2384: 121.9831 | F2384: 36.2569 | G2384: 155.3388 | H2384: 10.22773 | I2384: 1768.32 | J2384: 2403.471 | K2384: 1487.659 | L2384: 125.8 | M2384: #N/A N/A | N2384: #N/A N/A | O2384: #N/A N/A | P2384: 99.5239 | Q2384: #N/A N/A | R2384: 96.79 | S2384: #N/A N/A
A2385: 36207 | B2385: 85.0295 | C2385: 157.503 | D2385: 83.9114 | E2385: 117.7444 | F2385: 35.7838 | G2385: 154.0105 | H2385: 10.46914 | I2385: 1782.724 | J2385: 2404.118 | K2385: 1487.659 | L2385: 126.21 | M2385: #N/A N/A | N2385: #N/A N/A | O2385: #N/A N/A | P2385: 99.0171 | Q2385: #N/A N/A | R2385: 97.21 | S2385: #N/A N/A
A2386: 36208 | B2386: 85.3616 | C2386: 157.372 | D2386: 86.4128 | E2386: 117.4312 | F2386: 35.6468 | G2386: 153.6979 | H2386: 10.54156 | I2386: 1790.27 | J2386: 2410.583 | K2386: 1492.055 | L2386: 124.89 | M2386: #N/A N/A | N2386: #N/A N/A | O2386: #N/A N/A | P2386: 99.4781 | Q2386: #N/A N/A | R2386: 97.06 | S2386: #N/A N/A
A2387: 36209 | B2387: 89.5135 | C2387: 163.126 | D2387: 85.0484 | E2387: 115.7608 | F2387: 35.7838 | G2387: 152.2133 | H2387: 10.61398 | I2387: 1798.638 | J2387: 2402.825 | K2387: 1489.598 | L2387: 125.83 | M2387: #N/A N/A | N2387: #N/A N/A | O2387: #N/A N/A | P2387: 99.3676 | Q2387: #N/A N/A | R2387: 97.32 | S2387: #N/A N/A
A2388: 36210 | B2388: 87.7697 | C2388: 161.252 | D2388: 87.3224 | E2388: 116.7422 | F2388: 36.0452 | G2388: 150.8849 | H2388: 10.6864 | I2388: 1815.101 | J2388: 2398.946 | K2388: 1492.313 | L2388: 126.33 | M2388: #N/A N/A | N2388: #N/A N/A | O2388: #N/A N/A | P2388: 98.2497 | Q2388: #N/A N/A | R2388: 98.27 | S2388: #N/A N/A
A2389: 36213 | B2389: 89.2644 | C2389: 163.868 | D2389: 86.8676 | E2389: 114.6333 | F2389: 35.9207 | G2389: 149.4784 | H2389: 10.53351 | I2389: 1819.217 | J2389: 2404.764 | K2389: 1496.579 | L2389: 129.48 | M2389: #N/A N/A | N2389: #N/A N/A | O2389: #N/A N/A | P2389: 97.6769 | Q2389: #N/A N/A | R2389: 98.52 | S2389: #N/A N/A
... A2400: 36228 | B2400: 97.5701 | C2400: 186.816 | D2400: 98.4636 | E2400: 116.0405 | F2400: 36.5301 | G2400: 147.6812 | H2400: 9.986314 | I2400: 1825.173 | J2400: 2376.173 | K2400: 1472.188 | L2400: 130.02 | M2400: #N/A N/A | N2400: #N/A N/A | O2400: #N/A N/A | P2400: 96.33 | Q2400: #N/A N/A | R2400: 99.64 | S2400: #N/A N/A
A2401: 36229 | B2401: 104.9487 | C2401: 194.785 | D2401: 99.646 | E2401: 116.4358 | F2401: 36.6293 | G2401: 149.0095 | H2401: 9.736857 | I2401: 1826.658 | J2401: 2373.591 | K2401: 1474.919 | L2401: 130.96 | M2401: #N/A N/A | N2401: #N/A N/A | O2401: 100 | P2401: 96.9119 | Q2401: #N/A N/A | R2401: 99.01 | S2401: #N/A N/A
A2402: 36230 | B2402: 101.3716 | C2402: 192.675 | D2402: 103.3805 | E2402: 116.3319 | F2402: 36.8003 | G2402: 149.4002 | H2402: 9.777092 | I2402: 1813.367 | J2402: 2373.591 | K2402: 1485.324 | L2402: 132.53 | M2402: #N/A N/A | N2402: #N/A N/A | O2402: 99.7904 | P2402: 95.8163 | Q2402: #N/A N/A | R2402: 98.46 | S2402: #N/A N/A
A2403: 36231 | B2403: 103.2549 | C2403: 195.752 | D2403: 103.8359 | E2403: 115.5223 | F2403: 36.5528 | G2403: 148.3063 | H2403: 9.817327 | I2403: 1819.182 | J2403: 2379.401 | K2403: 1481.813 | L2403: 131.2 | M2403: #N/A N/A | N2403: #N/A N/A | O2403: 100.5116 | P2403: 96.7987 | Q2403: #N/A N/A | R2403: 99.13 | S2403: #N/A N/A
A2404: 36234 | B2404: 104.4013 | C2404: 195.239 | D2404: 103.6082 | E2404: 114.0277 | F2404: 35.8228 | G2404: 147.2124 | H2404: 9.680528 | I2404: 1809.213 | J2404: 2382.629 | K2404: 1482.073 | L2404: 132.76 | M2404: #N/A N/A | N2404: #N/A N/A | O2404: 101.4553 | P2404: 96.7951 | Q2404: #N/A N/A | R2404: 98.89 | S2404: #N/A N/A
A2405: 36235 | B2405: 104.1556 | C2405: 194.256 | D2405: 102.2419 | E2405: 113.9239 | F2405: 35.3773 | G2405: 150.8849 | H2405: 9.913891 | I2405: 1808.936 | J2405: 2388.439 | K2405: 1489.746 | L2405: 132.73 | M2405: #N/A N/A | N2405: #N/A N/A | O2405: 101.6456 | P2405: 96.4802 | Q2405: #N/A N/A | R2405: 98.56 | S2405: #N/A N/A
A2406: 36236 | B2406: 108.4954 | C2406: 204.298 | D2406: 106.5684 | E2406: 115.1902 | F2406: 35.402 | G2406: 150.4161 | H2406: 9.865609 | I2406: 1822.366 | J2406: 2384.565 | K2406: 1490.787 | L2406: 132 | M2406: #N/A N/A | N2406: #N/A N/A | O2406: 101.1269 | P2406: 97.3477 | Q2406: #N/A N/A | R2406: 98.62 | S2406: #N/A N/A
A2407: 36237 | B2407: 109.478 | C2407: 203.486 | D2407: 108.3901 | E2407: 114.8581 | F2407: 35.3278 | G2407: 150.6505 | H2407: 9.841468 | I2407: 1823.889 | J2407: 2387.793 | K2407: 1492.738 | L2407: 133.97 | M2407: #N/A N/A | N2407: #N/A N/A | O2407: 101.6348 | P2407: 97.149 | Q2407: #N/A N/A | R2407: 98.57 | S2407: #N/A N/A
A2408: 36238 | B2408: 109.9693 | C2408: 206.264 | D2408: 108.8455 | E2408: 114.692 | F2408: 35.4763 | G2408: 152.9165 | H2408: 9.696622 | I2408: 1826.519 | J2408: 2379.401 | K2408: 1490.527 | L2408: 131.78 | M2408: #N/A N/A | N2408: #N/A N/A | O2408: 102.1762 | P2408: 96.6076 | Q2408: #N/A N/A | R2408: 99.05 | S2408: #N/A N/A
A2409: 36241 | B2409: 113.4903 | C2409: 213.742 | D2409: 110.4395 | E2409: 115.0034 | F2409: 35.501 | G2409: 156.042 | H2409: 9.463259 | I2409: 1826.519 | J2409: 2375.527 | K2409: 1488.316 | L2409: 131.95 | M2409: #N/A N/A | N2409: #N/A N/A | O2409: 101.4804 | P2409: 96.4172 | Q2409: #N/A N/A | R2409: 98.92 | S2409: #N/A N/A
A2410: 36242 | B2410: 112.2621 | C2410: 211.776 | D2410: 113.172 | E2410: 120.0893 | F2410: 35.4887 | G2410: 154.1667 | H2410: 9.551776 | I2410: 1825.827 | J2410: 2375.527 | K2410: 1483.633 | L2410: 128.03 | M2410: #N/A N/A | N2410: #N/A N/A | O2410: 101.4277 | P2410: 96.3425 | Q2410: #N/A N/A | R2410: 98.92 | S2410: #N/A N/A
A2411: 36243 | B2411: 112.1802 | C2411: 208.699 | D2411: 110.8949 | E2411: 119.3212 | F2411: 35.4144 | G2411: 152.4477 | H2411: 9.527635 | I2411: 1816.136 | J2411: 2380.692 | K2411: 1484.674 | L2411: 128.76 | M2411: #N/A N/A | N2411: #N/A N/A | O2411: 101.7434 | P2411: 96.5495 | Q2411: #N/A N/A | R2411: 99.06 | S2411: #N/A N/A
A2412: 36244 | B2412: 114.4729 | C2412: 210.793 | D2412: 111.3503 | E2412: 120.0685 | F2412: 35.2907 | G2412: 155.9639 | H2412: 9.575917 | I2412: 1826.658 | J2412: 2373.591 | K2412: 1485.975 | L2412: 131.22 | M2412: #N/A N/A | N2412: #N/A N/A | O2412: 101.2424 | P2412: 96.1119 | Q2412: #N/A N/A | R2412: 99.48 | S2412: #N/A N/A
... A2546: 36432 | B2546: 196.3886 | C2546: 313.276 | D2546: 160.935 | E2546: 141.1922 | F2546: 36.786 | G2546: 147.5161 | H2546: 7.666406 | I2546: 1873.103 | J2546: 2291.075 | K2546: 1393.123 | L2546: 126.11 | M2546: #N/A N/A | N2546: #N/A N/A | O2546: 109.3393 | P2546: 92.6325 | Q2546: #N/A N/A | R2546: 98.8 | S2546: #N/A N/A
A2547: 36433 | B2547: 194.9661 | C2547: 313.276 | D2547: 158.6654 | E2547: 141.3316 | F2547: 36.4814 | G2547: 147.3661 | H2547: 7.607263 | I2547: 1870.25 | J2547: 2301.194 | K2547: 1399.608 | L2547: 127.91 | M2547: #N/A N/A | N2547: 100 | O2547: 109.4192 | P2547: 92.9766 | Q2547: #N/A N/A | R2547: 98.54 | S2547: #N/A N/A
A2548: 36434 | B2548: 195.3008 | C2548: 311.203 | D2548: 160.1097 | E2548: 140.2362 | F2548: 37.1879 | G2548: 144.2913 | H2548: 7.629442 | I2548: 1874.53 | J2548: 2286.831 | K2548: 1387.036 | L2548: 127.49 | M2548: #N/A N/A | N2548: 99.7129 | O2548: 110.8534 | P2548: 93.3952 | Q2548: #N/A N/A | R2548: 98.06 | S2548: #N/A N/A
A2549: 36437 | B2549: 190.7823 | C2549: 302.232 | D2549: 156.8085 | E2549: 139.4794 | F2549: 38.7349 | G2549: 144.9663 | H2549: 7.474192 | I2549: 1883.091 | J2549: 2294.339 | K2549: 1389.153 | L2549: 129.93 | M2549: #N/A N/A | N2549: 102.358 | O2549: 109.4833 | P2549: 93.3967 | Q2549: #N/A N/A | R2549: 98.04 | S2549: #N/A N/A
A2550: 36438 | B2550: 189.9455 | C2550: 300.61 | D2550: 151.8567 | E2550: 140.2562 | F2550: 39.7094 | G2550: 145.1163 | H2550: 7.208049 | I2550: 1880.095 | J2550: 2280.629 | K2550: 1392.859 | L2550: 129.63 | M2550: #N/A N/A | N2550: 102.8706 | O2550: 108.7991 | P2550: 93.2327 | Q2550: #N/A N/A | R2550: 97.98 | S2550: #N/A N/A
A2551: 36439 | B2551: 189.1087 | C2551: 294.299 | D2551: 154.1263 | E2551: 139.6985 | F2551: 39.7094 | G2551: 146.7662 | H2551: 7.008441 | I2551: 1871.677 | J2551: 2279.324 | K2551: 1390.477 | L2551: 131.5 | M2551: #N/A N/A | N2551: 104.798 | O2551: 108.2951 | P2551: 93.4425 | Q2551: #N/A N/A | R2551: 98.48 | S2551: #N/A N/A
A2552: 36440 | B2552: 183.1677 | C2552: 282.895 | D2552: 149.5871 | E2552: 139.2603 | F2552: 39.5023 | G2552: 146.7662 | H2552: 6.831012 | I2552: 1857.408 | J2552: 2278.671 | K2552: 1388.227 | L2552: 130.94 | M2552: #N/A N/A | N2552: 104.5315 | O2552: 108.1364 | P2552: 93.6421 | Q2552: #N/A N/A | R2552: 98.38 | S2552: #N/A N/A
A2553: 36441 | B2553: 172.4702 | C2553: 266.857 | D2553: 140.0162 | E2553: 133.15 | F2553: 39.1856 | G2553: 147.4383 | H2553: 6.949298 | I2553: 1857.408 | J2553: 2280.303 | K2553: 1384.522 | L2553: 132.69 | M2553: #N/A N/A | N2553: 105.7207 | O2553: 108.3469 | P2553: 92.7271 | Q2553: #N/A N/A | R2553: 99.02 | S2553: #N/A N/A
A2554: 36444 | B2554: 176.3946 | C2554: 272.084 | D2554: 140.14 | E2554: 131.0644 | F2554: 39.0151 | G2554: 147.9588 | H2554: 6.897548 | I2554: 1857.408 | J2554: 2280.303 | K2554: 1385.316 | L2554: 132.71 | M2554: #N/A N/A | N2554: 107.115 | O2554: 109.0208 | P2554: 92.8248 | Q2554: #N/A N/A | R2554: 98.71 | S2554: #N/A N/A
A2555: 36445 | B2555: 184.4771 | C2555: 284.104 | D2555: 147.0768 | E2555: 136.5271 | F2555: 38.7593 | G2555: 149.8544 | H2555: 7.015834 | I2555: 1845.137 | J2555: 2275.733 | K2555: 1378.302 | L2555: 130.64 | M2555: #N/A N/A | N2555: 104.9621 | O2555: 109.466 | P2555: 93.5971 | Q2555: #N/A N/A | R2555: 97.95 | S2555: #N/A N/A
A2556: 36446 | B2556: 187.9716 | C2556: 287.685 | D2556: 151.0005 | E2556: 137.0659 | F2556: 39.1978 | G2556: 149.8691 | H2556: 7.045405 | I2556: 1849.417 | J2556: 2267.572 | K2556: 1375.788 | L2556: 127.05 | M2556: #N/A N/A | N2556: 101.4968 | O2556: 108.2739 | P2556: 93.8703 | Q2556: #N/A N/A | R2556: 97.89 | S2556: #N/A N/A
A2557: 36447 | B2557: 183.5467 | C2557: 282.587 | D2557: 152.2399 | E2557: 136.8285 | F2557: 38.272 | G2557: 148.8411 | H2557: 7.015834 | I2557: 1847.991 | J2557: 2261.697 | K2557: 1367.187 | L2557: 127.1 | M2557: #N/A N/A | N2557: 102.2965 | O2557: 108.6961 | P2557: 94.0216 | Q2557: #N/A N/A | R2557: 97.92 | S2557: #N/A N/A
A2558: 36448 | B2558: 187.9716 | C2558: 287.913 | D2558: 149.7611 | E2558: 136.0965 | F2558: 38.54 | G2558: 147.3725 | H2558: 6.993655 | I2558: 1842.283 | J2558: 2273.775 | K2558: 1371.024 | L2558: 123.79 | M2558: #N/A N/A | N2558: 99.0773 | O2558: 110.0791 | P2558: 94.9038 | Q2558: #N/A N/A | R2558: 97.04 | S2558: #N/A N/A
... A3762: 38134 | B3762: 508.4191 | C3762: 1080.832 | D3762: 375.2343 | E3762: 188.1766 | F3762: 42.2354 | G3762: 244.0612 | H3762: 8.815393 | I3762: 2151.91 | J3762: 2985.717 | K3762: 1618.142 | L3762: 98.89 | M3762: #N/A N/A | N3762: 52.3103 | O3762: 90.5798 | P3762: 107.7855 | Q3762: #N/A N/A | R3762: 88.67 | S3762: #N/A N/A
A3763: 38135 | B3763: 513.2356 | C3763: 1086.656 | D3763: 375.8425 | E3763: 188.2433 | F3763: 42.1075 | G3763: 241.6859 | H3763: 8.987161 | I3763: 2143.064 | J3763: 2970.725 | K3763: 1612.875 | L3763: 98.67 | M3763: #N/A N/A | N3763: 52.3103 | O3763: 90.8018 | P3763: 107.3287 | Q3763: 1000 | R3763: 88.9 | S3763: #N/A N/A
A3764: 38138 | B3764: 513.2356 | C3764: 1086.656 | D3764: 375.8425 | E3764: 188.2433 | F3764: 42.1075 | G3764: 241.6859 | H3764: 8.987161 | I3764: 2141.512 | J3764: 2970.725 | K3764: 1606.897 | L3764: 98.67 | M3764: #N/A N/A | N3764: 52.3103 | O3764: 90.8018 | P3764: 107.3287 | Q3764: 993.3815 | R3764: 88.9 | S3764: #N/A N/A
A3765: 38139 | B3765: 548.2257 | C3765: 1141.938 | D3765: 401.9934 | E3765: 190.7763 | F3765: 42.1714 | G3765: 256.5315 | H3765: 8.729509 | I3765: 2136.08 | J3765: 2963.872 | K3765: 1607.893 | L3765: 98.76 | M3765: #N/A N/A | N3765: 52.3816 | O3765: 91.2931 | P3765: 107.4244 | Q3765: 994.2978 | R3765: 88.88 | S3765: #N/A N/A
A3766: 38140 | B3766: 518.6187 | C3766: 1082.267 | D3766: 393.7832 | E3766: 185.5103 | F3766: 41.8516 | G3766: 252.2263 | H3766: 8.232608 | I3766: 2138.253 | J3766: 2957.018 | K3766: 1606.328 | L3766: 99.13 | M3766: #N/A N/A | N3766: 52.2568 | O3766: 91.054 | P3766: 107.8841 | Q3766: 990.5474 | R3766: 88.84 | S3766: #N/A N/A
A3767: 38141 | B3767: 513.0939 | C3767: 1042.683 | D3767: 376.7547 | E3767: 185.4436 | F3767: 41.4677 | G3767: 239.3107 | H3767: 8.257146 | I3767: 2138.098 | J3767: 2961.73 | K3767: 1607.148 | L3767: 98.21 | M3767: #N/A N/A | N3767: 51.4545 | O3767: 90.2762 | P3767: 107.6299 | Q3767: 967.952 | R3767: 88.95 | S3767: #N/A N/A
A3768: 38142 | B3768: 504.1693 | C3768: 994.153 | D3768: 373.7139 | E3768: 182.5773 | F3768: 41.7663 | G3768: 248.9603 | H3768: 8.183531 | I3768: 2134.994 | J3768: 2948.023 | K3768: 1604.722 | L3768: 98.94 | M3768: #N/A N/A | N3768: 51.9359 | O3768: 90.0791 | P3768: 107.6067 | Q3768: 972.8955 | R3768: 88.54 | S3768: #N/A N/A
...

Sheet Prices_Monthly
B1: Commodity | C1: Commodity | D1: Bonds | E1: Bonds | F1: Equity | G1: Equity | H1: Currency/Alternative | I1: Currency/Alternative | K1: Benchmark | L1: Benchmark
A2: date | B2: GSCI Gasoil | C2: GSCI Gold | D2: Japan Gov't Bond | E2: US 10Y Gov't Bond FUTURES INDEX | F2: S&P 500 Futures Excess Rtn Index | G2: Nasdaq 100 Futures Excess Rtn Index | H2: SGI FX Forwards JPY/USD in USD | I2: SGI FX Forwards EUR/USD in USD | K2: global bond bench | L2: equity bench
B3: SPGCGOP INDEX | C3: SPGCGCP INDEX | D3: SGIXBJB INDEX | E3: SGIXBTY INDEX | F3: SPXFP INDEX | G3: NDXNQER INDEX | H3: SGIXFJPU INDEX | I3: SGIXFEUU INDEX | K3: sbwgl INDEX | L3: nddlwi INDEX
A4: 32873
A5: 32904 | B5: #N/A N/A | C5: 75.9869 | D5: 1112 | E5: 1661.224 | F5: #N/A N/A | G5: #N/A N/A | H5: #N/A N/A | I5: #N/A N/A | K5: 157.1698 | L5: 756.345
A6: 32932 | B6: #N/A N/A | C6: 74.3682 | D6: 1085.449 | E6: 1650.249 | F6: #N/A N/A | G6: #N/A N/A | H6: #N/A N/A | I6: #N/A N/A | K6: 156.0661 | L6: 732.234
A7: 32963 | B7: #N/A N/A | C7: 67.2911 | D7: 1069.709 | E7: 1635.254 | F7: #N/A N/A | G7: #N/A N/A | H7: #N/A N/A | I7: #N/A N/A | K7: 156.152 | L7: 703.404
A8: 32993 | B8: #N/A N/A | C8: 66.6451 | D8: 1069.135 | E8: 1597.767 | F8: #N/A N/A | G8: #N/A N/A | H8: #N/A N/A | I8: #N/A N/A | K8: 155.4654 | L8: 692.637
A9: 33024 | B9: #N/A N/A | C9: 65.3079 | D9: 1098.195 | E9: 1643.824 | F9: #N/A N/A | G9: #N/A N/A | H9: #N/A N/A | I9: #N/A N/A | K9: 159.5394 | L9: 753.318
A10: 33054 | B10: #N/A N/A | C10: 63.7664 | D10: 1073.486 | E10: 1663.106 | F10: #N/A N/A | G10: #N/A N/A | H10: #N/A N/A | I10: #N/A N/A | K10: 161.3032 | L10: 741.05
A11: 33085 | B11: #N/A N/A | C11: 65.5999 | D11: 1059.193 | E11: 1672.212 | F11: #N/A N/A | G11: #N/A N/A | H11: #N/A N/A | I11: #N/A N/A | K11: 162.7747 | L11: 728.366
A12: 33116 | B12: #N/A N/A | C12: 67.3299 | D12: 1022.03 | E12: 1620.263 | F12: #N/A N/A | G12: #N/A N/A | H12: #N/A N/A | I12: #N/A N/A | K12: 160.6187 | L12: 653.215
A13: 33146 | B13: #N/A N/A | C13: 70.5995 | D13: 993.475 | E13: 1625.093 | F13: #N/A N/A | G13: #N/A N/A | H13: #N/A N/A | I13: #N/A N/A | K13: 161.1314 | L13: 576.87
A14: 33177 | B14: #N/A N/A | C14: 65.9632 | D14: 1042.404 | E14: 1644.415 | F14: #N/A N/A | G14: #N/A N/A | H14: #N/A N/A | I14: #N/A N/A | K14: 164.8243 | L14: 613.811
A15: 33207 | B15: #N/A N/A | C15: 66.0784 | D15: 1065.899 | E15: 1682.926 | F15: #N/A N/A | G15: #N/A N/A | H15: #N/A N/A | I15: #N/A N/A | K15: 168.0377 | L15: 608.218
A16: 33238 | B16: #N/A N/A | C16: 67.8773 | D16: 1084.441 | E16: 1697.977 | F16: #N/A N/A | G16: #N/A N/A | H16: #N/A N/A | I16: #N/A N/A | K16: 170.2904 | L16: 625.255
... A96: 35673 | B96: #N/A N/A | C96: 42.9275 | D96: 1718.518 | E96: 2254.101 | F96: #N/A N/A | G96: #N/A N/A | H96: #N/A N/A | I96: #N/A N/A | K96: 315.5745 | L96: 1408.685
A97: 35703 | B97: #N/A N/A | C97: 44.1731 | D97: 1742.388 | E97: 2283.912 | F97: 101.12 | G97: #N/A N/A | H97: #N/A N/A | I97: #N/A N/A | K97: 320.2655 | L97: 1481.265
A98: 35734 | B98: #N/A N/A | C98: 40.9214 | D98: 1769.206 | E98: 2317.611 | F98: 97.89 | G98: #N/A N/A | H98: #N/A N/A | I98: #N/A N/A | K98: 323.1909 | L98: 1390.865
A99: 35764 | B99: #N/A N/A | C99: 38.9854 | D99: 1762.434 | E99: 2314.851 | F99: 101.16 | G99: #N/A N/A | H99: #N/A N/A | I99: #N/A N/A | K99: 324.837 | L99: 1434.38
A100: 35795 | B100: #N/A N/A | C100: 37.8495 | D100: 1764.153 | E100: 2331.09 | F100: 102.56 | G100: #N/A N/A | H100: #N/A N/A | I100: #N/A N/A | K100: 328.1397 | L100: 1467.391
A101: 35826 | B101: #N/A N/A | C101: 39.5632 | D101: 1750.506 | E101: 2363.568 | F101: 103.47 | G101: #N/A N/A | H101: #N/A N/A | I101: #N/A N/A | K101: 332.144 | L101: 1509.903
A102: 35854 | B102: #N/A N/A | C102: 38.9787 | D102: 1761.697 | E102: 2341.645 | F102: 110.03 | G102: #N/A N/A | H102: #N/A N/A | I102: #N/A N/A | K102: 333.3581 | L102: 1605.391
A103: 35885 | B103: #N/A N/A | C103: 39.161 | D103: 1773.496 | E103: 2336.448 | F103: 116.33 | G103: #N/A N/A | H103: #N/A N/A | I103: #N/A N/A | K103: 335.2754 | L103: 1688.635
A104: 35915 | B104: #N/A N/A | C104: 39.7549 | D104: 1789.445 | E104: 2335.149 | F104: 117.24 | G104: #N/A N/A | H104: #N/A N/A | I104: #N/A N/A | K104: 336.5238 | L104: 1692.669
A105: 35946 | B105: #N/A N/A | C105: 37.8298 | D105: 1820.254 | E105: 2349.112 | F105: 114.28 | G105: #N/A N/A | H105: #N/A N/A | I105: #N/A N/A | K105: 340.3682 | L105: 1683.272
A106: 35976 | B106: #N/A N/A | C106: 38.2144 | D106: 1807.19 | E106: 2364.04 | F106: 118.44 | G106: #N/A N/A | H106: #N/A N/A | I106: #N/A N/A | K106: 342.1749 | L106: 1726.333
A107: 36007 | B107: #N/A N/A | C107: 36.7039 | D107: 1818.489 | E107: 2358.198 | F107: 116.37 | G107: #N/A N/A | H107: #N/A N/A | I107: #N/A N/A | K107: 343.9461 | L107: 1728.759
A108: 36038 | B108: #N/A N/A | C108: 35.2382 | D108: 1845.171 | E108: 2429.578 | F108: 98.88 | G108: #N/A N/A | H108: #N/A N/A | I108: #N/A N/A | K108: 350.9502 | L108: 1489.869
... A112: 36160 | B112: #N/A N/A | C112: 36.2687 | D112: 1757.344 | E112: 2464.892 | F112: 126.54 | G112: #N/A N/A | H112: #N/A N/A | I112: #N/A N/A | K112: 359.0656 | L112: 1770.59
A113: 36191 | B113: 93.2715 | C113: 35.8834 | D113: 1771.338 | E113: 2465.538 | F113: 130.19 | G113: #N/A N/A | H113: #N/A N/A | I113: #N/A N/A | K113: 362.4171 | L113: 1829.126
A114: 36219 | B114: 91.1883 | C114: 35.8958 | D114: 1799.873 | E114: 2371.008 | F114: 125.52 | G114: #N/A N/A | H114: #N/A N/A | I114: 97.1707 | K114: 357.6739 | L114: 1802.741
A115: 36250 | B115: 119.0925 | C115: 34.8823 | D115: 1836.903 | E115: 2369.717 | F115: 130.14 | G115: #N/A N/A | H115: 100.936 | I115: 95.4121 | K115: 360.5588 | L115: 1882.091
A116: 36280 | B116: 121.0898 | C116: 35.6124 | D116: 1874.7 | E116: 2369.717 | F116: 134.62 | G116: #N/A N/A | H116: 99.6829 | I116: 93.346 | K116: 363.4716 | L116: 1964.618
A117: 36311 | B117: 107.0848 | C117: 33.4466 | D117: 1883.423 | E117: 2316.872 | F117: 130.49 | G117: #N/A N/A | H117: 98.1621 | I117: 92.1029 | K117: 361.2346 | L117: 1904.096
A118: 36341 | B118: 121.8456 | C118: 32.4136 | D118: 1817.702 | E118: 2309.736 | F118: 137.68 | G118: #N/A N/A | H118: 97.5823 | I118: 90.6569 | K118: 356.2341 | L118: 1999.127
A119: 36372 | B119: 136.8148 | C119: 31.5239 | D119: 1841.837 | E119: 2291.571 | F119: 132.7 | G119: #N/A N/A | H119: 102.4327 | I119: 93.8615 | K119: 355.1336 | L119: 1959.934
A120: 36403 | B120: 150.2179 | C120: 31.3412 | D120: 1836.505 | E120: 2285.199 | F120: 131.5 | G120: #N/A N/A | H120: 106.7557 | I120: 92.4486 | K120: 355.0075 | L120: 1952.818
A121: 36433 | B121: 158.6654 | C121: 36.4814 | D121: 1870.25 | E121: 2301.194 | F121: 127.91 | G121: 100 | H121: 109.4192 | I121: 92.9766 | K121: 356.1423 | L121: 1916.626
A122: 36464 | B122: 148.5216 | C122: 36.5789 | D122: 1826.873 | E122: 2292.707 | F122: 135.59 | G122: 108.8989 | H122: 111.175 | I122: 91.5652 | K122: 356.0963 | L122: 2017.117
A123: 36494 | B123: 167.6216 | C123: 35.4989 | D123: 1844.994 | E123: 2281.232 | F123: 137.1 | G123: 121.8987 | H123: 113.0083 | I123: 87.5514 | K123: 356.7508 | L123: 2092.685
A124: 36525 | B124: 179.257 | C124: 35.087 | D124: 1882.874 | E124: 2243.244 | F124: 144.31 | G124: 151.7084 | H124: 112.2481 | I124: 86.9212 | K124: 356.157 | L124: 2260.666
A125: 36556 | B125: 185.0291 | C125: 34.418 | D125: 1893.098 | E125: 2218.04 | F125: 136.22 | G125: 145.99 | H125: 106.8827 | I125: 84.6649 | K125: 355.8016 | L125: 2156.528
A126: 36585 | B126: 195.8919 | C126: 35.38 | D126: 1873.075 | E126: 2241.494 | F126: 133.4 | G126: 173.814 | H126: 103.6564 | I126: 83.1374 | K126: 358.2953 | L126: 2184.085
A127: 36616 | B127: 179.5563 | C127: 33.5327 | D127: 1883.242 | E127: 2304.652 | F127: 145.44 | G127: 177.7753 | H127: 110.4372 | I127: 82.4421 | K127: 363.0793 | L127: 2313.735
A128: 36646 | B128: 187.2097 | C128: 32.7343 | D128: 1896.121 | E128: 2278.214 | F128: 140.14 | G128: 151.9515 | H128: 104.3548 | I128: 78.3758 | K128: 363.2205 | L128: 2260.646
A129: 36677 | B129: 208.8242 | C129: 32.4222 | D129: 1916.441 | E129: 2278.238 | F129: 136.51 | G129: 132.6086 | H129: 104.1765 | I129: 79.5853 | K129: 364.6518 | L129: 2205.267
A130: 36707 | B130: 235.7287 | C130: 34.3926 | D130: 1913.785 | E130: 2318.324 | F130: 138.77 | G130: 149.8325 | H130: 105.3775 | I130: 82.0951 | K130: 366.7702 | L130: 2251.479
A131: 36738 | B131: 220.5363 | C131: 32.7138 | D131: 1928.913 | E131: 2327.885 | F131: 136.03 | G131: 141.9817 | H131: 101.2346 | I131: 79.2213 | K131: 368.8883 | L131: 2217.974
A132: 36769 | B132: 287.7994 | C132: 32.5868 | D132: 1902.835 | E132: 2357.405 | F132: 143.81 | G132: 160.7059 | H132: 103.3869 | I132: 75.87 | K132: 369.5608 | L132: 2308.939
... A443: 46234 | B443: 1798.786 | C443: 240.3091 | D443: 2569.178 | E443: 4178.752 | F443: 598.42 | G443: 742.0093 | H443: 39.6645 | I443: 80.5788 | K443: 746.9207 | L443: 12177.677

Sheet rets_1M
B2: Commodity | C2: Commodity | D2: Bonds | E2: Bonds | F2: Equity | G2: Equity | H2: Currency/Alternative | I2: Currency/Alternative | K2: Benchmark | L2: Benchmark | M2: Benchmark
B3: GSCI Gasoil | C3: GSCI Gold | D3: Japan Gov't Bond | E3: US 10Y Gov't Bond FUTURES INDEX | F3: S&P 500 Futures Excess Rtn Index | G3: Nasdaq 100 Futures Excess Rtn Index | H3: SGI FX Forwards JPY/USD in USD | I3: SGI FX Forwards EUR/USD in USD | K3: global bond bench | L3: equity bench | M3: 60/40 Balanced
A4: date | B4: GSCI Gasoil | C4: GSCI Gold | D4: Japan Gov't Bond | E4: US 10Y Gov't Bond FUTURES INDEX | F4: S&P 500 Futures Excess Rtn Index | G4: Nasdaq 100 Futures Excess Rtn Index | H4: SGI FX Forwards JPY/USD in USD | I4: SGI FX Forwards EUR/USD in USD | K4: global bond bench | L4: equity bench | M4: 60/40 Balanced
A5: 32873
A6: 32904 | B6: =VLOOKUP($A6,Prices_Monthly!$A:$I,COLUMN(B$4),FALSE)/VLOOKUP(EOMONTH($A6,-1),Prices_Monthly!$A:$I,COLUMN(B$4),FALSE)-1 -> #VALUE! | C6: =VLOOKUP($A6,Prices_Monthly!$A:$I,COLUMN(C$4),FALSE)/VLOOKUP(EOMONTH($A6,-1),Prices_Monthly!$A:$I,COLUMN(C$4),FALSE)-1 -> #DIV/0! | D6: =VLOOKUP($A6,Prices_Monthly!$A:$I,COLUMN(D$4),FALSE)/VLOOKUP(EOMONTH($A6,-1),Prices_Monthly!$A:$I,COLUMN(D$4),FALSE)-1 -> #DIV/0! | E6: =VLOOKUP($A6,Prices_Monthly!$A:$I,COLUMN(E$4),FALSE)/VLOOKUP(EOMONTH($A6,-1),Prices_Monthly!$A:$I,COLUMN(E$4),FALSE)-1 -> #DIV/0! | F6: =VLOOKUP($A6,Prices_Monthly!$A:$I,COLUMN(F$4),FALSE)/VLOOKUP(EOMONTH($A6,-1),Prices_Monthly!$A:$I,COLUMN(F$4),FALSE)-1 -> #VALUE! | G6: =VLOOKUP($A6,Prices_Monthly!$A:$I,COLUMN(G$4),FALSE)/VLOOKUP(EOMONTH($A6,-1),Prices_Monthly!$A:$I,COLUMN(G$4),FALSE)-1 -> #VALUE! | H6: =VLOOKUP($A6,Prices_Monthly!$A:$I,COLUMN(H$4),FALSE)/VLOOKUP(EOMONTH($A6,-1),Prices_Monthly!$A:$I,COLUMN(H$4),FALSE)-1 -> #VALUE! | I6: =VLOOKUP($A6,Prices_Monthly!$A:$I,COLUMN(I$4),FALSE)/VLOOKUP(EOMONTH($A6,-1),Prices_Monthly!$A:$I,COLUMN(I$4),FALSE)-1 -> #VALUE! | K6: =VLOOKUP($A6,Prices_Monthly!$A:$L,COLUMN(K$4),FALSE)/VLOOKUP(EOMONTH($A6,-1),Prices_Monthly!$A:$L,COLUMN(K$4),FALSE)-1 -> #DIV/0! | L6: =VLOOKUP($A6,Prices_Monthly!$A:$L,COLUMN(L$4),FALSE)/VLOOKUP(EOMONTH($A6,-1),Prices_Monthly!$A:$L,COLUMN(L$4),FALSE)-1 -> #DIV/0! | M6: =(0.6*L6)+(0.4*K6) -> #DIV/0!
A7: 32932 | B7: =VLOOKUP($A7,Prices_Monthly!$A:$I,COLUMN(B$4),FALSE)/VLOOKUP(EOMONTH($A7,-1),Prices_Monthly!$A:$I,COLUMN(B$4),FALSE)-1 -> #VALUE! | C7: =VLOOKUP($A7,Prices_Monthly!$A:$I,COLUMN(C$4),FALSE)/VLOOKUP(EOMONTH($A7,-1),Prices_Monthly!$A:$I,COLUMN(C$4),FALSE)-1 -> -0.021302356 | D7: =VLOOKUP($A7,Prices_Monthly!$A:$I,COLUMN(D$4),FALSE)/VLOOKUP(EOMONTH($A7,-1),Prices_Monthly!$A:$I,COLUMN(D$4),FALSE)-1 -> -0.023876799 | E7: =VLOOKUP($A7,Prices_Monthly!$A:$I,COLUMN(E$4),FALSE)/VLOOKUP(EOMONTH($A7,-1),Prices_Monthly!$A:$I,COLUMN(E$4),FALSE)-1 -> -0.0066065744 | F7: =VLOOKUP($A7,Prices_Monthly!$A:$I,COLUMN(F$4),FALSE)/VLOOKUP(EOMONTH($A7,-1),Prices_Monthly!$A:$I,COLUMN(F$4),FALSE)-1 -> #VALUE! | G7: =VLOOKUP($A7,Prices_Monthly!$A:$I,COLUMN(G$4),FALSE)/VLOOKUP(EOMONTH($A7,-1),Prices_Monthly!$A:$I,COLUMN(G$4),FALSE)-1 -> #VALUE! | H7: =VLOOKUP($A7,Prices_Monthly!$A:$I,COLUMN(H$4),FALSE)/VLOOKUP(EOMONTH($A7,-1),Prices_Monthly!$A:$I,COLUMN(H$4),FALSE)-1 -> #VALUE! | I7: =VLOOKUP($A7,Prices_Monthly!$A:$I,COLUMN(I$4),FALSE)/VLOOKUP(EOMONTH($A7,-1),Prices_Monthly!$A:$I,COLUMN(I$4),FALSE)-1 -> #VALUE! | K7: =VLOOKUP($A7,Prices_Monthly!$A:$L,COLUMN(K$4),FALSE)/VLOOKUP(EOMONTH($A7,-1),Prices_Monthly!$A:$L,COLUMN(K$4),FALSE)-1 -> -0.0070223414 | L7: =VLOOKUP($A7,Prices_Monthly!$A:$L,COLUMN(L$4),FALSE)/VLOOKUP(EOMONTH($A7,-1),Prices_Monthly!$A:$L,COLUMN(L$4),FALSE)-1 -> -0.03187831 | M7: =(0.6*L7)+(0.4*K7) -> -0.021935922
A8: 32963 | B8: =VLOOKUP($A8,Prices_Monthly!$A:$I,COLUMN(B$4),FALSE)/VLOOKUP(EOMONTH($A8,-1),Prices_Monthly!$A:$I,COLUMN(B$4),FALSE)-1 -> #VALUE! | C8: =VLOOKUP($A8,Prices_Monthly!$A:$I,COLUMN(C$4),FALSE)/VLOOKUP(EOMONTH($A8,-1),Prices_Monthly!$A:$I,COLUMN(C$4),FALSE)-1 -> -0.095162986 | D8: =VLOOKUP($A8,Prices_Monthly!$A:$I,COLUMN(D$4),FALSE)/VLOOKUP(EOMONTH($A8,-1),Prices_Monthly!$A:$I,COLUMN(D$4),FALSE)-1 -> -0.014500912 | E8: =VLOOKUP($A8,Prices_Monthly!$A:$I,COLUMN(E$4),FALSE)/VLOOKUP(EOMONTH($A8,-1),Prices_Monthly!$A:$I,COLUMN(E$4),FALSE)-1 -> -0.0090865076 | F8: =VLOOKUP($A8,Prices_Monthly!$A:$I,COLUMN(F$4),FALSE)/VLOOKUP(EOMONTH($A8,-1),Prices_Monthly!$A:$I,COLUMN(F$4),FALSE)-1 -> #VALUE! | G8: =VLOOKUP($A8,Prices_Monthly!$A:$I,COLUMN(G$4),FALSE)/VLOOKUP(EOMONTH($A8,-1),Prices_Monthly!$A:$I,COLUMN(G$4),FALSE)-1 -> #VALUE! | H8: =VLOOKUP($A8,Prices_Monthly!$A:$I,COLUMN(H$4),FALSE)/VLOOKUP(EOMONTH($A8,-1),Prices_Monthly!$A:$I,COLUMN(H$4),FALSE)-1 -> #VALUE! | I8: =VLOOKUP($A8,Prices_Monthly!$A:$I,COLUMN(I$4),FALSE)/VLOOKUP(EOMONTH($A8,-1),Prices_Monthly!$A:$I,COLUMN(I$4),FALSE)-1 -> #VALUE! | K8: =VLOOKUP($A8,Prices_Monthly!$A:$L,COLUMN(K$4),FALSE)/VLOOKUP(EOMONTH($A8,-1),Prices_Monthly!$A:$L,COLUMN(K$4),FALSE)-1 -> 0.00055040781 | L8: =VLOOKUP($A8,Prices_Monthly!$A:$L,COLUMN(L$4),FALSE)/VLOOKUP(EOMONTH($A8,-1),Prices_Monthly!$A:$L,COLUMN(L$4),FALSE)-1 -> -0.03937266 | M8: =(0.6*L8)+(0.4*K8) -> -0.023403433
A9: 32993 | B9: =VLOOKUP($A9,Prices_Monthly!$A:$I,COLUMN(B$4),FALSE)/VLOOKUP(EOMONTH($A9,-1),Prices_Monthly!$A:$I,COLUMN(B$4),FALSE)-1 -> #VALUE! | C9: =VLOOKUP($A9,Prices_Monthly!$A:$I,COLUMN(C$4),FALSE)/VLOOKUP(EOMONTH($A9,-1),Prices_Monthly!$A:$I,COLUMN(C$4),FALSE)-1 -> -0.0096000808 | D9: =VLOOKUP($A9,Prices_Monthly!$A:$I,COLUMN(D$4),FALSE)/VLOOKUP(EOMONTH($A9,-1),Prices_Monthly!$A:$I,COLUMN(D$4),FALSE)-1 -> -0.00053659453 | E9: =VLOOKUP($A9,Prices_Monthly!$A:$I,COLUMN(E$4),FALSE)/VLOOKUP(EOMONTH($A9,-1),Prices_Monthly!$A:$I,COLUMN(E$4),FALSE)-1 -> -0.022924267 | F9: =VLOOKUP($A9,Prices_Monthly!$A:$I,COLUMN(F$4),FALSE)/VLOOKUP(EOMONTH($A9,-1),Prices_Monthly!$A:$I,COLUMN(F$4),FALSE)-1 -> #VALUE! | G9: =VLOOKUP($A9,Prices_Monthly!$A:$I,COLUMN(G$4),FALSE)/VLOOKUP(EOMONTH($A9,-1),Prices_Monthly!$A:$I,COLUMN(G$4),FALSE)-1 -> #VALUE! | H9: =VLOOKUP($A9,Prices_Monthly!$A:$I,COLUMN(H$4),FALSE)/VLOOKUP(EOMONTH($A9,-1),Prices_Monthly!$A:$I,COLUMN(H$4),FALSE)-1 -> #VALUE! | I9: =VLOOKUP($A9,Prices_Monthly!$A:$I,COLUMN(I$4),FALSE)/VLOOKUP(EOMONTH($A9,-1),Prices_Monthly!$A:$I,COLUMN(I$4),FALSE)-1 -> #VALUE! | K9: =VLOOKUP($A9,Prices_Monthly!$A:$L,COLUMN(K$4),FALSE)/VLOOKUP(EOMONTH($A9,-1),Prices_Monthly!$A:$L,COLUMN(K$4),FALSE)-1 -> -0.0043969978 | L9: =VLOOKUP($A9,Prices_Monthly!$A:$L,COLUMN(L$4),FALSE)/VLOOKUP(EOMONTH($A9,-1),Prices_Monthly!$A:$L,COLUMN(L$4),FALSE)-1 -> -0.015306993 | M9: =(0.6*L9)+(0.4*K9) -> -0.010942995
A10: 33024 | B10: =VLOOKUP($A10,Prices_Monthly!$A:$I,COLUMN(B$4),FALSE)/VLOOKUP(EOMONTH($A10,-1),Prices_Monthly!$A:$I,COLUMN(B$4),FALSE)-1 -> #VALUE! | C10: =VLOOKUP($A10,Prices_Monthly!$A:$I,COLUMN(C$4),FALSE)/VLOOKUP(EOMONTH($A10,-1),Prices_Monthly!$A:$I,COLUMN(C$4),FALSE)-1 -> -0.020064491 | D10: =VLOOKUP($A10,Prices_Monthly!$A:$I,COLUMN(D$4),FALSE)/VLOOKUP(EOMONTH($A10,-1),Prices_Monthly!$A:$I,COLUMN(D$4),FALSE)-1 -> 0.027180852 | E10: =VLOOKUP($A10,Prices_Monthly!$A:$I,COLUMN(E$4),FALSE)/VLOOKUP(EOMONTH($A10,-1),Prices_Monthly!$A:$I,COLUMN(E$4),FALSE)-1 -> 0.028825855 | F10: =VLOOKUP($A10,Prices_Monthly!$A:$I,COLUMN(F$4),FALSE)/VLOOKUP(EOMONTH($A10,-1),Prices_Monthly!$A:$I,COLUMN(F$4),FALSE)-1 -> #VALUE! | G10: =VLOOKUP($A10,Prices_Monthly!$A:$I,COLUMN(G$4),FALSE)/VLOOKUP(EOMONTH($A10,-1),Prices_Monthly!$A:$I,COLUMN(G$4),FALSE)-1 -> #VALUE! | H10: =VLOOKUP($A10,Prices_Monthly!$A:$I,COLUMN(H$4),FALSE)/VLOOKUP(EOMONTH($A10,-1),Prices_Monthly!$A:$I,COLUMN(H$4),FALSE)-1 -> #VALUE! | I10: =VLOOKUP($A10,Prices_Monthly!$A:$I,COLUMN(I$4),FALSE)/VLOOKUP(EOMONTH($A10,-1),Prices_Monthly!$A:$I,COLUMN(I$4),FALSE)-1 -> #VALUE! | K10: =VLOOKUP($A10,Prices_Monthly!$A:$L,COLUMN(K$4),FALSE)/VLOOKUP(EOMONTH($A10,-1),Prices_Monthly!$A:$L,COLUMN(K$4),FALSE)-1 -> 0.026205188 | L10: =VLOOKUP($A10,Prices_Monthly!$A:$L,COLUMN(L$4),FALSE)/VLOOKUP(EOMONTH($A10,-1),Prices_Monthly!$A:$L,COLUMN(L$4),FALSE)-1 -> 0.087608661 | M10: =(0.6*L10)+(0.4*K10) -> 0.063047272
A11: 33054 | B11: =VLOOKUP($A11,Prices_Monthly!$A:$I,COLUMN(B$4),FALSE)/VLOOKUP(EOMONTH($A11,-1),Prices_Monthly!$A:$I,COLUMN(B$4),FALSE)-1 -> #VALUE! | C11: =VLOOKUP($A11,Prices_Monthly!$A:$I,COLUMN(C$4),FALSE)/VLOOKUP(EOMONTH($A11,-1),Prices_Monthly!$A:$I,COLUMN(C$4),FALSE)-1 -> -0.023603576 | D11: =VLOOKUP($A11,Prices_Monthly!$A:$I,COLUMN(D$4),FALSE)/VLOOKUP(EOMONTH($A11,-1),Prices_Monthly!$A:$I,COLUMN(D$4),FALSE)-1 -> -0.022499647 | E11: =VLOOKUP($A11,Prices_Monthly!$A:$I,COLUMN(E$4),FALSE)/VLOOKUP(EOMONTH($A11,-1),Prices_Monthly!$A:$I,COLUMN(E$4),FALSE)-1 -> 0.011729966 | F11: =VLOOKUP($A11,Prices_Monthly!$A:$I,COLUMN(F$4),FALSE)/VLOOKUP(EOMONTH($A11,-1),Prices_Monthly!$A:$I,COLUMN(F$4),FALSE)-1 -> #VALUE! | G11: =VLOOKUP($A11,Prices_Monthly!$A:$I,COLUMN(G$4),FALSE)/VLOOKUP(EOMONTH($A11,-1),Prices_Monthly!$A:$I,COLUMN(G$4),FALSE)-1 -> #VALUE! | H11: =VLOOKUP($A11,Prices_Monthly!$A:$I,COLUMN(H$4),FALSE)/VLOOKUP(EOMONTH($A11,-1),Prices_Monthly!$A:$I,COLUMN(H$4),FALSE)-1 -> #VALUE! | I11: =VLOOKUP($A11,Prices_Monthly!$A:$I,COLUMN(I$4),FALSE)/VLOOKUP(EOMONTH($A11,-1),Prices_Monthly!$A:$I,COLUMN(I$4),FALSE)-1 -> #VALUE! | K11: =VLOOKUP($A11,Prices_Monthly!$A:$L,COLUMN(K$4),FALSE)/VLOOKUP(EOMONTH($A11,-1),Prices_Monthly!$A:$L,COLUMN(K$4),FALSE)-1 -> 0.011055576 | L11: =VLOOKUP($A11,Prices_Monthly!$A:$L,COLUMN(L$4),FALSE)/VLOOKUP(EOMONTH($A11,-1),Prices_Monthly!$A:$L,COLUMN(L$4),FALSE)-1 -> -0.016285287 | M11: =(0.6*L11)+(0.4*K11) -> -0.0053489418
A12: 33085 | B12: =VLOOKUP($A12,Prices_Monthly!$A:$I,COLUMN(B$4),FALSE)/VLOOKUP(EOMONTH($A12,-1),Prices_Monthly!$A:$I,COLUMN(B$4),FALSE)-1 -> #VALUE! | C12: =VLOOKUP($A12,Prices_Monthly!$A:$I,COLUMN(C$4),FALSE)/VLOOKUP(EOMONTH($A12,-1),Prices_Monthly!$A:$I,COLUMN(C$4),FALSE)-1 -> 0.028753387 | D12: =VLOOKUP($A12,Prices_Monthly!$A:$I,COLUMN(D$4),FALSE)/VLOOKUP(EOMONTH($A12,-1),Prices_Monthly!$A:$I,COLUMN(D$4),FALSE)-1 -> -0.013314566 | E12: =VLOOKUP($A12,Prices_Monthly!$A:$I,COLUMN(E$4),FALSE)/VLOOKUP(EOMONTH($A12,-1),Prices_Monthly!$A:$I,COLUMN(E$4),FALSE)-1 -> 0.0054752974 | F12: =VLOOKUP($A12,Prices_Monthly!$A:$I,COLUMN(F$4),FALSE)/VLOOKUP(EOMONTH($A12,-1),Prices_Monthly!$A:$I,COLUMN(F$4),FALSE)-1 -> #VALUE! | G12: =VLOOKUP($A12,Prices_Monthly!$A:$I,COLUMN(G$4),FALSE)/VLOOKUP(EOMONTH($A12,-1),Prices_Monthly!$A:$I,COLUMN(G$4),FALSE)-1 -> #VALUE! | H12: =VLOOKUP($A12,Prices_Monthly!$A:$I,COLUMN(H$4),FALSE)/VLOOKUP(EOMONTH($A12,-1),Prices_Monthly!$A:$I,COLUMN(H$4),FALSE)-1 -> #VALUE! | I12: =VLOOKUP($A12,Prices_Monthly!$A:$I,COLUMN(I$4),FALSE)/VLOOKUP(EOMONTH($A12,-1),Prices_Monthly!$A:$I,COLUMN(I$4),FALSE)-1 -> #VALUE! | K12: =VLOOKUP($A12,Prices_Monthly!$A:$L,COLUMN(K$4),FALSE)/VLOOKUP(EOMONTH($A12,-1),Prices_Monthly!$A:$L,COLUMN(K$4),FALSE)-1 -> 0.0091225717 | L12: =VLOOKUP($A12,Prices_Monthly!$A:$L,COLUMN(L$4),FALSE)/VLOOKUP(EOMONTH($A12,-1),Prices_Monthly!$A:$L,COLUMN(L$4),FALSE)-1 -> -0.017116254 | M12: =(0.6*L12)+(0.4*K12) -> -0.0066207237
A13: 33116 | B13: =VLOOKUP($A13,Prices_Monthly!$A:$I,COLUMN(B$4),FALSE)/VLOOKUP(EOMONTH($A13,-1),Prices_Monthly!$A:$I,COLUMN(B$4),FALSE)-1 -> #VALUE! | C13: =VLOOKUP($A13,Prices_Monthly!$A:$I,COLUMN(C$4),FALSE)/VLOOKUP(EOMONTH($A13,-1),Prices_Monthly!$A:$I,COLUMN(C$4),FALSE)-1 -> 0.026371991 | D13: =VLOOKUP($A13,Prices_Monthly!$A:$I,COLUMN(D$4),FALSE)/VLOOKUP(EOMONTH($A13,-1),Prices_Monthly!$A:$I,COLUMN(D$4),FALSE)-1 -> -0.035086146 | E13: =VLOOKUP($A13,Prices_Monthly!$A:$I,COLUMN(E$4),FALSE)/VLOOKUP(EOMONTH($A13,-1),Prices_Monthly!$A:$I,COLUMN(E$4),FALSE)-1 -> -0.031066037 | F13: =VLOOKUP($A13,Prices_Monthly!$A:$I,COLUMN(F$4),FALSE)/VLOOKUP(EOMONTH($A13,-1),Prices_Monthly!$A:$I,COLUMN(F$4),FALSE)-1 -> #VALUE! | G13: =VLOOKUP($A13,Prices_Monthly!$A:$I,COLUMN(G$4),FALSE)/VLOOKUP(EOMONTH($A13,-1),Prices_Monthly!$A:$I,COLUMN(G$4),FALSE)-1 -> #VALUE! | H13: =VLOOKUP($A13,Prices_Monthly!$A:$I,COLUMN(H$4),FALSE)/VLOOKUP(EOMONTH($A13,-1),Prices_Monthly!$A:$I,COLUMN(H$4),FALSE)-1 -> #VALUE! | I13: =VLOOKUP($A13,Prices_Monthly!$A:$I,COLUMN(I$4),FALSE)/VLOOKUP(EOMONTH($A13,-1),Prices_Monthly!$A:$I,COLUMN(I$4),FALSE)-1 -> #VALUE! | K13: =VLOOKUP($A13,Prices_Monthly!$A:$L,COLUMN(K$4),FALSE)/VLOOKUP(EOMONTH($A13,-1),Prices_Monthly!$A:$L,COLUMN(K$4),FALSE)-1 -> -0.013245302 | L13: =VLOOKUP($A13,Prices_Monthly!$A:$L,COLUMN(L$4),FALSE)/VLOOKUP(EOMONTH($A13,-1),Prices_Monthly!$A:$L,COLUMN(L$4),FALSE)-1 -> -0.10317752 | M13: =(0.6*L13)+(0.4*K13) -> -0.067204635
A14: 33146 | B14: =VLOOKUP($A14,Prices_Monthly!$A:$I,COLUMN(B$4),FALSE)/VLOOKUP(EOMONTH($A14,-1),Prices_Monthly!$A:$I,COLUMN(B$4),FALSE)-1 -> #VALUE! | C14: =VLOOKUP($A14,Prices_Monthly!$A:$I,COLUMN(C$4),FALSE)/VLOOKUP(EOMONTH($A14,-1),Prices_Monthly!$A:$I,COLUMN(C$4),FALSE)-1 -> 0.048560892 | D14: =VLOOKUP($A14,Prices_Monthly!$A:$I,COLUMN(D$4),FALSE)/VLOOKUP(EOMONTH($A14,-1),Prices_Monthly!$A:$I,COLUMN(D$4),FALSE)-1 -> -0.027939493 | E14: =VLOOKUP($A14,Prices_Monthly!$A:$I,COLUMN(E$4),FALSE)/VLOOKUP(EOMONTH($A14,-1),Prices_Monthly!$A:$I,COLUMN(E$4),FALSE)-1 -> 0.0029809975 | F14: =VLOOKUP($A14,Prices_Monthly!$A:$I,COLUMN(F$4),FALSE)/VLOOKUP(EOMONTH($A14,-1),Prices_Monthly!$A:$I,COLUMN(F$4),FALSE)-1 -> #VALUE! | G14: =VLOOKUP($A14,Prices_Monthly!$A:$I,COLUMN(G$4),FALSE)/VLOOKUP(EOMONTH($A14,-1),Prices_Monthly!$A:$I,COLUMN(G$4),FALSE)-1 -> #VALUE! | H14: =VLOOKUP($A14,Prices_Monthly!$A:$I,COLUMN(H$4),FALSE)/VLOOKUP(EOMONTH($A14,-1),Prices_Monthly!$A:$I,COLUMN(H$4),FALSE)-1 -> #VALUE! | I14: =VLOOKUP($A14,Prices_Monthly!$A:$I,COLUMN(I$4),FALSE)/VLOOKUP(EOMONTH($A14,-1),Prices_Monthly!$A:$I,COLUMN(I$4),FALSE)-1 -> #VALUE! | K14: =VLOOKUP($A14,Prices_Monthly!$A:$L,COLUMN(K$4),FALSE)/VLOOKUP(EOMONTH($A14,-1),Prices_Monthly!$A:$L,COLUMN(K$4),FALSE)-1 -> 0.0031920318 | L14: =VLOOKUP($A14,Prices_Monthly!$A:$L,COLUMN(L$4),FALSE)/VLOOKUP(EOMONTH($A14,-1),Prices_Monthly!$A:$L,COLUMN(L$4),FALSE)-1 -> -0.11687576 | M14: =(0.6*L14)+(0.4*K14) -> -0.068848644
A15: 33177 | B15: =VLOOKUP($A15,Prices_Monthly!$A:$I,COLUMN(B$4),FALSE)/VLOOKUP(EOMONTH($A15,-1),Prices_Monthly!$A:$I,COLUMN(B$4),FALSE)-1 -> #VALUE! | C15: =VLOOKUP($A15,Prices_Monthly!$A:$I,COLUMN(C$4),FALSE)/VLOOKUP(EOMONTH($A15,-1),Prices_Monthly!$A:$I,COLUMN(C$4),FALSE)-1 -> -0.065670437 | D15: =VLOOKUP($A15,Prices_Monthly!$A:$I,COLUMN(D$4),FALSE)/VLOOKUP(EOMONTH($A15,-1),Prices_Monthly!$A:$I,COLUMN(D$4),FALSE)-1 -> 0.049250359 | E15: =VLOOKUP($A15,Prices_Monthly!$A:$I,COLUMN(E$4),FALSE)/VLOOKUP(EOMONTH($A15,-1),Prices_Monthly!$A:$I,COLUMN(E$4),FALSE)-1 -> 0.011889781 | F15: =VLOOKUP($A15,Prices_Monthly!$A:$I,COLUMN(F$4),FALSE)/VLOOKUP(EOMONTH($A15,-1),Prices_Monthly!$A:$I,COLUMN(F$4),FALSE)-1 -> #VALUE! | G15: =VLOOKUP($A15,Prices_Monthly!$A:$I,COLUMN(G$4),FALSE)/VLOOKUP(EOMONTH($A15,-1),Prices_Monthly!$A:$I,COLUMN(G$4),FALSE)-1 -> #VALUE! | H15: =VLOOKUP($A15,Prices_Monthly!$A:$I,COLUMN(H$4),FALSE)/VLOOKUP(EOMONTH($A15,-1),Prices_Monthly!$A:$I,COLUMN(H$4),FALSE)-1 -> #VALUE! | I15: =VLOOKUP($A15,Prices_Monthly!$A:$I,COLUMN(I$4),FALSE)/VLOOKUP(EOMONTH($A15,-1),Prices_Monthly!$A:$I,COLUMN(I$4),FALSE)-1 -> #VALUE! | K15: =VLOOKUP($A15,Prices_Monthly!$A:$L,COLUMN(K$4),FALSE)/VLOOKUP(EOMONTH($A15,-1),Prices_Monthly!$A:$L,COLUMN(K$4),FALSE)-1 -> 0.022918562 | L15: =VLOOKUP($A15,Prices_Monthly!$A:$L,COLUMN(L$4),FALSE)/VLOOKUP(EOMONTH($A15,-1),Prices_Monthly!$A:$L,COLUMN(L$4),FALSE)-1 -> 0.064036958 | M15: =(0.6*L15)+(0.4*K15) -> 0.0475896
